Workbook
Name AnalysisTerm: 'Initial Screens'!$C$14
Name Growth: 'ROI Results'!$I$8
Name Hardware_Refreshcylce: 'ROI Results'!$F$53
Name Hosts: 'Initial Screens'!$C$17
Name Inflation: 'ROI Results'!$I$9
Name VMs: 'Initial Screens'!$C$16

Sheet Initial Screens
B2: Private Cloud Maturity & Optimization (PCMO) Tool | E2: any values in yellow input cells for illustration only | G2: Cell Color Legend
B3: Layout should be aligned with PCMO | G3: Input | I3: must be input
G4: Overridable default | I4: Can be edited
B5: PCMO Get Started Screen | G5: Data pull | I5: Can't be edited
G6: Calculation | I6: Can't be edited
B7: Customer Name | C7: Acme Company | G7: Data ingestion or overridable default | I7: Can't be edited if data ingested from collector tool (RV Tools, Live Optics)
B8: Analysis Data Industry | C8: Financial Services | D8: <-- Note to Mediafly: Default should be blank | G8: red notes | H8: comments for MediaFly or internal
B9: Analysis Data Region | C9: AMER | D9: <-- Note to Mediafly: Default should be blank
B11: Value Model Configuration | D11: <-- This "screen" follows when Value Model is included
B13: Future state solution | C13: VCF 9
B14: Term of analysis | C14: 10
B16: Number of VMs | C16: 5000
B17: Number of VM Hosts | C17: 400
B18: Average allocated/provisioned storage (GBs) per VM | C18: 300 | H18: vSAN storage = VMs x avg allocated GBs per VM
G19: Traditional storage only used for TCO Assessment
B20: Component Usage | C20: Current State | D20: Future State
B21: % of Operations coverage | C21: 0 | D21: 1
A22: =IF(ISNUMBER(SEARCH("VCF",$C$13)),"Show","Hide") -> Show | B22: % of Automation coverage | C22: 0 | D22: =IF(A22="Show",100%,0) -> 1
A23: =$A$22 -> Show | B23: % Of NSX coverage | C23: 0 | D23: 1
A24: =IF($C$13="VVF","Hide","Show") -> Show | B24: % of vSAN Coverage | C24: 0 | D24: 1
B26: Select Advanced Services: | C26: Avi Load Balancer | D26: No
A27: =$A$22 -> Show | C27: vDefend Distributed Firewall | D27: No
C28: Data Services Manager (DSM) | D28: No | E28: =IF(D28="Yes","","Must include DSM for any Public Native Cloud comparison") -> Must include DSM for any Public Native Cloud comparison
C29: VMware Live Recovery (VLR) | D29: No

Sheet Notes
B2: For MediaFly
B4: Cell Color Legend
B5: Input | D5: must be input
B6: Overridable default | D6: Can be edited
B7: Data pull | D7: Can't be edited
B8: Calculation | D8: Can't be edited
B9: red notes | C9: comments for MediaFly or internal
B12: Internal
B14: V2.5 Items
A15: x | B15: VLR simplified
A16: x | B16: Custom Benefits for Software Cost Savings and Labor Productivity
A17: x | B17: VVF jump start
A18: x | B18: add P2V
A19: x | B19: Sustainability
A20: x | B20: Growth & Inflation
B21: Past Value Analysis - see separate workbook
B23: Time permitting
B24: Rounding
B25: Fully Q&A for consistency & errors

Sheet Excel Output
B2: TCO & ROI Analysis Workbook | I2: Cell Color Legend
I3: Overridable default | K3: Can be edited
B4: Customer | C4: ='Initial Screens'!C7 -> Acme Company | I4: Data pull | K4: Generally should not be edited
B5: Date | C5: =NOW() -> 45982.798 | H5: Date of download | I5: Calculation | K5: Shouldn't be edited
B6: Term of Analysis | C6: =AnalysisTerm&"-Year Term" -> 10-Year Term
B7: VMware Solution | C7: Vmware Cloud Foundation
B9: Workbook Contents
B10: Intro
B11: This workbook provides value analysis output for transparency of math regarding data used and assumptions made for estimating the financial value of moving to VCF.
B12: Analysis Tabs
B13: Tabs include the ablity to create bottoms up calculations for current state and future state costs related to Compute, Storage, Network, Software, Labor, Migration, and Reskilling.
B14: In addition Business Impact in the form of profits related to increased or protected revenue and risk reduction based on reduced downtime and security incidents can be assessed.
B15: Results Tab
B16: ROI Summary - provides key financial metrics and a summary of multi-year benefit and investment calculations, based on the benefits analyzed and assumed value realization assumptions.
B18: Some Data Used
B19: Initial data inputs
B20: ='Initial Screens'!B14 -> Term of analysis | D20: =AnalysisTerm -> 10
B22: ='Initial Screens'!B16 -> Number of VMs | D22: ='Initial Screens'!C16 -> 5000 | H22: for Excel output, these values should drive the rest of the output sheets
B23: ='Initial Screens'!B17 -> Number of VM Hosts | D23: ='Initial Screens'!C17 -> 400 | H23: for Excel output, these values should drive the rest of the output sheets
B24: ='Initial Screens'!B18 -> Average allocated/provisioned storage (GBs) per VM | D24: ='Initial Screens'!C18 -> 300 | H24: for Excel output, these values should drive the rest of the output sheets
B26: ='Initial Screens'!B20 -> Component Usage | D26: ='Initial Screens'!C20 -> Current State | E26: ='Initial Screens'!D20 -> Future State
B27: ='Initial Screens'!B21 -> % of Operations coverage | D27: ='Initial Screens'!C21 -> 0 | E27: ='Initial Screens'!D21 -> 1 | H27: for Excel output, these values should drive the rest of the output sheets
A28: ='Initial Screens'!$A$22 -> Show | B28: ='Initial Screens'!B22 -> % of Automation coverage | D28: ='Initial Screens'!C22 -> 0 | E28: =IF(A28="Hide",D28,'Initial Screens'!D22) -> 1 | H28: for Excel output, these values should drive the rest of the output sheets
A29: ='Initial Screens'!$A$22 -> Show | B29: ='Initial Screens'!B23 -> % Of NSX coverage | D29: ='Initial Screens'!C23 -> 0 | E29: =IF(A29="Hide",D29,'Initial Screens'!D23) -> 1 | H29: for Excel output, these values should drive the rest of the output sheets
A30: =IF('Initial Screens'!$C$13="VVF","Hide","Show") -> Show | B30: ='Initial Screens'!B24 -> % of vSAN Coverage | D30: ='Initial Screens'!C24 -> 0 | E30: =IF(A30="Hide",D30,'Initial Screens'!D24) -> 1 | H30: for Excel output, these values should drive the rest of the output sheets
B32: TCO Results Overview
B34: CURRENT STATE | E34: FUTURE STATE
B35: Products | C35: ="vSphere"&IF('Excel Output'!D27>0,", VCF Operations","")&IF('Excel Output'!D28>0,", VCF Automation","")&IF('Excel Output'!D29>0,", NSX","")&IF('Excel Output'!D30>0,", vSAN","") -> vSphere | E35: Products | F35: =IF('Initial Screens'!C13="VCF","VMware Cloud Foundation"&IF('Initial Screens'!D26="Yes",", Avi Load Balancer","")&IF('Initial Screens'!D27="yes",", vDefend Firewall","")&IF('Initial Screens'!D28="yes",", Data Services Manager","")&IF('Initial Screens'!D29="yes",", VMware Live Recovery",""),IF('Initial Screens'!C13="VVF","VMware vSphere Foundation","VMware vSphere Foundation, vSAN")) -> VMware vSphere Foundation, vSAN
B36: Host Architecture | C36: =FIXED(Compute!D40,0)&" CPUs, "&FIXED(Compute!D41,0)&" Cores, "&FIXED(Compute!D42,0)&" GB RAM per Host" -> 2 CPUs, 36 Cores, 768 GB RAM per Host | E36: Host Architecture | F36: =FIXED(Compute!F40,0)&" CPUs, "&FIXED(Compute!F41,0)&" Cores, "&FIXED(Compute!F42,0)&" GB RAM per Host" -> 2 CPUs, 48 Cores, 1,024 GB RAM per Host
B37: License Type | C37: SnS related to perpetual or subscription | E37: License Type | F37: Subscription
B39: ='Initial Screens'!C14&" Year Total TCO" -> 10 Year Total TCO | C39: =SUM(C45:C53) -> 2.1468287e+08 | E39: =B39 -> 10 Year Total TCO | F39: =SUM(F45:F53) -> 1.2261756e+08
E40: $ Savings over Current | F40: =C39-F39 -> 92065311
E41: % Savings over Current | F41: =F40/C39 -> 0.42884331
E42: % ROI over Current | F42: ='ROI Results'!E9 -> 9.75
B44: Cost Categories | E44: =FIXED(D20,0)&"-Year VCF Migration and Adoption Future State" -> 10-Year VCF Migration and Adoption Future State
B45: Compute | C45: ='ROI Results'!O71 -> 61914772 | D45: worksheet | E45: Compute | F45: ='ROI Results'!O85 -> 27627724
B46: Storage | C46: ='ROI Results'!O72 -> 25461120 | D46: worksheet | E46: Storage | F46: ='ROI Results'!O86 -> 9458613.3
B47: Network | C47: ='ROI Results'!O73 -> 6166095.6 | D47: worksheet | E47: Network | F47: ='ROI Results'!O87 -> 2743020.3
B48: Software | C48: ='ROI Results'!O74 -> 6288946.3 | D48: worksheet | E48: Software | F48: ='ROI Results'!O88 -> 8881408
B49: Facilities | C49: ='ROI Results'!O75 -> 37336277 | D49: worksheet | E49: Facilities | F49: ='ROI Results'!O89 -> 21605405
B50: Labor | C50: ='ROI Results'!O76 -> 68936136 | D50: worksheet | E50: Labor | F50: ='ROI Results'!O90 -> 48893379
B51: Support | C51: ='ROI Results'!O77 -> 1250000 | D51: worksheet | E51: Support | F51: ='ROI Results'!O91 -> 1375000
B52: Migration | C52: ='ROI Results'!O78 -> 7290521.4 | D52: worksheet | E52: Migration | F52: ='ROI Results'!O92 -> 1877008.8
B53: Reskilling | C53: ='ROI Results'!O79 -> 39000 | D53: worksheet | E53: Reskilling | F53: ='ROI Results'!O93 -> 156000
B55: Additional Information
B57: This workbook is an output of the VMware Value Modeler. Although great care has been and will be taken to ensure the accuracy and completeness of this model. VMware will be unable to accept any legal responsibility for any actions taken based on the information contained herein and VMware makes no warranties of any kind.

Sheet Compute
B2: Current State Compute Costs & Anticipated Reduction | G2: Return button
B4: Current State | H4: Sourcing & Comments
B5: Number of VMs | F5: ='Excel Output'!D22 -> 5000
B6: Number of VM Hosts | F6: ='Excel Output'!$D$23 -> 400
B7: VMs/Host | F7: =F5/F6 -> 12.5 | H7: Calculation
A8: =IF('Initial Screens'!$C$13="VVF","Hide","Show") -> Show | B8: Percent of Hosts that are vSAN ready nodes | F8: =IF('Initial Screens'!C13="VVF",0,'Excel Output'!D30) -> 0
A9: =IF($F$8=100%,"Hide","Show") -> Show | B9: Average purchase cost per current state ESXi host | F9: =IF(F8=1,0,25000) -> 25000 | H9: Placeholder default
A10: =IF($F$8=0,"Hide","Show") -> Hide | B10: Average purchase cost per current state vSAN ready node | F10: =IF(F8>0,35000,0) -> 0 | H10: Placeholder default
B11: Annual compute hardware support | F11: 0.15 | H11: Placeholder default
B12: =FIXED(AnalysisTerm,0)&"-Year Current State Cost" -> 10-Year Current State Cost | F12: =(ROUND(F6*(1-F8),0)*F9+ROUND(F6*F8,0)*F10)*(1+AnalysisTerm*F11) -> 25000000 | H12: Calculation
B13: Future State
B14: Percent of VMs to be decommissioned (including reduction via containerization of applications) | F14: =IF('Excel Output'!E28>'Excel Output'!D28,10%,5%) -> 0.1 | H14: Conservative default estimate; The Forrester Total Economic Impact™ Of VMware vRealize Automation (2019) indicated as high as 50% per year
B15: Number of VMs on premises | F15: =ROUND(F$5*(1-F$14),0) -> 4500 | H15: Calculation
A16: =IF('Initial Screens'!$C$13="VVF","Hide","Show") -> Show | B16: Percent of Hosts that will be vSAN ready nodes | F16: ='Excel Output'!E30 -> 1 | H16: From Inputs | P16: OLD | Q16: OLD | R16: NEW | S16: NEW
B17: =IF('Initial Screens'!$C$13="VVF","Number of VM Hosts","Number of VM Hosts (vSAN Ready Nodes and ESXi Hosts)") -> Number of VM Hosts (vSAN Ready Nodes and ESXi Hosts) | F17: =F46 -> 143 | H17: From worksheet below | M17: Component Usage | N17: Current State | O17: Future State | P17: CPU Utilization | Q17: RAM Utilization | R17: CPU Utilization | S17: RAM Utilization
B18: VMs/Host | F18: =F15/F17 -> 31.468531 | H18: Calculation | L18: Scenario 1 | M18: % of Operations coverage | N18: 0 | O18: 1 | P18: 0.3 | Q18: 0.45873786 | R18: 0.35 | S18: 0.45873786
A19: =IF($F$16=0%,"Hide","Show") -> Show | B19: Number of vSAN Ready Nodes | F19: =ROUND(F16*F17,0) -> 143 | G19: Worksheet | H19: Calculation | L19: Scenario 1 | M19: % of Automation coverage | N19: 0 | O19: 1
A20: =IF($F$16=100%,"Hide","Show") -> Hide | B20: Number of ESXi Hosts | F20: =ROUND(F17*(1-F16),0) -> 0 | G20: Worksheet | H20: Calculation | L20: Scenario 1 | M20: % Of NSX coverage | N20: 0 | O20: 1
A21: =IF($F$16=0%,"Hide","Show") -> Show | B21: Average compute cost (excludes storage component) per vSAN Ready Node | F21: =IF(F16=0,0,C65) -> 25000 | G21: Worksheet | H21: Calculation below | L21: Scenario 1 | M21: % of vSAN Coverage | N21: 0 | O21: 1
A22: =IF($F$16=100%,"Hide","Show") -> Hide | B22: Average purchase cost per host (ESXi Hosts) | F22: =IF(F16=1,0,F9) -> 0 | H22: Pull from above | L22: Scenario 2 | M22: % of Operations coverage | N22: 0 | O22: 1 | P22: 0.3 | Q22: 0.40909091 | R22: 0.3125 | S22: 0.40909091
B23: Annual compute hardware support | F23: 0.15 | H23: Placeholder estimate | L23: Scenario 2 | M23: % of Automation coverage | N23: 0 | O23: 1
B24: =FIXED(AnalysisTerm,0)&"-Year Future State Cost" -> 10-Year Future State Cost | F24: =ROUND(F19*F21+F20*F22,0)*(1+AnalysisTerm*F23) -> 8937500 | H24: Calculation | L24: Scenario 2 | M24: % Of NSX coverage | N24: 0.5 | O24: 1
L25: Scenario 2 | M25: % of vSAN Coverage | N25: 0 | O25: 1
B26: Target VM Host Sizing | L26: Scenario 3 | M26: % of Operations coverage | N26: 0.5 | O26: 1 | P26: 0.3125 | Q26: 0.40909091 | R26: 0.3 | S26: 0.40909091
A28: =IF('Initial Screens'!C13="VCF 9","Show","hide") -> Show | B28: Include Memory Tiering benefits | D28: =IF(A28="show","Yes","No") -> Yes | H28: Advanced Memory Management and Scheduling, with DPM :VCF delivers better resource management through its memory overcommitment and memory oversubscription features leading to improved host consolidation
A29: =IF(D28="No","hide","show") -> show | B29: Anticipated percentage improvement in CPU overcommit (vCPU:pCPU) due to additional Memory capacity | D29: =IF(D28="Yes",20%,0%) -> 0.2
A30: =$A$29 -> show | B30: Anticipated percentage improvement in Memory overcommit | D30: =IF(D28="Yes",5%,0%) -> 0.05 | G30: =(50%-D43)/(2+IF('Excel Output'!E27=0,2,0)+IF('Excel Output'!E29=0,2,0))*SUM(Misc!E136,Misc!E138)/2 -> 0.15
G31: =G30*(1+D29) -> 0.18 | L31: Scenario 3 | M31: % of Automation coverage | N31: 0.5 | O31: 1
B32: VM Profile | D32: Current State | F32: Future State | H32: Sourcing and Comments | L32: Scenario 3 | M32: % Of NSX coverage | N32: 0 | O32: 1
B33: Number of VMs (on premises) | D33: =F5 -> 5000 | F33: =F15 -> 4500 | H33: =H5 -> 0 | L33: Scenario 3 | M33: % of vSAN Coverage | N33: 0 | O33: 1
B34: Total Storage requirement per VM(GB) | D34: ='Excel Output'!D24 -> 300 | F34: =D34 -> 300 | H34: ='Initial Screens'!$E$18 -> 0 | L34: Scenario 4 | M34: % of Operations coverage | N34: 0.5 | O34: 1 | P34: 0.3 | Q34: 0.40909091 | R34: 0.3125 | S34: 0.40909091
B35: vCPUs per VM | D35: 2 | F35: =D35 -> 2 | H35: Placeholder default | J35: Pull current state from Data Ingestion when used | L35: Scenario 4 | M35: % of Automation coverage | N35: 0 | O35: 1
B36: GB RAM per VM | D36: 4 | F36: =D36 -> 4 | H36: Placeholder default | J36: Pull current state from Data Ingestion when used | L36: Scenario 4 | M36: % Of NSX coverage | N36: 0 | O36: 1
B37: vCPU to core ratio | D37: 4 | F37: =D37 -> 4 | H37: Placeholder default | J37: Pull current state from Data Ingestion when used | L37: Scenario 4 | M37: % of vSAN Coverage | N37: 0 | O37: 1
B38: On Premises VM Host Profile | L38: Scenario 4 | M38: % of Operations coverage | N38: 0 | O38: 1 | P38: 0.3 | Q38: 0.45873786 | R38: 0.35 | S38: 0.45873786
B39: Number of Hosts | D39: =F6 -> 400 | H39: ='Initial Screens'!$E$17 -> 0 | L39: Scenario 4 | M39: % of Automation coverage | N39: 0.5 | O39: 1
B40: CPUs (Sockets) per host | D40: =ROUND(2,0) -> 2 | F40: 2 | G40: =48-F41 -> 0 | H40: Placeholder default | L40: Scenario 4 | M40: % Of NSX coverage | N40: 0 | O40: 1
B41: Total Cores per Host | D41: 36 | F41: =IF('Initial Screens'!$C$13="VCF",MAX(48,D41),D41)+12 -> 48 | H41: Placeholder default | J41: Pull current state from Data Ingestion when used | L41: Scenario 4 | M41: % of vSAN Coverage | N41: 0 | O41: 1
B42: RAM (GB)/host server | D42: =ROUND(768,0) -> 768 | F42: =IF(ISNUMBER(SEARCH("VCF",'Initial Screens'!$C$13)),MAX(1024,D42),D42) -> 1024 | H42: Placeholder default | J42: Pull current state from Data Ingestion when used
B43: CPU Utilization | D43: 0.2 | F43: =IF(ISNUMBER(SEARCH("VCF",'Initial Screens'!$C$13)),D43+(50%-D43)/(2+IF('Excel Output'!E27=0,2,0)+IF('Excel Output'!E29=0,2,0))*SUM(Misc!E136,Misc!E138)/2*(1+D29),D43+1%) -> 0.38 | H43: Placeholder default | J43: Pull current state from Data Ingestion when used
B44: RAM Utilization | D44: 0.35 | F44: =D44*D42*D39*(1-F14)/F17/F42*(1+D30) -> 0.69388112 | G44: =IF(F44>80%,"Decrease CPU Utilization","") | H44: Placeholder default | J44: Pull current state from Data Ingestion when used
G45: ^^ see error note here ^^
B46: Total Future State Host Count | F46: =ROUNDUP(F33/(D33/D39*F41/D41*F43/D43),0) -> 143 | H46: Calculation
B47: Est. % on prem host reduction | F47: =(D39-F46)/D39 -> 0.6425 | H47: Calculation
A49: =IF('Initial Screens'!$C$13="VVF","Hide","Show") -> Show | B49: Target Host Configuration and Cost
A50: =IF('Initial Screens'!$C$13="VVF","Hide","Show") -> Show | B50: Note: Capacity Disks to be costed in the storage cost worksheet
A51: =IF('Initial Screens'!$C$13="VVF","Hide","Show") -> Show
A52: =IF('Initial Screens'!$C$13="VVF","Hide","Show") -> Show | B52: Host Configuration (Core Components) | C52: Non-vSAN/vSAN Ready Nodes | D52: Qty Per host | E52: Qty Unit | F52: Net Cost Per unit | H52: Sourcing and Comments
A53: =IF('Initial Screens'!$C$13="VVF","Hide","Show") -> Show | B53: CPUs (Sockets) | C53: =F40 -> 2 | D53: =F40 -> 2 | E53: n/a | F53: 5000 | H53: Placeholder estimate
A54: =IF('Initial Screens'!$C$13="VVF","Hide","Show") -> Show | B54: GB RAM | C54: =F42 -> 1024 | D54: =ROUND(C54/64,0) -> 16 | E54: 64 GB RAM | F54: 575 | H54: Placeholder estimate
A55: =IF('Initial Screens'!$C$13="VVF","Hide","Show") -> Show | B55: Disk (GB) | C55: 2000 | D55: 1 | E55: =FIXED(C55,0)&" GB Disk" -> 2,000 GB Disk | F55: =ROUND(C55*0.3,0) -> 600 | H55: Capacity SATA 7.2K RPM (TB), $/GB=0.26
A56: =IF('Initial Screens'!$C$13="VVF","Hide","Show") -> Show
A57: =IF('Initial Screens'!$C$13="VVF","Hide","Show") -> Show
A58: =IF('Initial Screens'!$C$13="VVF","Hide","Show") -> Show | B58: Additional Components
A59: =IF('Initial Screens'!$C$13="VVF","Hide","Show") -> Show | B59: Peripherals (SFPs, Cables, Adapters, SAS/SATA Controllers, Cage, etc.) | D59: =ROUND(1,0) -> 1 | E59: set | F59: 4600 | H59: Placeholder Estimate
A60: =IF('Initial Screens'!$C$13="VVF","Hide","Show") -> Show | B60: Power Supply (W) | D60: =ROUND(1,0) -> 1 | E60: power supply | F60: 600 | H60: Placeholder Estimate
A61: =IF('Initial Screens'!$C$13="VVF","Hide","Show") -> Show | B61: Others | D61: =ROUND(0,0) -> 0 | F61: 0 | H61: Enter other costs if any
A62: =IF('Initial Screens'!$C$13="VVF","Hide","Show") -> Show
A63: =IF('Initial Screens'!$C$13="VVF","Hide","Show") -> Show | B63: Total Cost | C63: =SUMPRODUCT(D53:D55,F53:F55)+SUMPRODUCT(D59:D61,F59:F61) -> 25000 | H63: Calculation
A64: =IF('Initial Screens'!$C$13="VVF","Hide","Show") -> Show | B64: Discount | C64: 0 | H64: Placeholder Estimate
A65: =IF('Initial Screens'!$C$13="VVF","Hide","Show") -> Show | B65: Net Cost | C65: =ROUNDUP(C63*(1-C64),0) -> 25000 | H65: Calculation
B68: Include Physical to Virtual (P2V) Benefit | D68: =IF(C68="",IF('Initial Screens'!C13="VCF","No","Yes"),C68) -> Yes | H68: Don't use if Government or non-profit
B70: Reduced Physical Server Hardware
B72: Current State | H72: Sourcing & Comments
B73: Number of Physical legacy servers (that can be virtualized) | F73: 0 | G73: <-- for illustration only
B74: Average purchase cost to refresh a physical legacy server | F74: 5000 | H74: Placeholder default
B75: Annual physical legacy server hardware support | F75: 0.15 | H75: Placeholder default
B76: =FIXED(AnalysisTerm,0)&"-Year Current State Cost" -> 10-Year Current State Cost | F76: =IF(D68="Yes",F73*F74*(1+AnalysisTerm*F75),0) -> 0 | H76: Calculation
B77: Future State
B78: Resultant number of new VMs on premises | F78: =F73 -> 0 | H78: Default assumes 1:1 server:VM migration
B79: Consolidation Ratio (average VMs per host) | F79: =F18 -> 31.468531 | H79: Placeholder estimate
A80: =IF('Initial Screens'!$C$13="VVF","Hide","Show") -> Show | B80: % of vSAN Coverage | F80: =F16 -> 1 | H80: Placeholder estimate based on anticipated vSAN coverage
A81: =IF(OR($F$80=0%,'Initial Screens'!$C$13="VVF"),"Hide","Show") -> Show | B81: Number of vSAN Ready Nodes | F81: =ROUND(F78/F79*F80,0) -> 0 | H81: Calculation
B82: Number of ESXi Hosts | F82: =ROUND(F78/F79-F81,0) -> 0 | H82: Calculation
A83: =IF(OR($F$80=0%,'Initial Screens'!$C$13="VVF"),"Hide","Show") -> Show | B83: Average compute cost per vSAN Ready Node | F83: =F21 -> 25000 | H83: Assumes 2 CPU, 36 Cores 768 GB RAM hosts. This is the server compute cost, embedded storage cost is factored under storage costs
B84: Average purchase cost per ESXi host | F84: =F22 -> 0 | H84: Assumes 2 CPU, 36 Cores, 768 GB RAM
B85: Annual compute hardware support | F85: 0.15 | H85: Placeholder estimate
B86: =FIXED(AnalysisTerm,0)&"-Year Future State Cost" -> 10-Year Future State Cost | F86: =IF(D68="Yes",(F81*F83+F82*F84)*(1+AnalysisTerm*F85),0) -> 0 | H86: Calculation
A89: =IF('Initial Screens'!$D$29="Yes","Show","Hide") -> Hide | B89: Reduced Disaster Recovery HW (CapEx)
A90: =IF('Initial Screens'!$D$29="Yes","Show","Hide") -> Hide | B90: Current State | F90: Likely | H90: Sourcing & Comments
A91: =IF('Initial Screens'!$D$29="Yes","Show","Hide") -> Hide | B91: Current state compute refresh cost | F91: =(ROUND(F6*(1-F8),0)*F9+ROUND(F6*F8,0)*F10) -> 10000000 | H91: From Compute
A92: =IF('Initial Screens'!$D$29="Yes","Show","Hide") -> Hide | B92: Current state storage refresh cost | F92: =ROUND(Storage!F11*Storage!F12*Storage!F14+Storage!F11*(1-Storage!F12)*Storage!F13+Storage!F19,0) -> 4785714 | H92: From Storage
A93: =IF('Initial Screens'!$D$29="Yes","Show","Hide") -> Hide | B93: Current state network refresh cost | F93: =ROUND(Network!F5*Network!F6*Network!F8,0) -> 1000000 | H93: From Network
A94: =IF('Initial Screens'!$D$29="Yes","Show","Hide") -> Hide | B94: Percent of workloads (VMs) protected by current disaster recovery solution | F94: =IF('Initial Screens'!$D$29="Yes",80%,0) -> 0 | H94: Placeholder Estimate
A95: =IF('Initial Screens'!$D$29="Yes","Show","Hide") -> Hide | B95: Current disaster recovery cost as a percent of production cost? | F95: =ROUND(50%,3) -> 0.5 | H95: Placeholder Estimate
A96: =IF('Initial Screens'!$D$29="Yes","Show","Hide") -> Hide | B96: Estimated disaster recovery compute cost | F96: =F91*$F$94*$F$95 -> 0 | H96: Calculation - this is added to compute cost
A97: =IF('Initial Screens'!$D$29="Yes","Show","Hide") -> Hide | B97: Estimated disaster recovery storage cost | F97: =F92*$F$94*$F$95 -> 0 | H97: Calculation - this is added to storage costs
A98: =IF('Initial Screens'!$D$29="Yes","Show","Hide") -> Hide | B98: Estimated disaster recovery network cost (other network devices, not firewalls or load balancers) | F98: =F93*$F$94*$F$95 -> 0 | H98: Calculation - this is added to network costs
A99: =IF('Initial Screens'!$D$29="Yes","Show","Hide") -> Hide | B99: Annual disaster recovery hardware support | F99: 0.15 | H99: Placeholder default
A100: =IF('Initial Screens'!$D$29="Yes","Show","Hide") -> Hide | B100: =AnalysisTerm&"-Year Current State Cost - Compute" -> 10-Year Current State Cost - Compute | F100: =F96*(1+AnalysisTerm*$F$99) -> 0 | H100: Calculation
A101: =IF('Initial Screens'!$D$29="Yes","Show","Hide") -> Hide | B101: =AnalysisTerm&"-Year Current State Cost - Storage" -> 10-Year Current State Cost - Storage | F101: =F97*(1+AnalysisTerm*$F$99) -> 0 | H101: Calculation
A102: =IF('Initial Screens'!$D$29="Yes","Show","Hide") -> Hide | B102: =AnalysisTerm&"-Year Current State Cost - Network" -> 10-Year Current State Cost - Network | F102: =F98*(1+AnalysisTerm*$F$99) -> 0 | H102: Calculation
A103: =IF('Initial Screens'!$D$29="Yes","Show","Hide") -> Hide | B103: ="Total "&AnalysisTerm&"-Year Current State Cost" -> Total 10-Year Current State Cost | F103: =ROUND(SUM(F96:F98)*(1+AnalysisTerm*F99),0) -> 0 | H103: Calculation
A104: =IF('Initial Screens'!$D$29="Yes","Show","Hide") -> Hide | B104: Future State
A105: =IF('Initial Screens'!$D$29="Yes","Show","Hide") -> Hide | B105: Percent of workloads (VMs) to be protected by VMware Live Cyber Recovery (VLCR) | F105: =IF('Initial Screens'!$D$29="Yes",F94*50%,0) -> 0 | G105: =IF(SUM(F105:F106)>100%,"Sum of VLCR & VLSR protection is limited to 100%","") | H105: Placeholder Estimate
A106: =IF('Initial Screens'!$D$29="Yes","Show","Hide") -> Hide | B106: Percent of workloads (VMs) to be protected by VMware Live Site Recovery (VLSR) | F106: =IF('Initial Screens'!$D$29="Yes",F94*50%,0) -> 0 | H106: Placeholder Estimate
A107: =IF('Initial Screens'!$D$29="Yes","Show","Hide") -> Hide | B107: Anticipated percent reduction | F107: =IFERROR(ROUND(SUM(F105:F106)/F94*75%,3),0) -> 0 | G107: ^^ see error note here ^^ | H107: Placeholder Estimate
A108: =IF('Initial Screens'!$D$29="Yes","Show","Hide") -> Hide | B108: Estimated disaster recovery compute cost | F108: =IFERROR(MIN(SUM($F$105:$F$106)/$F$94,1)*(1-$F$107)*F96,0) -> 0 | H108: Calculation - this is added to compute cost
A109: =IF('Initial Screens'!$D$29="Yes","Show","Hide") -> Hide | B109: Estimated disaster recovery storage cost | F109: =IFERROR(MIN(SUM($F$105:$F$106)/$F$94,1)*(1-$F$107)*F97,0) -> 0 | H109: Calculation - this is added to storage costs
A110: =IF('Initial Screens'!$D$29="Yes","Show","Hide") -> Hide | B110: Estimated disaster recovery network cost (other network devices, not firewalls or load balancers) | F110: =IFERROR(MIN(SUM($F$105:$F$106)/$F$94,1)*(1-$F$107)*F98,0) -> 0 | H110: Calculation - this is added to network costs
...

Sheet Storage
B2: Current State Storage Costs & Anticipated Reduction | G2: Return button
B4: Current State | H4: Sourcing & Comments
B5: Number of VMs | F5: ='Excel Output'!D22 -> 5000 | H5: From inputs
A6: =IF(Compute!$D$68="No","Hide","Show") -> Show | B6: Number of Physical legacy servers | F6: =Compute!F73 -> 0 | H6: From Compute
B7: Average allocated/provisioned storage (GBs) per VM | F7: ='Excel Output'!D24 -> 300
A8: =IF(Compute!$D$68="No","Hide","Show") -> Show | B8: Average allocated/provisioned storage (GBs) per Physical Server | F8: =IF(Compute!D68="No",0,'Excel Output'!D24) -> 300 | G8: =IF(Compute!D68="No","leave blank","") | H8: Placeholder default
B9: Total GBs of allocated/provisioned storage to support VMs | F9: =ROUND(F5*F7+F6*F8,0) -> 1500000 | H9: Calculation
B10: Usable to Raw Ratio | F10: 0.7 | H10: Placeholder estimate - Ratio of Usable storage to Raw capacity. The raw capacity includes storage requirement for RAID/FTT levels, swap space, dedupe, compression and other file and system overheads
B11: Total Raw Capacity required to support VMs (GB) | F11: =ROUND(F9/F10,0) -> 2142857 | H11: Calculation
A12: =IF('Initial Screens'!$C$13="VVF","Hide","Show") -> Show | B12: Percent of Hosts that are vSAN ready nodes | F12: =Compute!F8 -> 0 | H12: From inputs
A13: =IF($F$12=100%,"Hide","Show") -> Show | B13: Upfront external storage purchase cost per GB | F13: 2 | H13: Placeholder estimate
A14: =IF($F$12=0%,"Hide","Show") -> Hide | B14: Upfront capacity disk based storage cost per GB | F14: =F26 -> 0.98 | H14: From worksheet
B15: Other Storage Devices (includes SAN switches, HBAs etc.) as % of Host Cost | F15: 0.05 | H15: Placeholder estimate - Includes FC SAN switches and HBA/SFP interconnects
B16: Number of VM Hosts | F16: ='Excel Output'!D23 -> 400 | H16: ='Initial Screens'!$E$17 -> 0
B17: Average purchase cost per current state VM host | F17: =Compute!F8*Compute!F10+(1-Compute!F8)*Compute!F9 -> 25000 | H17: Calculation
A18: =IF(Compute!$D$68="No","Hide","Show") -> Show | B18: Average purchase cost per physical legacy server | F18: =Compute!F74 -> 5000 | H18: From Compute
B19: Other Storage Devices Cost | F19: =ROUND(F15*(F16*F17+F6*F18),0) -> 500000 | H19: Calculation
B20: Annual storage hardware support | F20: 0.15 | H20: Placeholder default
B21: =FIXED(AnalysisTerm,0)&"-Year Current State Cost" -> 10-Year Current State Cost | F21: =ROUND(Storage!F11*Storage!F12*Storage!F14+Storage!F11*(1-Storage!F12)*Storage!F13+Storage!F19,0)*(1+AnalysisTerm*Storage!F20) -> 11964285 | H21: Calculation
B22: Future State
B23: Number of VMs | F23: =ROUND(SUM(Compute!F15),0) -> 4500 | H23: Calculation
B24: Usable to Raw Ratio | F24: =IF('Initial Screens'!$C$13="VVF",F10,C47) -> 1.125 | G24: Worksheet | H24: From Worksheet
B25: Total Raw Capacity required to support VMs (GB) | F25: =ROUND(F23*F7*'Initial Screens'!D24/F24+F23*F7*(1-'Initial Screens'!D24)/Storage!F10,0) -> 1200000 | H25: Calculation based on the vSAN coverage
A26: =IF($F$29>0,"Show","Hide") -> Show | B26: Upfront storage purchase cost per GB with vSAN | F26: =C66 -> 0.98 | G26: Worksheet | H26: From Worksheet
A27: =IF($F$30>0,"Show","Hide") -> Hide | B27: Upfront storage purchase cost per GB without vSAN | F27: =F13 -> 2 | H27: Placeholder estimate
A28: =IF($F$30>0,"Show","Hide") -> Hide | B28: =B15 -> Other Storage Devices (includes SAN switches, HBAs etc.) as % of Host Cost | F28: =F15 -> 0.05 | H28: From above
A29: =IF($F$29>0,"Show","Hide") -> Show | B29: Number of vSAN Ready Nodes | F29: =Compute!F19 -> 143 | H29: From Compute
A30: =IF($F$30>0,"Show","Hide") -> Hide | B30: Number of ESXi Hosts | F30: =Compute!F20 -> 0 | H30: From Compute
A31: =IF($F$30>0,"Show","Hide") -> Hide | B31: Average purchase cost per host (ESXi Hosts) | F31: =Compute!F9 -> 25000 | H31: This is the server compute cost, embedded storage cost is factored under storage costs
A32: =IF($F$30>0,"Show","Hide") -> Hide | B32: Other Storage Devices Cost | F32: =F28*F30*F31 -> 0 | H32: Calculation
B33: Annual storage hardware support | F33: 0.15 | H33: Placeholder default
B34: =FIXED(AnalysisTerm,0)&"-Year Future State Cost" -> 10-Year Future State Cost | F34: =ROUND(F25*F26*Compute!F16+F25*(1-Compute!F16)*F27+F32,0)*(1+AnalysisTerm*F33) -> 2940000 | H34: Calculation
A36: =IF('Initial Screens'!$C$13="VVF","Hide","Show") -> Show | B36: Usable to Raw Ratio (Assumes ESA vSAN Architecture)
A37: =IF('Initial Screens'!$C$13="VVF","Hide","Show") -> Show
A38: =IF('Initial Screens'!$C$13="VVF","Hide","Show") -> Show | B38: Usable to Raw Ratio Calculation | H38: Sourcing and Comments
A39: =IF('Initial Screens'!$C$13="VVF","Hide","Show") -> Show | B39: Capacity Disk Size (GB) | C39: 1920 | D39: <--note to MF, this value should be bidirectionally linked with value in the worksheet below | H39: Placeholder estimate
A40: =IF('Initial Screens'!$C$13="VVF","Hide","Show") -> Show | B40: Operation Reserve Percentage | C40: =ROUND(25%,3) -> 0.25 | E40: In Excel output, should be as shown here | H40: Placeholder estimate
A41: =IF('Initial Screens'!$C$13="VVF","Hide","Show") -> Show | B41: Reserved Capacity Percentage | C41: =ROUND(1-C40,3) -> 0.75 | H41: Calculation
A42: =IF('Initial Screens'!$C$13="VVF","Hide","Show") -> Show | B42: RAID Overhead | C42: 1.5 | H42: FTT1/2/RAID-5/6 configuration with 3 node in a cluster
A43: =IF('Initial Screens'!$C$13="VVF","Hide","Show") -> Show | B43: Compression Ratio | C43: 1.5 | H43: Placeholder estimate
A44: =IF(AND($A$43="Show",'Initial Screens'!C13="VCF 9"),"Show","hide") -> Show | B44: Global Deduplication factor | C44: =IF(A44="Show",1.5,1) -> 1.5 | H44: Placeholder estimate
A45: =IF('Initial Screens'!$C$13="VVF","Hide","Show") -> Show | B45: Usable Storage per vSAN Host (GB) | C45: =ROUND(C39*C41*C43*C44/C42,1) -> 2160 | H45: Calculation
A46: =$A$44 -> Show | B46: Storage Space Efficency | C46: =C45/C39 -> 1.125 | H46: Calculation
A47: =IF('Initial Screens'!$C$13="VVF","Hide","Show") -> Show | B47: Usable to Raw Storage | C47: =ROUND(C45/(C39),3) -> 1.125 | H47: Calculation
A48: =IF('Initial Screens'!$C$13="VVF","Hide","Show") -> Show
A49: =IF('Initial Screens'!$C$13="VVF","Hide","Show") -> Show | B49: Capacity Disk Calculation (Assumes ESA vSAN Architecture)
A50: =IF('Initial Screens'!$C$13="VVF","Hide","Show") -> Show
A51: =IF('Initial Screens'!$C$13="VVF","Hide","Show") -> Show | B51: Number of Capacity Disks
A52: =IF('Initial Screens'!$C$13="VVF","Hide","Show") -> Show | B52: Number of vSAN Ready Nodes | C52: =F29 -> 143 | H52: From Compute
A53: =IF('Initial Screens'!$C$13="VVF","Hide","Show") -> Show | B53: Total capacity disks per host | C53: =IFERROR(IF(ROUNDUP(F25*'Excel Output'!E30/(F29*C39),0)<4,4,ROUNDUP(F25*'Excel Output'!E30/(F29*C39),0)),0) -> 5 | D53: =IF(C53>24,"Increase Capacity Disk Size","") | H53: Minimum Capacity Disks per host =4, Maximum Capacity Disks per host=24
A54: =IF('Initial Screens'!$C$13="VVF","Hide","Show") -> Show | B54: Total Raw Capacity available per host (TiB) | C54: =C53*C39*0.000909495 -> 8.731152 | D54: ^^ see error note here ^^ | H54: Calculation
A55: =IF('Initial Screens'!$C$13="VVF","Hide","Show") -> Show | B55: Total effective available capacity per host (TiB) | C55: =C54*C47 -> 9.822546
A56: =IF('Initial Screens'!$C$13="VVF","Hide","Show") -> Show
A57: =IF('Initial Screens'!$C$13="VVF","Hide","Show") -> Show | B57: Storage Cost Calculation | C57: Disk Size | D57: Qty Per host | E57: Cost Per unit (List)
A58: =IF('Initial Screens'!$C$13="VVF","Hide","Show") -> Show | B58: =B53 -> Total capacity disks per host | C58: =C39 -> 1920 | D58: =C53 -> 5 | E58: =ROUND(C58*0.855,0) -> 1642 | H58: Estimated net price/GB = $0.855
A59: =IF('Initial Screens'!$C$13="VVF","Hide","Show") -> Show
A60: =IF('Initial Screens'!$C$13="VVF","Hide","Show") -> Show | B60: Additional Discount | C60: 0 | H60: Placeholder estimate
A61: =IF('Initial Screens'!$C$13="VVF","Hide","Show") -> Show | B61: Cost of vSAN Ready Node Storage Component | C61: =ROUNDUP(D58*E58*(1-C60),0) -> 8210 | H61: Calculation
A62: =IF('Initial Screens'!$C$13="VVF","Hide","Show") -> Show
A63: =IF('Initial Screens'!$C$13="VVF","Hide","Show") -> Show | C63: Future State | H63: Sourcing and Comments
A64: =IF('Initial Screens'!$C$13="VVF","Hide","Show") -> Show | B64: Total cost of Storage in vSAN Ready Nodes | C64: =F29*C61 -> 1174030 | H64: Calculation
A65: =IF('Initial Screens'!$C$13="VVF","Hide","Show") -> Show | B65: Total Raw Capacity required to support VMs (GB) | C65: =F25*'Excel Output'!E30 -> 1200000 | H65: From Benefits Cost Sheet
A66: =IF('Initial Screens'!$C$13="VVF","Hide","Show") -> Show | B66: Average fully loaded storage cost per GB w/ vSAN | C66: =IFERROR(ROUND(C64/(C65),2),0) -> 0.98 | H66: Calculation
A67: =IF('Initial Screens'!$C$13="VVF","Hide","Show") -> Show | B67: Average Effectivestorage cost per GB w/ vSAN | C67: =IFERROR(ROUND(C64/(C55*C52*1099.511627776),2),0) -> 0.76 | H67: Calculation

Sheet Network
B2: Current State Network (Host Based) Costs & Anticipated Reduction | G2: Return button
B4: Current State | H4: Sourcing & Comments
B5: Other Network Devices (primarily ToRs) as % of Host Cost | F5: 0.1 | H5: Placeholder default
B6: Number of VM Hosts | F6: =Compute!F6 -> 400 | H6: ='Initial Screens'!$E$17 -> 0
A7: =IF(Compute!$D$68="No","Hide","Show") -> Show | B7: Number of Physical legacy servers (that can be virtualized) | F7: =Compute!F73 -> 0 | H7: From Compute
B8: Average purchase cost per current state host | F8: =Compute!F8*Compute!F10+(1-Compute!F8)*Compute!F9 -> 25000 | H8: From Compute
A9: =IF(Compute!$D$68="No","Hide","Show") -> Show | B9: Average purchase cost to refresh a physical legacy server | F9: =Compute!F74 -> 5000 | H9: From Compute
B10: Annual network hardware support | F10: 0.15 | H10: Placeholder default
B11: =FIXED(AnalysisTerm,0)&"-Year Current State Cost" -> 10-Year Current State Cost | F11: =ROUND(Network!F5*Network!F6*Network!F8,0)*(1+AnalysisTerm*Network!F10) -> 2500000 | H11: Calculation
B12: Future State
B13: Other Network Devices (primarily ToRs) as % of Host Cost | F13: =ROUND(F5,3) -> 0.1 | H13: From above
A14: =IF('Initial Screens'!$C$13="VVF","Hide","Show") -> Show | B14: Number of vSAN Ready Nodes | F14: =Compute!F19+Compute!F81 -> 143 | H14: From Compute
B15: Number of ESXi Hosts | F15: =Compute!F20+Compute!F82 -> 0 | H15: From Compute
A16: =IF('Initial Screens'!$C$13="VVF","Hide","Show") -> Show | B16: Average compute cost (excludes storage component) per host (vSAN Ready Nodes) | F16: =Compute!F21 -> 25000 | H16: From Compute
B17: Average purchase cost per host (ESXi Hosts) | F17: =Compute!F22 -> 0 | H17: From Compute
B18: Annual network hardware support | F18: 0.15 | H18: Placeholder default
B19: =FIXED(AnalysisTerm,0)&"-Year Future State Cost" -> 10-Year Future State Cost | F19: =ROUND(F13*(F14*F16+F15*F17),0)*(1+AnalysisTerm*F18) -> 893750 | H19: Calculation
B21: VCF Network Add-Ons
A23: =IF('Initial Screens'!$D$26="Yes","Show","Hide") -> Hide | B23: Reduced Load Balancer Hardware
A24: =IF('Initial Screens'!$D$26="Yes","Show","Hide") -> Hide
A25: =IF('Initial Screens'!$D$26="Yes","Show","Hide") -> Hide | B25: Current State | H25: Sourcing & Comments
A26: =IF('Initial Screens'!$D$26="Yes","Show","Hide") -> Hide | B26: Number of Data Center HW Load Balancers (existing and planned) | F26: =IF('Initial Screens'!D26="Yes",C43,0) -> 0 | G26: Worksheet | H26: Assumes host traffic = 4 Gbps, LB throughput = 20 Gbps and HW LB Traffic = 25%
A27: =IF('Initial Screens'!$D$26="Yes","Show","Hide") -> Hide | B27: Cost per load balancer | F27: 87000 | H27: Based on estimated net price for F5-BIG-LTM-8900
A28: =IF('Initial Screens'!$D$26="Yes","Show","Hide") -> Hide | B28: Annual network hardware support | F28: 0.15 | H28: Placeholder default
A29: =IF('Initial Screens'!$D$26="Yes","Show","Hide") -> Hide | B29: =FIXED(AnalysisTerm,0)&"-Year Current State Cost" -> 10-Year Current State Cost | F29: =ROUND(F26*F27,0)*(1+AnalysisTerm*F28) -> 0 | H29: Calculation
A30: =IF('Initial Screens'!$D$26="Yes","Show","Hide") -> Hide | B30: Future State
A31: =IF('Initial Screens'!$D$26="Yes","Show","Hide") -> Hide | B31: ="Anticipated Percent of DC load balancers that can be retired (or purchases avoided) in "&AnalysisTerm&" years" -> Anticipated Percent of DC load balancers that can be retired (or purchases avoided) in 10 years | F31: 1 | H31: Placeholder estimate
A32: =IF('Initial Screens'!$D$26="Yes","Show","Hide") -> Hide | B32: Anticipated number of Data Center load balancers | F32: =EVEN(F26*(1-F31)) -> 0 | H32: Calculation
A33: =IF('Initial Screens'!$D$26="Yes","Show","Hide") -> Hide | B33: Annual network hardware support | F33: 0.15 | H33: Placeholder default
A34: =IF('Initial Screens'!$D$26="Yes","Show","Hide") -> Hide | B34: =FIXED(AnalysisTerm,0)&"-Year Future State Cost" -> 10-Year Future State Cost | F34: =ROUND(F32*F27,0)*(1+AnalysisTerm*F33) -> 0 | H34: Calculation
A35: =IF('Initial Screens'!$D$26="Yes","Show","Hide") -> Hide
A36: =IF('Initial Screens'!$D$26="Yes","Show","Hide") -> Hide | B36: Data Center HW Load Balancers
A37: =IF('Initial Screens'!$D$26="Yes","Show","Hide") -> Hide
A38: =IF('Initial Screens'!$D$26="Yes","Show","Hide") -> Hide | B38: Number of Hosts | C38: ='Excel Output'!$D$23 -> 400 | H38: From Inputs
A39: =IF('Initial Screens'!$D$26="Yes",IF(Compute!$D$68="No","Hide","Show"),"Hide") -> Hide | B39: Number of Physical Servers | C39: =Compute!$F$73 -> 0 | H39: From Compute
A40: =IF('Initial Screens'!$D$26="Yes","Show","Hide") -> Hide | B40: Host Traffic (Gbps) | C40: =ROUND(4,1) -> 4 | H40: Placeholder estimate
A41: =IF('Initial Screens'!$D$26="Yes","Show","Hide") -> Hide | B41: LB Throughput (Gbps) | C41: =ROUND(20,1) -> 20 | H41: Placeholder estimate
A42: =IF('Initial Screens'!$D$26="Yes","Show","Hide") -> Hide | B42: HW LB traffic | C42: =ROUND(25%,2) -> 0.25 | H42: Placeholder estimate
A43: =IF('Initial Screens'!$D$26="Yes","Show","Hide") -> Hide | B43: Number of HW Load balancers | C43: =EVEN((C38+C39)*C40/C41*C42) -> 20 | H43: Calculation
A45: =IF('Initial Screens'!$D$27="Yes","Show","Hide") -> Hide | B45: Reduced Firewall Hardware
A46: =IF('Initial Screens'!$D$27="Yes","Show","Hide") -> Hide
A47: =IF('Initial Screens'!$D$27="Yes","Show","Hide") -> Hide | B47: Current State | H47: Sourcing & Comments
A48: =IF('Initial Screens'!$D$27="Yes","Show","Hide") -> Hide | B48: Number of Data Center HW Firewalls (existing and planned) | F48: =IF('Initial Screens'!D27="Yes",C65,0) -> 0 | G48: Worksheet | H48: Assumes host traffic = 4 Gbps, FW throughput = 20 Gbps, HW FW Traffic = 30%, and active-active
A49: =IF('Initial Screens'!$D$27="Yes","Show","Hide") -> Hide | B49: Cost per firewall | F49: =ROUND(90000,0) -> 90000 | H49: Based on estimated net price for PA-5260-DC
A50: =IF('Initial Screens'!$D$27="Yes","Show","Hide") -> Hide | B50: Annual network hardware support | F50: 0.15 | H50: Placeholder default
A51: =IF('Initial Screens'!$D$27="Yes","Show","Hide") -> Hide | B51: =FIXED(AnalysisTerm,0)&"-Year Current State Cost" -> 10-Year Current State Cost | F51: =ROUND(F48*F49,0)*(1+AnalysisTerm*F50) -> 0 | H51: Calculation
A52: =IF('Initial Screens'!$D$27="Yes","Show","Hide") -> Hide | B52: Future State
A53: =IF('Initial Screens'!$D$27="Yes","Show","Hide") -> Hide | B53: ="Anticipated Percent of DC firewalls that can be retired (or purchases avoided) in "&AnalysisTerm&" years" -> Anticipated Percent of DC firewalls that can be retired (or purchases avoided) in 10 years | F53: =ROUND(70%,3) -> 0.7 | H53: Placeholder estimate
A54: =IF('Initial Screens'!$D$27="Yes","Show","Hide") -> Hide | B54: Anticipated number of Data Center firewalls | F54: =ROUND(F48*(1-F53),0) -> 0 | H54: Calculation
A55: =IF('Initial Screens'!$D$27="Yes","Show","Hide") -> Hide | B55: Annual network hardware support | F55: 0.15 | H55: Placeholder default
A56: =IF('Initial Screens'!$D$27="Yes","Show","Hide") -> Hide | B56: =FIXED(AnalysisTerm,0)&"-Year Future State Cost" -> 10-Year Future State Cost | F56: =ROUND(F54*F49,0)*(1+AnalysisTerm*F55) -> 0 | H56: Calculation
A57: =IF('Initial Screens'!$D$27="Yes","Show","Hide") -> Hide
A58: =IF('Initial Screens'!$D$27="Yes","Show","Hide") -> Hide | B58: Data Center HW Firewalls
A59: =IF('Initial Screens'!$D$27="Yes","Show","Hide") -> Hide
A60: =IF('Initial Screens'!$D$27="Yes","Show","Hide") -> Hide | B60: Number of Hosts | C60: ='Excel Output'!$D$23 -> 400 | H60: From Inputs
A61: =IF('Initial Screens'!$D$26="Yes",IF(Compute!$D$68="No","Hide","Show"),"Hide") -> Hide | B61: Number of Physical Servers | C61: =Compute!$F$73 -> 0 | H61: From Compute
A62: =IF('Initial Screens'!$D$27="Yes","Show","Hide") -> Hide | B62: Host Traffic (Gbps) | C62: =ROUND(4,1) -> 4 | H62: Placeholder estimate
A63: =IF('Initial Screens'!$D$27="Yes","Show","Hide") -> Hide | B63: FW Throughput (Gbps) | C63: =ROUND(20,1) -> 20 | H63: Placeholder estimate
A64: =IF('Initial Screens'!$D$27="Yes","Show","Hide") -> Hide | B64: HW FW traffic | C64: =ROUND(30%,2) -> 0.3 | H64: Placeholder estimate
A65: =IF('Initial Screens'!$D$27="Yes","Show","Hide") -> Hide | B65: Number of HW Firewalls | C65: =EVEN((C60+C61)*C62/C63*C64) -> 24 | H65: Calculation

Sheet Software
B2: Current VMware Annual Investment Elimination | G2: Return button
B4: Current State | H4: Sourcing & Comments | I4: =F5*((1+F6)^5-1)/F6 -> 2762815.6
A5: (i) | B5: Annual VMware Software, Subscription and Services Renewal | F5: 500000 | H5: Please update with the actual stated out year value or similar
B6: Estimated annual increase | F6: 0.05 | H6: Placeholder default
B7: =FIXED(AnalysisTerm,0)&"-Year Current State Cost" -> 10-Year Current State Cost | F7: =IF(AnalysisTerm=3,F5+F5*(1+F6)+F5*(1+F6)^2,F5+F5*(1+F6)+F5*(1+F6)^2+F5*(1+F6)^3+F5*(1+F6)^4) -> 2762815.6 | H7: Calculation
B8: Future State
B9: Anticipated reduction | F9: =ROUND(100%,3)-50% -> 0.5 | H9: Assumes elimination of cost as part of execution of new contract | J9: =F10*F6/((1+F6)^5-1) -> 250000.03
B10: =FIXED(AnalysisTerm,0)&"-Year Future State Cost" -> 10-Year Future State Cost | F10: =ROUND(F7*(1-F9),0) -> 1381408 | H10: Calculation
A12: =IF('Initial Screens'!$D$28="Yes","Show","Hide") -> Hide | B12: Software License Cost Reduction with Data Services Manager (DSM)
A13: =IF('Initial Screens'!$D$28="Yes","Show","Hide") -> Hide
A14: =IF('Initial Screens'!$D$28="Yes","Show","Hide") -> Hide | B14: Current State | H14: Sourcing & Comments
A15: =IF('Initial Screens'!$D$28="Yes","Show","Hide") -> Hide | B15: Total number of Cores | F15: =Compute!D39*Compute!D41 -> 14400 | H15: Pulled from current number of hosts times current state cores per host
A16: =IF('Initial Screens'!$D$28="Yes","Show","Hide") -> Hide | B16: Percent of Cores requiring DSM coverage | F16: =ROUND(12%,3) -> 0.12 | H16: Postgres use
A17: =IF('Initial Screens'!$D$28="Yes","Show","Hide") -> Hide | B17: Average annual cost per core for competitive offerings (management of DB) | F17: =1000 -> 1000 | H17: RDS Outpost - Annualized cost of Nutanix DB (latest pricing 2024) - Not including the DB support
A18: =IF('Initial Screens'!$D$28="Yes","Show","Hide") -> Hide | B18: =FIXED(AnalysisTerm,0)&"-Year Current State Cost" -> 10-Year Current State Cost | F18: =IF('Initial Screens'!$D$28="Yes",ROUND(F15*F16*F17*AnalysisTerm,0),0) -> 0 | H18: Calculation
A19: =IF('Initial Screens'!$D$28="Yes","Show","Hide") -> Hide | B19: Future State
A20: =IF('Initial Screens'!$D$28="Yes","Show","Hide") -> Hide | B20: Anticipated reduction | F20: 1 | H20: Assumes full takeout
A21: =IF('Initial Screens'!$D$28="Yes","Show","Hide") -> Hide | B21: =FIXED(AnalysisTerm,0)&"-Year Future State Cost" -> 10-Year Future State Cost | F21: =IF('Initial Screens'!$D$28="Yes",ROUND(F18*(1-F20),0),0) -> 0 | H21: Calculation
B23: Include Custom Benefit | C23: No
B25: Other Reduced Software Cost(s)
B27: Current State | H27: Sourcing & Comments
B28: Number of software subscription contracts
B29: Annual average cost per contract
B30: =FIXED(AnalysisTerm,0)&"-Year Current State Cost" -> 10-Year Current State Cost | F30: =IFERROR(ROUND(F28*F29*AnalysisTerm,0),"") -> 0 | H30: Calculation
B31: Future State
B32: Percent to be impacted by VMware | F32: 1
B33: Anticipated cost reduction
B34: =FIXED(AnalysisTerm,0)&"-Year Future State Cost" -> 10-Year Future State Cost | F34: =IFERROR(ROUND((F30*(1-F32)+F30*F32*(1-F33))*AnalysisTerm,0),"") -> 0 | H34: Calculation

Sheet Facilities
B2: Reduced Power, Cooling, Rack Costs | G2: Return button
B4: Current State | H4: Sourcing & Comments
B5: Number of VM Hosts | F5: ='Excel Output'!$D$23+Compute!$F$94*'Excel Output'!$D$23 -> 400 | H5: =Compute!H6 -> 0
B6: Opex per host per year (rack, power, cooling) | F6: =F57 -> 6032 | G6: Worksheet | H6: From worksheet
A7: =IF(Compute!$D$68="No","Hide","Show") -> Show | B7: Number of Physical legacy servers | F7: =Compute!F73 -> 0 | H7: =Compute!H73 -> 0
A8: =IF(Compute!$D$68="No","Hide","Show") -> Show | B8: Opex per physical legacy server per year (rack, power, cooling) | F8: =F58 -> 5151 | H8: From worksheet
A9: =IF('Initial Screens'!$D$26="Yes","Show","Hide") -> Hide | B9: Number of load balancers | F9: =IF('Initial Screens'!$D$26="Yes",Network!F26,0) -> 0 | H9: From Network Calculation Section Above (Reduced Load Balancer Hardware)
A10: =IF('Initial Screens'!$D$26="Yes","Show","Hide") -> Hide | B10: Opex per load balancer per year (rack, power, cooling) | F10: =IF('Initial Screens'!$D$26="Yes",F59,0) -> 0 | G10: Worksheet | H10: From worksheet
A11: =IF('Initial Screens'!$D$27="Yes","Show","Hide") -> Hide | B11: Number of firewalls | F11: =IF('Initial Screens'!$D$27="Yes",Network!F48,0) -> 0 | H11: From Network Calculation Section Above (Reduced Firewall Hardware)
A12: =IF('Initial Screens'!$D$27="Yes","Show","Hide") -> Hide | B12: Opex per firewalls per year (rack, power, cooling) | F12: =IF('Initial Screens'!$D$27="Yes",F60,0) -> 0 | G12: Worksheet | H12: From worksheet
B13: =FIXED(AnalysisTerm,0)&"-Year Current State Cost" -> 10-Year Current State Cost | F13: =ROUND(F5*F6+F7*F8+F9*F10+F11*F12,0)*AnalysisTerm -> 24128000 | H13: Calculation
B14: Future State
B15: Number of Hosts (vSAN Ready Nodes & ESXi Hosts) | F15: =Compute!F17+Compute!F81+Compute!F82 -> 143 | H15: From Compute
B16: Opex per vSAN Ready Node per year (rack, power, cooling) | F16: =ROUND($F$6*IF(AND(Compute!F41>Compute!D41,Compute!F42>Compute!D42),0.9,1),0) -> 5429 | H16: From above
A17: =IF('Initial Screens'!$D$26="Yes","Show","Hide") -> Hide | B17: Number of load balancers | F17: =IF('Initial Screens'!$D$26="Yes",Network!F32,0) -> 0 | H17: From Network sheet
A18: =IF('Initial Screens'!$D$26="Yes","Show","Hide") -> Hide | B18: Opex per load balancer per year (rack, power, cooling) | F18: =F10 -> 0 | H18: From above
A19: =IF('Initial Screens'!$D$27="Yes","Show","Hide") -> Hide | B19: Number of firewalls | F19: =IF('Initial Screens'!$D$27="Yes",Network!F54,0) -> 0 | H19: From Network sheet
A20: =IF('Initial Screens'!$D$27="Yes","Show","Hide") -> Hide | B20: Opex per firewalls per year (rack, power, cooling) | F20: =F12 -> 0 | H20: From above
B21: =FIXED(AnalysisTerm,0)&"-Year Future State Cost" -> 10-Year Future State Cost | F21: =ROUND(F15*F16+F17*F18+F19*F20,0)*AnalysisTerm -> 7763470 | H21: Calculation
B23: Current State Ongoing Opex per device per year
B24: Power & Cooling Requirement | H24: Sourcing & Comments
B25: 24 x 7 Operations for DC HW (365*24) | F25: =ROUND(365*24,0) -> 8760 | H25: Assumes 365 days x 24 hours per year
B26: Operational Power rating per Physical Host (kW) | F26: =ROUND(0.65,2) -> 0.65 | H26: Placeholder estimate
A27: =IF(Compute!$D$68="No","Hide","Show") -> Show | B27: Operational Power rating per physical legacy server (kW) | F27: =ROUND(0.3,2) -> 0.3 | H27: Placeholder estimate
A28: =IF('Initial Screens'!$D$26="Yes","Show","Hide") -> Hide | B28: Operational Power rating per Load balancer (kW) | F28: =ROUND(0.3,2) -> 0.3 | H28: Placeholder estimate
A29: =IF('Initial Screens'!$D$27="Yes","Show","Hide") -> Hide | B29: Operational Power rating per Firewall (kW) | F29: =ROUND(0.3,2) -> 0.3 | H29: Placeholder estimate
B30: Burdened rate for additional Network and Storage Devices | F30: =ROUND(30%,2) -> 0.3 | H30: Placeholder estimate
B31: Power Usage Effectiveness- On-Premise DC | F31: =ROUND(1.7,1) -> 1.7 | H31: Placeholder estimate
B32: Resultant annual power consumption per physical host (KWh) | F32: =ROUND($F$25*F26*(1+$F$30)*$F$31,0) -> 12584 | H32: Calculation
A33: =IF(Compute!$D$68="No","Hide","Show") -> Show | B33: Resultant annual power consumption per physical legacy server (KWh) | F33: =ROUND($F$25*F27*(1+$F$30)*$F$31,0) -> 5808 | H33: Calculation
A34: =IF('Initial Screens'!$D$26="Yes","Show","Hide") -> Hide | B34: Resultant annual power consumption per load balancer (KWh) | F34: =ROUND($F$25*F28*(1+$F$30)*$F$31,0) -> 5808 | H34: Calculation
A35: =IF('Initial Screens'!$D$27="Yes","Show","Hide") -> Hide | B35: Resultant annual power consumption per firewall (KWh) | F35: =ROUND($F$25*F29*(1+$F$30)*$F$31,0) -> 5808 | H35: Calculation
B36: Electricity cost per kWh | F36: 0.13 | H36: https://www.globalpetrolprices.com/electricity_prices/#hl48
B37: Annual Power & Cooling Cost Per device
B38: VM Host | F38: =ROUND(F32*$F$36,0) -> 1636 | H38: Calculation
A39: =IF(Compute!$D$68="No","Hide","Show") -> Show | B39: Physical legacy server | F39: =ROUND(F33*$F$36,0) -> 755 | H39: Calculation
A40: =IF('Initial Screens'!$D$26="Yes","Show","Hide") -> Hide | B40: Load balancer | F40: =ROUND(F34*$F$36,0) -> 755 | H40: Calculation
A41: =IF('Initial Screens'!$D$27="Yes","Show","Hide") -> Hide | B41: Firewall | F41: =ROUND(F35*$F$36,0) -> 755 | H41: Calculation
B42: Data Center Space Requirement
B43: Unit for data center space/area calculations | F43: Sq. Feet | H43: Based on Region
B44: ="Space required per rack ("&F43&" )" -> Space required per rack (Sq. Feet ) | F44: =ROUNDUP(IF(F43=Misc!B112,0.092903,1)*25,2) -> 25 | H44: Industry average
B45: Rack Units (RU) per 19" Rack | F45: =ROUND(42,0) -> 42 | H45: Industry average
B46: Percent of rack that can be utilized by host servers | F46: =ROUND(65%,2) -> 0.65 | H46: Industry average
B47: Rack Units (RU) per Physical Host | F47: =ROUND(2,0) -> 2 | H47: Industry average
A48: =IF(Compute!$D$68="No","Hide","Show") -> Show | B48: Rack Units (RU) per Physical legacy server | F48: =ROUND(2,0) -> 2 | H48: Industry average
A49: =IF(OR('Initial Screens'!$D$26="Yes",'Initial Screens'!$D$27="Yes"),"Show","Hide") -> Hide | B49: Rack Units (RU) per Physical Load Balancer/Firewall | F49: =ROUND(2,0) -> 2 | H49: Industry average
B50: ="Annual Rack and Floor Space rental (per "&F43&")" -> Annual Rack and Floor Space rental (per Sq. Feet) | F50: =ROUND(((2400/IF(F43=Misc!B112,0.092903,1))),0) -> 2400 | H50: Placeholder estimate
B51: Annual Data Center Space Cost per Device
B52: VM Host | F52: =ROUND($F$47/($F$45*$F$46)*$F$44*$F$50,0) -> 4396 | H52: Calculation
A53: =IF(Compute!$D$68="No","Hide","Show") -> Show | B53: Physical legacy server | F53: =ROUND($F$48/($F$45*$F$46)*$F$44*$F$50,0) -> 4396 | H53: Calculation
A54: =IF('Initial Screens'!$D$26="Yes","Show","Hide") -> Hide | B54: Load balancer | F54: =ROUND($F$49/($F$45*$F$46)*$F$44*$F$50,0) -> 4396 | H54: Calculation
A55: =IF('Initial Screens'!$D$27="Yes","Show","Hide") -> Hide | B55: Firewall | F55: =ROUND($F$49/($F$45*$F$46)*$F$44*$F$50,0) -> 4396 | H55: Calculation
B56: Total Opex per device per year
B57: VM Host | F57: =ROUNDUP(SUM(F38,F52),0) -> 6032 | H57: Calculation
A58: =IF(Compute!$D$68="No","Hide","Show") -> Show | B58: Physical legacy server | F58: =ROUNDUP(SUM(F39,F53),0) -> 5151 | H58: Calculation
A59: =IF('Initial Screens'!$D$26="Yes","Show","Hide") -> Hide | B59: Load balancer | F59: =ROUNDUP(SUM(F40,F54),0) -> 5151 | H59: Calculation
A60: =IF('Initial Screens'!$D$27="Yes","Show","Hide") -> Hide | B60: Firewall | F60: =ROUNDUP(SUM(F41,F55),0) -> 5151 | H60: Calculation

Sheet Labor
K1: =(F60*F107*F108)/2080 -> 0
B2: Labor Productivity | G2: Return button
B4: Total Number of FTE(s) involved cosidered in Current state | F4: =ROUND(Misc!C156,1) -> 25.2 | H4: Calculation -Sum of all the individual FTEs cosnidered for estimating the operational efficiency improvement
B5: Total recaptured labor hours in future state | F5: =(F4*2080)*(1-F6) -> 27828.874 | H5: Calculation -Sum of all the individual FTEs cosnidered for estimating the operational efficiency improvement
B6: Anticipated Efficiency improvement | F6: =(F127-F128)/F127 -> 0.46907674 | H6: Calculation- Sum of all the individual FTEs cosnidered for estimating the operational efficiency improvement
B8: Server Admin Productivity
B9: Current State | H9: Sourcing & Comments
B10: Number of Server Administrators | F10: =ROUND(MIN(10,'Excel Output'!$D$22/1000),1) -> 5 | H10: Assumes 1000 VMs per admin
B11: Average annual fully burdened cost per server admin FTE | F11: =ROUND(Benchmarks!$D$16,2) -> 175032.71 | H11: ="Skillsoft 2024 IT Skills and Salary Report Benchmark for "&'Initial Screens'!$C$9&" "&'Initial Screens'!$C$8&" + conservative "&FIXED(Benchmarks!$D$45*100,1)&"% burden rate per" -> Skillsoft 2024 IT Skills and Salary Report Benchmark for AMER Financial Services + conservative 45.0% burden rate per
B12: Current State Annualized Cost | F12: =ROUND(F10*F11,0) -> 875164 | H12: Calculation
B13: Future State
B14: Anticipated percent productivity gain | F14: =IF(ISNUMBER(SEARCH("VCF",'Initial Screens'!$C$13)),MIN(50%,ROUND(40%*(1+Compute!$D$29),3)),ROUND(20%,3)) -> 0.48 | H14: Placeholder estimate
B15: Future State Annualized Cost | F15: =ROUND(F12*(1-F14),0) -> 455085 | H15: Calculation
A17: =IF('Initial Screens'!$C$13="VVF","Hide","Show") -> Show | B17: Storage Admin Productivity
A18: =IF('Initial Screens'!$C$13="VVF","Hide","Show") -> Show | B18: Current State | H18: Sourcing & Comments
A19: =IF('Initial Screens'!$C$13="VVF","Hide","Show") -> Show | B19: Number of storage administrator personnel | F19: =IF(A17="Show",ROUND(MIN(10,'Excel Output'!D22*'Excel Output'!D24/1000/300),1),0) -> 5 | H19: Assumes 300 TBs per admin
A20: =IF('Initial Screens'!$C$13="VVF","Hide","Show") -> Show | B20: Average annual fully burdened cost per storage administrator FTE | F20: =ROUND(Benchmarks!$D$16,2) -> 175032.71 | H20: ="Skillsoft 2024 IT Skills and Salary Report Benchmark for "&'Initial Screens'!$C$9&" "&'Initial Screens'!$C$8&" + conservative "&FIXED(Benchmarks!$D$45*100,1)&"% burden rate per" -> Skillsoft 2024 IT Skills and Salary Report Benchmark for AMER Financial Services + conservative 45.0% burden rate per
A21: =IF('Initial Screens'!$C$13="VVF","Hide","Show") -> Show | B21: Current State Annualized Cost | F21: =ROUND(F19*F20,0) -> 875164 | H21: Calculation
A22: =IF('Initial Screens'!$C$13="VVF","Hide","Show") -> Show | B22: Future State
A23: =IF('Initial Screens'!$C$13="VVF","Hide","Show") -> Show | B23: Anticipated percent productivity gain | F23: =MIN(50%,ROUND(40%*Misc!$E$139*(1+(Storage!F11-Storage!F25)/Storage!F11),3)) -> 0.5 | H23: Placeholder estimate
A24: =IF('Initial Screens'!$C$13="VVF","Hide","Show") -> Show | B24: Future State Annualized Cost | F24: =ROUND(F21*(1-F23),0) -> 437582 | H24: Calculation
A26: =IF(ISNUMBER(SEARCH("VCF",'Initial Screens'!$C$13)),"Show",IF(OR('Initial Screens'!$D$26="Yes",'Initial Screens'!$D$27="Yes"),"Show","Hide")) -> Show | B26: Network Admin (provisioning/troubleshooting) Productivity
A27: =$A$26 -> Show | B27: Current State | H27: Sourcing & Comments
A28: =$A$26 -> Show | B28: Number of network administrator personnel | F28: =ROUND(MIN(10,'Excel Output'!$D$22/1000),1) -> 5 | H28: Assumes 1000 VMs per admin
A29: =$A$26 -> Show | B29: Average annual fully burdened cost per network administrator FTE | F29: =ROUND(Benchmarks!$D$16,2) -> 175032.71 | H29: ="Skillsoft 2024 IT Skills and Salary Report Benchmark for "&'Initial Screens'!$C$9&" "&'Initial Screens'!$C$8&" + conservative "&FIXED(Benchmarks!$D$45*100,1)&"% burden rate per" -> Skillsoft 2024 IT Skills and Salary Report Benchmark for AMER Financial Services + conservative 45.0% burden rate per
A30: =$A$26 -> Show | B30: Current State Annualized Cost | F30: =ROUND(F28*F29,0) -> 875164 | H30: Calculation
A31: =$A$26 -> Show | B31: Future State
A32: =$A$26 -> Show | B32: Anticipated productivity gain | F32: =IF(ISNUMBER(SEARCH("VCF",'Initial Screens'!$C$13)),MIN(50%,ROUND(40%*(1+Compute!$D$29)*('Excel Output'!E29-'Excel Output'!D29),3)),ROUND(20%,3)) -> 0.48 | H32: Placeholder estimate
A33: =$A$26 -> Show | B33: Future State Annualized Cost | F33: =ROUND(F30*(1-F32),0) -> 455085 | H33: Calculation
A35: =IF(ISNUMBER(SEARCH("VCF",'Initial Screens'!$C$13)),"Show","Hide") -> Show | B35: Service Delivery (IaaS/Private Cloud) Productivity | K35: =3000*2.5 -> 7500
A36: =$A$35 -> Show | B36: Current State | H36: Sourcing & Comments | K36: =K35/1960 -> 3.8265306
A37: =$A$35 -> Show | B37: Number of IT service delivery personnel required for provisioning and deploying new VMS | F37: =IF(A35="Show",ROUND(MIN(10,'Excel Output'!$D$22/1000),1),0) -> 5 | H37: Assumes 1000 VMs per admin
A38: =$A$35 -> Show | B38: Average annual fully burdened cost per IT service delivery FTE | F38: =ROUND(Benchmarks!$D$16,2) -> 175032.71 | H38: ="Skillsoft 2024 IT Skills and Salary Report Benchmark for "&'Initial Screens'!$C$9&" "&'Initial Screens'!$C$8&" + conservative "&FIXED(Benchmarks!$D$45*100,1)&"% burden rate per" -> Skillsoft 2024 IT Skills and Salary Report Benchmark for AMER Financial Services + conservative 45.0% burden rate per | K38: =3000/K36 -> 784
A39: =$A$35 -> Show | B39: Current State Annualized Cost | F39: =ROUND(F37*F38,0) -> 875164 | H39: Calculation
A40: =$A$35 -> Show | B40: Future State
A41: =$A$35 -> Show | B41: Anticipated percent reduction in deploying new VMs | F41: =IF(ISNUMBER(SEARCH("VCF",'Initial Screens'!$C$13)),MIN(50%,ROUND(40%*(1+Compute!$D$29)*Misc!E137,3)),ROUND(20%,3)) -> 0.48 | H41: Placeholder estimate based on The Total Economic Impact™ Of VMware Cloud Foundation Automations
A42: =$A$35 -> Show | B42: Future State Annualized Cost | F42: =ROUND(F39*(1-F41),0) -> 455085 | H42: Calculation
A44: =IF(ISNUMBER(SEARCH("VCF",'Initial Screens'!$C$13)),"Show","Hide") -> Show | B44: =IF('Initial Screens'!C13="VCF 9", "Operational Efficency for Enterprise/Cloud Admin with VCF operations","Software Defined Datacenter (SDDC) Manager Productivity") -> Operational Efficency for Enterprise/Cloud Admin with VCF operations
A45: =$A$44 -> Show | B45: Current State | H45: Sourcing & Comments
A46: =$A$44 -> Show | B46: =IF('Initial Screens'!C13="VCF 9","Number of Cloud/Enterprise Admin", "Number of IT admin for existing SDDC Software LCM") -> Number of Cloud/Enterprise Admin | F46: =IF(A44="Show",ROUND(3,1),0) -> 3 | H46: Placeholder estimate
A47: =IF(AND('Initial Screens'!C13="VCF 9",A46="Show"),"Show","hide") -> Show | B47: Time required for application, workload, and infrastructure upgrades and patches (in hours) | F47: =IF(A47="Show",26,0) -> 26 | H47: Placeholder estimate based on The Total Economic Impact™ Of VMware Cloud Foundation Operations
A48: =$A$47 -> Show | B48: Annual number of upgrades | F48: =IF(A48="Show",4,0) -> 4 | H48: Placeholder estimate based on The Total Economic Impact™ Of VMware Cloud Foundation Operations
A49: =$A$47 -> Show | B49: Chargeback modeling hours (Includes chargeback model setup hours and data entry hours) | F49: =IF(A49="Show",96,0) -> 96
A50: =$A$44 -> Show | B50: Average annual fully burdened cost per IT service delivery FTE | F50: =ROUND(Benchmarks!$D$16,2) -> 175032.71 | H50: ="Skillsoft 2024 IT Skills and Salary Report Benchmark for "&'Initial Screens'!$C$9&" "&'Initial Screens'!$C$8&" + conservative "&FIXED(Benchmarks!$D$45*100,1)&"% burden rate per" -> Skillsoft 2024 IT Skills and Salary Report Benchmark for AMER Financial Services + conservative 45.0% burden rate per
A51: =$A$44 -> Show | B51: Current State Annualized Cost | F51: =ROUND(IF('Initial Screens'!C13="VCF 9",F47*F48*F46*F50/2080+F49*F50/2080+F46*F50,F46*F50),0) -> 559431 | H51: Calculation
A52: =$A$44 -> Show | B52: Future State
A53: =$A$44 -> Show | B53: Anticipated percent productivity gain | F53: =IF(ISNUMBER(SEARCH("VCF",'Initial Screens'!$C$13)),MIN(50%,ROUND(IF('Initial Screens'!$C$13="VCF 9",60%*(1+Compute!$D$29)*('Excel Output'!E27-'Excel Output'!D27),40%),3)),ROUND(20%,3)) -> 0.5 | H53: Placeholder estimate
A54: =$A$47 -> Show | B54: Anticipated upgrade efficency value | F54: =IF(A54="Show",MIN(77%,ROUND(77%*Misc!E136,3)),0) -> 0.77 | H54: Placeholder estimate based on The Total Economic Impact™ Of VMware Cloud Foundation Operations
A55: =$A$47 -> Show | B55: Anticipated chargeback modeling efficiency gain | F55: =IF(A55="Show",MIN(79%,ROUND(79%*Misc!E136,3)),0) -> 0.79 | H55: Placeholder estimate based on The Total Economic Impact™ Of VMware Cloud Foundation Operations
A56: =$A$44 -> Show | B56: Future State Annualized Cost | F56: =ROUND(F51*(1-F53)+(F47*F48*F46*F50/2080)*(1-F54)+(F49*F50/2080)*(1-F55),0) -> 287451 | H56: Calculation
A58: =IF('Initial Screens'!$D$28="Yes","Show","Hide") -> Hide | B58: Personnel Productivity with DSM
A59: =IF('Initial Screens'!$D$28="Yes","Show","Hide") -> Hide | B59: Current State | H59: Sourcing & Comments
A60: =IF('Initial Screens'!$D$28="Yes","Show","Hide") -> Hide | B60: Number of IT Personnel managing DBs | F60: =IF(A58="Show",ROUND(MIN(10,MAX(3,'Excel Output'!D22/1000)),1),0) -> 0 | H60: Placeholder Estimate
A61: =IF('Initial Screens'!$D$28="Yes","Show","Hide") -> Hide | B61: Average annual fully burdened cost per DSM FTE | F61: =ROUND(Benchmarks!$D$16,2) -> 175032.71 | H61: ="Skillsoft 2024 IT Skills and Salary Report Benchmark for "&'Initial Screens'!$C$9&" "&'Initial Screens'!$C$8&" + conservative "&FIXED(Benchmarks!$D$45*100,1)&"% burden rate per" -> Skillsoft 2024 IT Skills and Salary Report Benchmark for AMER Financial Services + conservative 45.0% burden rate per
A62: =IF('Initial Screens'!$D$28="Yes","Show","Hide") -> Hide | B62: Current State Annualized Cost | F62: =IF('Initial Screens'!$D$28="Yes",ROUND(F60*F61,0),0) -> 0 | H62: Calculation
A63: =IF('Initial Screens'!$D$28="Yes","Show","Hide") -> Hide | B63: Future State
A64: =IF('Initial Screens'!$D$28="Yes","Show","Hide") -> Hide | B64: Anticipated percent productivity gain | F64: =ROUND(40%,3) -> 0.4 | H64: Placeholder estimate
A65: =IF('Initial Screens'!$D$28="Yes","Show","Hide") -> Hide | B65: Future State Annualized Cost | F65: =IF('Initial Screens'!$D$28="Yes",ROUND(F62*(1-F64),0),0) -> 0 | H65: Calculation
A67: =IF('Initial Screens'!$D$29="Yes","Show","Hide") -> Hide | B67: Disaster Recovery Admin Productivity
A68: =IF('Initial Screens'!$D$29="Yes","Show","Hide") -> Hide | B68: Current State | H68: Sourcing & Comments
A69: =IF('Initial Screens'!$D$29="Yes","Show","Hide") -> Hide | B69: Number of Disaster Recovery Administrators | F69: =IF(A67="Show",ROUND(MIN(5,'Excel Output'!D22*'Excel Output'!D24/1000/300/2),1),0) -> 0 | H69: Assumes 1000 VMs per admin
A70: =IF('Initial Screens'!$D$29="Yes","Show","Hide") -> Hide | B70: Average annual fully burdened cost per server admin FTE | F70: =ROUND(Benchmarks!$D$16,2) -> 175032.71 | H70: ="Skillsoft 2024 IT Skills and Salary Report Benchmark for "&'Initial Screens'!$C$9&" "&'Initial Screens'!$C$8&" + conservative "&FIXED(Benchmarks!$D$45*100,1)&"% burden rate per" -> Skillsoft 2024 IT Skills and Salary Report Benchmark for AMER Financial Services + conservative 45.0% burden rate per
A71: =IF('Initial Screens'!$D$29="Yes","Show","Hide") -> Hide | B71: Current State Annualized Cost | F71: =ROUND(F69*F70,0) -> 0 | H71: Calculation
A72: =IF('Initial Screens'!$D$29="Yes","Show","Hide") -> Hide | B72: Future State
A73: =IF('Initial Screens'!$D$29="Yes","Show","Hide") -> Hide | B73: Anticipated percent productivity gain | F73: =IFERROR(ROUND(MAX(1,SUM(Compute!F105:F106)/Compute!F94)*75%,3),0) -> 0 | H73: Placeholder estimate
A74: =IF('Initial Screens'!$D$29="Yes","Show","Hide") -> Hide | B74: Future State Annualized Cost | F74: =ROUND(F71*(1-F73),0) -> 0 | H74: Calculation
A77: =IF(ISNUMBER(SEARCH("VCF",'Initial Screens'!$C$13)),"Show","Hide") -> Show | B77: Developer Productivity
A78: =$A$77 -> Show | B78: Current State | H78: Sourcing & Comments
A79: =$A$77 -> Show | B79: Number of business applications/databases
A80: =$A$77 -> Show | B80: Number of Developers | F80: =MIN(1300,ROUND(F79/2,0)) -> 0
A81: =$A$77 -> Show | B81: Average annual fully burdened cost per developer | F81: =ROUND(Benchmarks!$D$16*1.1,2) -> 192535.98 | H81: Placeholder estimate
A82: =$A$77 -> Show | B82: Current State Annualized Cost | F82: =F80*F81 -> 0 | H82: Calculation
A83: =$A$77 -> Show | B83: Future State
A84: =$A$77 -> Show | B84: Anticipated percent productivity gain | F84: =ROUND(6%,3) -> 0.06 | H84: Placeholder estimate
A85: =$A$77 -> Show | B85: Future State Annualized Cost | F85: =ROUND(F82*(1-F84),0) -> 0 | H85: Calculation
A88: =IF(AND('Initial Screens'!C13="VCF 9",'Initial Screens'!D21>0%),"Show","hide") -> Show | B88: Mean Time to Resolution (MTTR) Reduction | C88: =IF(A88="Hide","No","Yes") -> Yes
Q89: Current | R89: Future
A90: =IF(C88="No","Hide","Show") -> Show | B90: Mean Time to Resolution (MTTR) Reduction | P90: FTES | Q90: 15 | R90: 15
A91: =$A$90 -> Show | B91: Current State | H91: Sourcing & Comments | Q91: 120000 | R91: =Q91 -> 120000
A92: =$A$90 -> Show | B92: Number of infrastructure Admins required for resolving workload infrastructure issues | F92: =IF(A92="Show",ROUND(MIN(5,'Excel Output'!$D$22/3000),1),0) -> 1.7 | H92: Assumes 3000 VMs per admin | P92: Workload reduction | R92: 0.2
A93: =$A$90 -> Show | B93: Weekly cordination hours required for issue resolution (in hours) | F93: =IF(A93="Show",1,0) -> 1 | H93: Time allocated for meeting preparation and cordination to resolve the issue | Q93: =Q90*Q91 -> 1800000 | R93: =R90*R91*(1-R92) -> 1440000 | S93: =Q93-R93 -> 360000
A94: =$A$90 -> Show | B94: Average fully burdened IT cost per hour | F94: =ROUND(Benchmarks!$D$16,2) -> 175032.71 | H94: ="Skillsoft 2024 IT Skills and Salary Report Benchmark for "&'Initial Screens'!$C$9&" "&'Initial Screens'!$C$8&" + conservative "&FIXED(Benchmarks!$D$45*100,1)&"% burden rate per" -> Skillsoft 2024 IT Skills and Salary Report Benchmark for AMER Financial Services + conservative 45.0% burden rate per | P94: Legacy weekly | Q94: 1 | R94: 0.5
A95: =$A$90 -> Show | B95: Current State Annualized Cost | F95: =F92*F94*(1+F93*52/2080) -> 304994.5 | H95: Calculation | Q95: =Q94*(Q91/2080)*52*Q90 -> 45000 | R95: =R94*(R91/2080)*52*R90 -> 22500 | S95: =Q95-R95 -> 22500
A96: =$A$90 -> Show | B96: Future State
A97: =$A$90 -> Show | B97: Workload reduction on infrastructure issues | F97: =MIN(20%,ROUND(20%*Misc!$E$136,3)) -> 0.2 | H97: Placeholder estimate based on The Total Economic Impact™ Of VMware Cloud Foundation Operations
A98: =$A$90 -> Show | B98: Anticipated time reduction in weekly cordination hours | F98: =MIN(50%,ROUND(50%*Misc!$E$136,3)) -> 0.5 | H98: Placeholder estimate based on The Total Economic Impact™ Of VMware Cloud Foundation Operations
A99: =$A$90 -> Show | B99: Future State Annualized Cost | F99: =F92*F94*(1*(1-F97)+F93*52*1/2080*(1-F98)) -> 241763.93 | H99: Calculation
B101: Service Request (SR) Time Reduction | C101: Yes
A103: =IF(C101="No","Hide","Show") -> Show | B103: Service Request (SR) Time Reduction
A104: =$A$103 -> Show | B104: Current State | H104: Sourcing & Comments | M104: Not for UI
A105: =$A$103 -> Show | B105: Average number of SRs per week | F105: =IF(A103="Show",ROUND((20%*VMs)/52,0),0) -> 19 | H105: Placeholder estimate based on The Total Economic Impact™ Of VMware Cloud Foundation Automations | M105: Cost per SR | N105: 15
A106: =$A$103 -> Show | B106: Calculated number of SRs per year | F106: =ROUND(F105*52,0) -> 988 | H106: Calculation | M106: Assume hourly rate | N106: 61
A107: =$A$103 -> Show | B107: Average number of days to resolve an SR (weighted average of severity levels) | F107: 4.8 | H107: Placeholder estimate based on The Total Economic Impact™ Of VMware Cloud Foundation Automations | M107: AvgHoursPerSR | N107: =N105/N106 -> 0.24590164
A108: =$A$103 -> Show | B108: Average number of hours per day per open SR (weighted average of severity levels) | F108: 0.24 | H108: Placeholder estimate based on The Total Economic Impact™ Of VMware Cloud Foundation Automations
A109: =$A$103 -> Show | B109: Average fully burdened IT cost per hour | F109: =ROUND(Benchmarks!D10,2) -> 97.5 | H109: ="Skillsoft 2024 IT Skills and Salary Report Benchmark for "&'Initial Screens'!$C$9&" "&'Initial Screens'!$C$8&" + conservative "&FIXED(Benchmarks!$D$45*100,1)&"% burden rate per" -> Skillsoft 2024 IT Skills and Salary Report Benchmark for AMER Financial Services + conservative 45.0% burden rate per | M109: Sev 1 | N109: 0.1 | O109: =N109*$G$102 -> 0 | P109: 1 | Q109: 2
A110: =$A$103 -> Show | B110: Current State Annualized Cost | F110: =ROUND(F106*F107*F108*F109,0) -> 110972 | H110: Calculation | M110: Sev 2 | N110: 0.4 | O110: =N110*$G$102 -> 0 | P110: 3 | Q110: 4
A111: =$A$103 -> Show | B111: Future State | M111: Sev 3 | N111: 0.5 | O111: =N111*$G$102 -> 0 | P111: 7 | Q111: 1.5
A112: =$A$103 -> Show | B112: =IF('Initial Screens'!C13="VCF 9","Anticipated reduction in infrastructure related SR tickets ","Anticipated time reduction") -> Anticipated reduction in infrastructure related SR tickets | F112: =IF('Initial Screens'!C13="VCF 9", MIN(60%,ROUND(60%*Misc!E137,3)),ROUND(40%,3)) -> 0.6 | H112: Placeholder estimate based on The Total Economic Impact™ Of VMware Cloud Foundation Automations
A113: =$A$103 -> Show | B113: Future State Annualized Cost | F113: =ROUND(F110*(1-F112),0) -> 44389 | H113: Calculation | O113: =SUMPRODUCT(O109:O111,P109:P111)/SUM(O109:O111) -> #DIV/0!
B115: Include Custom Benefit | C115: No
...

Sheet Support
B2: Current VMware Support Investment Elimination | G2: Return button | H2: any values in yellow input cells for illustration only
B4: Current State | H4: Sourcing & Comments
B5: Annual VMware Support (e.g., TAM, etc.) | F5: 250000
B6: Estimated annual increase | F6: 0
B7: =FIXED(AnalysisTerm,0)&"-Year Current State Cost" -> 10-Year Current State Cost | F7: =IF(AnalysisTerm=3,F5+F5*(1+F6)+F5*(1+F6)^2,F5+F5*(1+F6)+F5*(1+F6)^2+F5*(1+F6)^3+F5*(1+F6)^4) -> 1250000 | H7: Calculation
B8: Future State
B9: Anticipated reduction | F9: 0.5 | H9: Assumes elimination of cost as part of execution of new contract (that may or may not include new support)
B10: =FIXED(AnalysisTerm,0)&"-Year Future State Cost" -> 10-Year Future State Cost | F10: =ROUND(F7*(1-F9),0) -> 625000 | H10: Calculation

Sheet Migration - Reskilling
B2: Include Migration Efficiency? | C2: Yes
A4: =IF($C$2="Yes","Show","Hide") -> Show | B4: =IF('Initial Screens'!C13="VCF 9","Migration Efficiency (related to host refresh and migration to VCF 9)","Migration Efficiency (related to host refresh)") -> Migration Efficiency (related to host refresh and migration to VCF 9) | G4: Return button
A5: =IF($C$2="Yes","Show","Hide") -> Show
A6: =IF($C$2="Yes","Show","Hide") -> Show | B6: Current State | H6: Sourcing & Comments
A7: =IF($C$2="Yes","Show","Hide") -> Show | B7: Number of VMs | F7: =IF(C2="Yes",'Excel Output'!D22,0) -> 5000 | H7: ='Initial Screens'!$E$16 -> 0
A8: =IF($C$2="Yes","Show","Hide") -> Show | B8: Expected percent of VMs to migrate over duration of analysis | F8: =ROUND(100%,3) -> 1 | H8: Assumes full migration
A9: =IF($C$2="Yes","Show","Hide") -> Show | B9: Average hours to migrate a VM (to the cloud or during a HW refresh) | F9: =ROUND(1,1) -> 1 | H9: VMware Benchmark (assumes vSphere only current state)
A10: =IF($C$2="Yes","Show","Hide") -> Show | B10: Fully burdened IT labor cost per hour | F10: =ROUND(Benchmarks!$D$10,2) -> 97.5 | H10: ="Skillsoft 2024 IT Skills and Salary Report Benchmark for "&'Initial Screens'!$C$9&" "&'Initial Screens'!$C$8&" + conservative "&FIXED(Benchmarks!$D$45*100,1)&"% burden rate per" -> Skillsoft 2024 IT Skills and Salary Report Benchmark for AMER Financial Services + conservative 45.0% burden rate per
A11: =IF($C$2="Yes","Show","Hide") -> Show | B11: =FIXED(AnalysisTerm,0)&"-Year Current State Cost" -> 10-Year Current State Cost | F11: =ROUND(F7*F8*F9*F10*AnalysisTerm,0) -> 4875000 | H11: Calculation
A12: =IF($C$2="Yes","Show","Hide") -> Show | B12: Future State
A13: =IF($C$2="Yes","Show","Hide") -> Show | B13: Anticipated percent reduction | F13: =ROUND(75%,3) -> 0.75 | H13: VMware Benchmark (assumes VCF w/ HCX)
A14: =IF($C$2="Yes","Show","Hide") -> Show | B14: =FIXED(AnalysisTerm,0)&"-Year Future State Cost" -> 10-Year Future State Cost | F14: =ROUND(F11*(1-F13),0) -> 1218750 | H14: Calculation
B16: Reskilling | G16: Return button
B18: Current State
B19: Number of FTEs (Server, Storage, Network, Service Delivery) | F19: =Labor!F10+Labor!F28+Labor!F19+Labor!F37 -> 20 | H19: From labor
B20: Annual Training Hours per year | F20: =ROUND(20,1) -> 20 | H20: Placeholder estimate
B21: Total Training Hours per year | F21: =F19*F20 -> 400 | H21: Calculation
B22: Fully burdened IT labor cost per hour | F22: =ROUND(Benchmarks!$D$10,2) -> 97.5 | H22: ="Skillsoft 2024 IT Skills and Salary Report Benchmark for "&'Initial Screens'!$C$9&" "&'Initial Screens'!$C$8&" + conservative "&FIXED(Benchmarks!$D$45*100,1)&"% burden rate per" -> Skillsoft 2024 IT Skills and Salary Report Benchmark for AMER Financial Services + conservative 45.0% burden rate per
B23: One Time Current State Reskilling cost | F23: =F21*F22 -> 39000 | H23: Calculation
B24: Future State
B25: Number of FTEs (Server, Storage, Network, Service Delivery) | F25: =Labor!F10+Labor!F28+Labor!F19+Labor!F37 -> 20 | H25: From labor
B26: Average Training Hours for Reskilling (one time) | F26: =ROUND(20*(('Excel Output'!E27-'Excel Output'!D27)+('Excel Output'!E28-'Excel Output'!D28)+('Excel Output'!E29-'Excel Output'!D29)+('Excel Output'!E30-'Excel Output'!D30)),1) -> 80 | H26: Calculation based on current-future state coverage for Ops, Automation, vSAN, and NSX
B27: Total Training Hours for reskilling | F27: =F25*F26 -> 1600 | H27: Calculation
B28: Fully burdened IT labor cost per hour | F28: =ROUND(Benchmarks!$D$10,2) -> 97.5 | H28: ="Skillsoft 2024 IT Skills and Salary Report Benchmark for "&'Initial Screens'!$C$9&" "&'Initial Screens'!$C$8&" + conservative "&FIXED(Benchmarks!$D$45*100,1)&"% burden rate per" -> Skillsoft 2024 IT Skills and Salary Report Benchmark for AMER Financial Services + conservative 45.0% burden rate per
B29: One Time Future State Reskilling cost | F29: =F27*F28 -> 156000 | H29: Calculation

Sheet InvestmentBVA
F6: =IF(#REF!<=3,"hide column","show column") -> #REF! | G6: =IF(#REF!<=4,"hide column","show column") -> #REF!
B7: Multi-year Impact (likely)
B9: Estimated Investment | C9: Year 1 | D9: Year 2 | E9: Year 3 | F9: =IF(#REF!>3,"Year 4","") -> #REF! | G9: =IF(#REF!>4,"Year 5","") -> #REF! | H9: Total
B10: Subscription | H10: =SUM(C10:G10) -> 0
B11: License | H11: =SUM(C11:G11) -> 0
B12: Maintenance (SnS) | H12: =SUM(C12:G12) -> 0
B13: Professional Services | H13: =SUM(C13:G13) -> 0
B14: Education / Training | H14: =SUM(C14:G14) -> 0
B15: Success360 / TAM | H15: =SUM(C15:G15) -> 0
B16: Other | H16: =SUM(C16:G16) -> 0
B17: Organizational Change Management (Consulting) | H17: =SUM(C17:G17) -> 0
B18: Organizational Change Management (Internal) | H18: =SUM(C18:G18) -> 0
B19: User Defined | H19: =SUM(C19:G19) -> 0
B20: Total Investment | C20: =SUM(C10:C19) -> 0 | D20: =SUM(D10:D19) -> 0 | E20: =SUM(E10:E19) -> 0 | F20: =SUM(F10:F19) -> 0 | G20: =SUM(G10:G19) -> 0 | H20: =SUM(H10:H19) -> 0
B21: Note: All pricing herein is an estimation and not an approved quote or formal proposal.

Sheet Misc
B2: Accordion Totals
C4: Current State | D4: Future State | E4: Future State for TCO Model (VCF at List Price)
B5: Compute | C5: =Compute!F12+Compute!F76+Compute!F100 -> 25000000 | D5: =Compute!F24+Compute!F86+Compute!F112 -> 8937500 | E5: =Transition!D11 -> 8937500
B6: Storage | C6: =Storage!F21+Compute!F101 -> 11964285 | D6: =Storage!F34+Compute!F113 -> 2940000 | E6: =Transition!D12 -> 2940000
B7: Network | C7: =Network!F11+Network!F29+Network!F51+Compute!F102 -> 2500000 | D7: =Network!F19+Network!F34+Network!F56+Compute!F114 -> 893750 | E7: =Transition!D13 -> 893750
B8: Software | C8: =Software!F7+Software!F18+Software!F30 -> 2762815.6 | D8: =Software!F10+Software!F21+Software!F34+'ROI Results'!O37 -> 8881408 | E8: =Transition!D14 -> 10000000
B9: Facilities | C9: =Facilities!F13 -> 24128000 | D9: =Facilities!F21 -> 7763470 | E9: =Transition!D15 -> 7763470
B10: Labor | C10: =Labor!F127 -> 44760535 | D10: =Labor!F128 -> 23764409 | E10: =Transition!D16 -> 23764409
B11: Support | C11: =Support!F7 -> 1250000 | D11: =Support!F10+'ROI Results'!O40 -> 1375000 | E11: =Transition!D17 -> 750000
B12: Migration | C12: ='Migration - Reskilling'!F11 -> 4875000 | D12: ='Migration - Reskilling'!F14 -> 1218750 | E12: =Transition!D18 -> 1218750
B13: One-time Reskilling | C13: ='Migration - Reskilling'!F23 -> 39000 | D13: ='Migration - Reskilling'!F29 -> 156000 | E13: =Transition!D19 -> 156000
B14: Sum of Annualized Business Benefits | C14: ='Business impact'!F19+'Business impact'!F34+'Business impact'!F54+'Business impact'!F65+'Business impact'!F77 -> 0
B16: CapEx v OpEx Calcs
E17: CapEx
B18: ='ROI Results'!$B$70 -> Ongoing current state (TCO) | E18: Year 1 | F18: Year 2 | G18: Year 3 | H18: =IF(AnalysisTerm>3,4,"") -> 4 | I18: =IF(AnalysisTerm>3,H18+1,"") -> 5 | J18: =IF(AnalysisTerm>5,I18+1,"") -> 6 | K18: =IF(AnalysisTerm>5,J18+1,"") -> 7 | L18: =IF(AnalysisTerm>7,K18+1,"") -> 8 | M18: =IF(AnalysisTerm>7,L18+1,"") -> 9 | N18: =IF(AnalysisTerm>7,M18+1,"") -> 10 | O18: Total
B19: Compute | E19: =(Hardware_Refreshcylce+Growth)*'ROI Results'!$C71 -> 2618750 | F19: =((Hardware_Refreshcylce+(1+Growth)^2-(1+Growth))*'ROI Results'!$C71)*(1+Inflation)^1 -> 2724285.6 | G19: =((Hardware_Refreshcylce+(1+Growth)^3-(1+Growth)^2)*'ROI Results'!$C71)*(1+Inflation)^2 -> 2835185.6 | H19: =IF(AnalysisTerm>3,((Hardware_Refreshcylce+(1+Growth)^H$18-(1+Growth)^3)*'ROI Results'!$C71)*(1+Inflation)^3,"") -> 2951790.1 | I19: =IF(AnalysisTerm>3,((Hardware_Refreshcylce+(1+Growth)^I$18-(1+Growth)^H$18)*'ROI Results'!$C71)*(1+Inflation)^H$18," ") -> 3074463.9 | J19: =IF(AnalysisTerm>$I$18,((Hardware_Refreshcylce+(1+Growth)^J$18-(1+Growth)^I$18)*'ROI Results'!$C71)*(1+Inflation)^I$18," ") -> 3203598.8 | K19: =IF(AnalysisTerm>$I$18,((Hardware_Refreshcylce+(1+Growth)^K$18-(1+Growth)^J$18)*'ROI Results'!$C71)*(1+Inflation)^J$18," ") -> 3339615.1 | L19: =IF(AnalysisTerm>$K$18,((Hardware_Refreshcylce+(1+Growth)^L$18-(1+Growth)^K$18)*'ROI Results'!$C71)*(1+Inflation)^K$18," ") -> 3482964.5 | M19: =IF(AnalysisTerm>$K$18,((Hardware_Refreshcylce+(1+Growth)^M$18-(1+Growth)^L$18)*'ROI Results'!$C71)*(1+Inflation)^L$18," ") -> 3634131.9 | N19: =IF(AnalysisTerm>$K$18,((Hardware_Refreshcylce+(1+Growth)^N$18-(1+Growth)^M$18)*'ROI Results'!$C71)*(1+Inflation)^M$18," ") -> 3793638.7 | O19: =SUM(E19:N19) -> 31658424 | P19: =SUM(E19+E32)='ROI Results'!E71 -> TRUE | Q19: =SUM(F19+F32)='ROI Results'!F71 -> TRUE | R19: =SUM(G19+G32)='ROI Results'!G71 -> TRUE | S19: =SUM(H19+H32)='ROI Results'!H71 -> TRUE | T19: =SUM(I19+I32)='ROI Results'!I71 -> TRUE | U19: =SUM(J19+J32)='ROI Results'!J71 -> TRUE | V19: =SUM(K19+K32)='ROI Results'!K71 -> TRUE | W19: =SUM(L19+L32)='ROI Results'!L71 -> TRUE | ... Z19: =SUM(O19+O32)='ROI Results'!O71 -> TRUE
B20: Storage | E20: =(Hardware_Refreshcylce+Growth)*'ROI Results'!$C72 -> 1196428.5 | F20: =((Hardware_Refreshcylce+(1+Growth)^2-(1+Growth))*'ROI Results'!$C72)*(1+Inflation)^1 -> 1244644.6 | G20: =((Hardware_Refreshcylce+(1+Growth)^3-(1+Growth)^2)*'ROI Results'!$C72)*(1+Inflation)^2 -> 1295311.5 | H20: =IF(AnalysisTerm>3,((Hardware_Refreshcylce+(1+Growth)^H$18-(1+Growth)^3)*'ROI Results'!$C72)*(1+Inflation)^3,"") -> 1348584.6 | I20: =IF(AnalysisTerm>3,((Hardware_Refreshcylce+(1+Growth)^I$18-(1+Growth)^H$18)*'ROI Results'!$C72)*(1+Inflation)^H$18," ") -> 1404630.6 | J20: =IF(AnalysisTerm>$I$18,((Hardware_Refreshcylce+(1+Growth)^J$18-(1+Growth)^I$18)*'ROI Results'!$C72)*(1+Inflation)^I$18," ") -> 1463628.4 | K20: =IF(AnalysisTerm>$I$18,((Hardware_Refreshcylce+(1+Growth)^K$18-(1+Growth)^J$18)*'ROI Results'!$C72)*(1+Inflation)^J$18," ") -> 1525770.2 | L20: =IF(AnalysisTerm>$K$18,((Hardware_Refreshcylce+(1+Growth)^L$18-(1+Growth)^K$18)*'ROI Results'!$C72)*(1+Inflation)^K$18," ") -> 1591262.2 | M20: =IF(AnalysisTerm>$K$18,((Hardware_Refreshcylce+(1+Growth)^M$18-(1+Growth)^L$18)*'ROI Results'!$C72)*(1+Inflation)^L$18," ") -> 1660326.1 | N20: =IF(AnalysisTerm>$K$18,((Hardware_Refreshcylce+(1+Growth)^N$18-(1+Growth)^M$18)*'ROI Results'!$C72)*(1+Inflation)^M$18," ") -> 1733200 | O20: =SUM(E20:N20) -> 14463787 | P20: =SUM(E20+E33)='ROI Results'!E72 -> TRUE | Q20: =SUM(F20+F33)='ROI Results'!F72 -> TRUE | R20: =SUM(G20+G33)='ROI Results'!G72 -> TRUE | S20: =SUM(H20+H33)='ROI Results'!H72 -> TRUE | T20: =SUM(I20+I33)='ROI Results'!I72 -> TRUE | U20: =SUM(J20+J33)='ROI Results'!J72 -> TRUE | V20: =SUM(K20+K33)='ROI Results'!K72 -> TRUE | W20: =SUM(L20+L33)='ROI Results'!L72 -> TRUE | ... Z20: =SUM(O20+O33)='ROI Results'!O72 -> TRUE
B21: Network | E21: =(Hardware_Refreshcylce+Growth)*'ROI Results'!$C73 -> 261875 | F21: =((Hardware_Refreshcylce+(1+Growth)^2-(1+Growth))*'ROI Results'!$C73)*(1+Inflation)^1 -> 272428.56 | G21: =((Hardware_Refreshcylce+(1+Growth)^3-(1+Growth)^2)*'ROI Results'!$C73)*(1+Inflation)^2 -> 283518.56 | H21: =IF(AnalysisTerm>3,((Hardware_Refreshcylce+(1+Growth)^H$18-(1+Growth)^3)*'ROI Results'!$C73)*(1+Inflation)^3,"") -> 295179.01 | I21: =IF(AnalysisTerm>3,((Hardware_Refreshcylce+(1+Growth)^I$18-(1+Growth)^H$18)*'ROI Results'!$C73)*(1+Inflation)^H$18," ") -> 307446.39 | J21: =IF(AnalysisTerm>$I$18,((Hardware_Refreshcylce+(1+Growth)^J$18-(1+Growth)^I$18)*'ROI Results'!$C73)*(1+Inflation)^I$18," ") -> 320359.88 | K21: =IF(AnalysisTerm>$I$18,((Hardware_Refreshcylce+(1+Growth)^K$18-(1+Growth)^J$18)*'ROI Results'!$C73)*(1+Inflation)^J$18," ") -> 333961.51 | L21: =IF(AnalysisTerm>$K$18,((Hardware_Refreshcylce+(1+Growth)^L$18-(1+Growth)^K$18)*'ROI Results'!$C73)*(1+Inflation)^K$18," ") -> 348296.45 | M21: =IF(AnalysisTerm>$K$18,((Hardware_Refreshcylce+(1+Growth)^M$18-(1+Growth)^L$18)*'ROI Results'!$C73)*(1+Inflation)^L$18," ") -> 363413.19 | N21: =IF(AnalysisTerm>$K$18,((Hardware_Refreshcylce+(1+Growth)^N$18-(1+Growth)^M$18)*'ROI Results'!$C73)*(1+Inflation)^M$18," ") -> 379363.87 | O21: =SUM(E21:N21) -> 3165842.4 | P21: =SUM(E21+E34)='ROI Results'!E73 -> TRUE | Q21: =SUM(F21+F34)='ROI Results'!F73 -> TRUE | R21: =SUM(G21+G34)='ROI Results'!G73 -> TRUE | S21: =SUM(H21+H34)='ROI Results'!H73 -> TRUE | T21: =SUM(I21+I34)='ROI Results'!I73 -> TRUE | U21: =SUM(J21+J34)='ROI Results'!J73 -> FALSE | V21: =SUM(K21+K34)='ROI Results'!K73 -> TRUE | W21: =SUM(L21+L34)='ROI Results'!L73 -> TRUE | ... Z21: =SUM(O21+O34)='ROI Results'!O73 -> TRUE
B22: Software | E22: 0 | F22: 0 | G22: 0 | H22: 0 | I22: 0 | J22: 0 | K22: 0 | L22: 0 | M22: 0 | N22: 0 | O22: =SUM(E22:N22) -> 0 | P22: =SUM(E22+E35)='ROI Results'!E74 -> TRUE | Q22: =SUM(F22+F35)='ROI Results'!F74 -> TRUE | R22: =SUM(G22+G35)='ROI Results'!G74 -> TRUE | S22: =SUM(H22+H35)='ROI Results'!H74 -> TRUE | T22: =SUM(I22+I35)='ROI Results'!I74 -> TRUE | U22: =SUM(J22+J35)='ROI Results'!J74 -> TRUE | V22: =SUM(K22+K35)='ROI Results'!K74 -> TRUE | W22: =SUM(L22+L35)='ROI Results'!L74 -> TRUE | ... Z22: =SUM(O22+O35)='ROI Results'!O74 -> TRUE
B23: Facilities | E23: 0 | F23: 0 | G23: 0 | H23: 0 | I23: 0 | J23: 0 | K23: 0 | L23: 0 | M23: 0 | N23: 0 | O23: =SUM(E23:N23) -> 0 | P23: =SUM(E23+E36)='ROI Results'!E75 -> TRUE | Q23: =SUM(F23+F36)='ROI Results'!F75 -> TRUE | R23: =SUM(G23+G36)='ROI Results'!G75 -> TRUE | S23: =SUM(H23+H36)='ROI Results'!H75 -> TRUE | T23: =SUM(I23+I36)='ROI Results'!I75 -> TRUE | U23: =SUM(J23+J36)='ROI Results'!J75 -> TRUE | V23: =SUM(K23+K36)='ROI Results'!K75 -> TRUE | W23: =SUM(L23+L36)='ROI Results'!L75 -> TRUE | ... Z23: =SUM(O23+O36)='ROI Results'!O75 -> TRUE
B24: Labor | E24: 0 | F24: 0 | G24: 0 | H24: 0 | I24: 0 | J24: 0 | K24: 0 | L24: 0 | M24: 0 | N24: 0 | O24: =SUM(E24:N24) -> 0 | P24: =SUM(E24+E37)='ROI Results'!E76 -> TRUE | Q24: =SUM(F24+F37)='ROI Results'!F76 -> TRUE | R24: =SUM(G24+G37)='ROI Results'!G76 -> TRUE | S24: =SUM(H24+H37)='ROI Results'!H76 -> TRUE | T24: =SUM(I24+I37)='ROI Results'!I76 -> TRUE | U24: =SUM(J24+J37)='ROI Results'!J76 -> TRUE | V24: =SUM(K24+K37)='ROI Results'!K76 -> TRUE | W24: =SUM(L24+L37)='ROI Results'!L76 -> TRUE | ... Z24: =SUM(O24+O37)='ROI Results'!O76 -> TRUE
B25: Support | E25: 0 | F25: 0 | G25: 0 | H25: 0 | I25: 0 | J25: 0 | K25: 0 | L25: 0 | M25: 0 | N25: 0 | O25: =SUM(E25:N25) -> 0 | P25: =SUM(E25+E38)='ROI Results'!E77 -> TRUE | Q25: =SUM(F25+F38)='ROI Results'!F77 -> TRUE | R25: =SUM(G25+G38)='ROI Results'!G77 -> TRUE | S25: =SUM(H25+H38)='ROI Results'!H77 -> TRUE | T25: =SUM(I25+I38)='ROI Results'!I77 -> TRUE | U25: =SUM(J25+J38)='ROI Results'!J77 -> TRUE | V25: =SUM(K25+K38)='ROI Results'!K77 -> TRUE | W25: =SUM(L25+L38)='ROI Results'!L77 -> TRUE | ... Z25: =SUM(O25+O38)='ROI Results'!O77 -> TRUE
B26: Migration | E26: ='ROI Results'!E78 -> 499687.5 | F26: ='ROI Results'!F78 -> 540412.03 | G26: ='ROI Results'!G78 -> 584455.61 | H26: ='ROI Results'!H78 -> 632088.74 | I26: ='ROI Results'!I78 -> 683603.98 | J26: ='ROI Results'!J78 -> 739317.7 | K26: ='ROI Results'!K78 -> 799572.09 | L26: ='ROI Results'!L78 -> 864737.22 | ... N26: ='ROI Results'!N78 -> 1011433.2 | O26: =SUM(E26:N26) -> 7290521.4 | P26: =SUM(E26+E39)='ROI Results'!E78 -> TRUE | Q26: =SUM(F26+F39)='ROI Results'!F78 -> TRUE | R26: =SUM(G26+G39)='ROI Results'!G78 -> TRUE | S26: =SUM(H26+H39)='ROI Results'!H78 -> TRUE | T26: =SUM(I26+I39)='ROI Results'!I78 -> TRUE | U26: =SUM(J26+J39)='ROI Results'!J78 -> TRUE | V26: =SUM(K26+K39)='ROI Results'!K78 -> TRUE | W26: =SUM(L26+L39)='ROI Results'!L78 -> TRUE | ... Z26: =SUM(O26+O39)='ROI Results'!O78 -> TRUE
B27: One-time Reskilling | E27: 0 | F27: 0 | G27: 0 | H27: 0 | I27: 0 | J27: 0 | K27: 0 | L27: 0 | M27: 0 | N27: 0 | O27: =SUM(E27:N27) -> 0 | P27: =SUM(E27+E40)='ROI Results'!E79 -> TRUE | Q27: =SUM(F27+F40)='ROI Results'!F79 -> TRUE | R27: =SUM(G27+G40)='ROI Results'!G79 -> TRUE | S27: =SUM(H27+H40)='ROI Results'!H79 -> TRUE | T27: =SUM(I27+I40)='ROI Results'!I79 -> TRUE | U27: =SUM(J27+J40)='ROI Results'!J79 -> TRUE | V27: =SUM(K27+K40)='ROI Results'!K79 -> TRUE | W27: =SUM(L27+L40)='ROI Results'!L79 -> TRUE | ... Z27: =SUM(O27+O40)='ROI Results'!O79 -> TRUE
N28: Total CapEx | O28: =SUM(O19:O27) -> 56578575
E30: OpEx
B31: ='ROI Results'!$B$70 -> Ongoing current state (TCO) | E31: Year 1 | F31: Year 2 | G31: Year 3 | H31: =H$18 -> 4 | I31: =I$18 -> 5 | J31: =J$18 -> 6 | K31: =K$18 -> 7 | L31: =L$18 -> 8 | M31: =M$18 -> 9 | N31: =N$18 -> 10 | O31: Total
B32: Compute | E32: ='ROI Results'!$D71/AnalysisTerm*(1+Growth) -> 2073750 | F32: ='ROI Results'!$D71/AnalysisTerm*((1+Growth)^2)*(1+Inflation)^1 -> 2242760.6 | G32: ='ROI Results'!$D71/AnalysisTerm*((1+Growth)^3)*(1+Inflation)^2 -> 2425545.6 | H32: =IF(AnalysisTerm>3,'ROI Results'!$D71/AnalysisTerm*((1+Growth)^H$31)*(1+Inflation)^3," ") -> 2623227.6 | I32: =IF(AnalysisTerm>3,'ROI Results'!$D71/AnalysisTerm*((1+Growth)^I$31)*(1+Inflation)^H$31," ") -> 2837020.6 | J32: =IF(AnalysisTerm>$I$31,'ROI Results'!$D71/AnalysisTerm*((1+Growth)^J$31)*(1+Inflation)^I$31," ") -> 3068237.8 | K32: =IF(AnalysisTerm>$I$31,'ROI Results'!$D71/AnalysisTerm*((1+Growth)^K$31)*(1+Inflation)^J$31," ") -> 3318299.2 | L32: =IF(AnalysisTerm>$L$31,'ROI Results'!$D71/AnalysisTerm*((1+Growth)^L$31)*(1+Inflation)^K$31," ") -> 3588740.6 | M32: =IF(AnalysisTerm>$L$31,'ROI Results'!$D71/AnalysisTerm*((1+Growth)^M$31)*(1+Inflation)^L$31," ") -> 3881222.9 | N32: =IF(AnalysisTerm>$L$31,'ROI Results'!$D71/AnalysisTerm*((1+Growth)^N$31)*(1+Inflation)^M$31," ") -> 4197542.6 | O32: =SUM(E32:N32) -> 30256348
B33: Storage | E33: ='ROI Results'!$D72/AnalysisTerm*(1+Growth) -> 753749.95 | F33: ='ROI Results'!$D72/AnalysisTerm*((1+Growth)^2)*(1+Inflation)^1 -> 815180.58 | G33: ='ROI Results'!$D72/AnalysisTerm*((1+Growth)^3)*(1+Inflation)^2 -> 881617.79 | H33: =IF(AnalysisTerm>3,'ROI Results'!$D72/AnalysisTerm*((1+Growth)^H$31)*(1+Inflation)^3," ") -> 953469.64 | I33: =IF(AnalysisTerm>3,'ROI Results'!$D72/AnalysisTerm*((1+Growth)^I$31)*(1+Inflation)^H$31," ") -> 1031177.4 | J33: =IF(AnalysisTerm>$I$31,'ROI Results'!$D72/AnalysisTerm*((1+Growth)^J$31)*(1+Inflation)^I$31," ") -> 1115218.4 | K33: =IF(AnalysisTerm>$I$31,'ROI Results'!$D72/AnalysisTerm*((1+Growth)^K$31)*(1+Inflation)^J$31," ") -> 1206108.7 | L33: =IF(AnalysisTerm>$L$31,'ROI Results'!$D72/AnalysisTerm*((1+Growth)^L$31)*(1+Inflation)^K$31," ") -> 1304406.5 | M33: =IF(AnalysisTerm>$L$31,'ROI Results'!$D72/AnalysisTerm*((1+Growth)^M$31)*(1+Inflation)^L$31," ") -> 1410715.7 | N33: =IF(AnalysisTerm>$L$31,'ROI Results'!$D72/AnalysisTerm*((1+Growth)^N$31)*(1+Inflation)^M$31," ") -> 1525689 | O33: =SUM(E33:N33) -> 10997334
B34: Network | E34: ='ROI Results'!$D73/AnalysisTerm*(1+Growth) -> 205635.36 | F34: ='ROI Results'!$D73/AnalysisTerm*((1+Growth)^2)*(1+Inflation)^1 -> 222394.64 | G34: ='ROI Results'!$D73/AnalysisTerm*((1+Growth)^3)*(1+Inflation)^2 -> 240519.81 | H34: =IF(AnalysisTerm>3,'ROI Results'!$D73/AnalysisTerm*((1+Growth)^H$31)*(1+Inflation)^3," ") -> 260122.17 | I34: =IF(AnalysisTerm>3,'ROI Results'!$D73/AnalysisTerm*((1+Growth)^I$31)*(1+Inflation)^H$31," ") -> 281322.13 | J34: =IF(AnalysisTerm>$I$31,'ROI Results'!$D73/AnalysisTerm*((1+Growth)^J$31)*(1+Inflation)^I$31," ") -> 304249.88 | K34: =IF(AnalysisTerm>$I$31,'ROI Results'!$D73/AnalysisTerm*((1+Growth)^K$31)*(1+Inflation)^J$31," ") -> 329046.24 | L34: =IF(AnalysisTerm>$L$31,'ROI Results'!$D73/AnalysisTerm*((1+Growth)^L$31)*(1+Inflation)^K$31," ") -> 355863.51 | M34: =IF(AnalysisTerm>$L$31,'ROI Results'!$D73/AnalysisTerm*((1+Growth)^M$31)*(1+Inflation)^L$31," ") -> 384866.39 | N34: =IF(AnalysisTerm>$L$31,'ROI Results'!$D73/AnalysisTerm*((1+Growth)^N$31)*(1+Inflation)^M$31," ") -> 416233 | O34: =SUM(E34:N34) -> 3000253.1
B35: Software | E35: ='ROI Results'!E74 -> 500000 | F35: ='ROI Results'!F74 -> 525000 | G35: ='ROI Results'!G74 -> 551250 | H35: ='ROI Results'!H74 -> 578812.5 | I35: ='ROI Results'!I74 -> 607753.12 | J35: ='ROI Results'!J74 -> 638140.78 | K35: ='ROI Results'!K74 -> 670047.82 | L35: ='ROI Results'!L74 -> 703550.21 | ... N35: ='ROI Results'!N74 -> 775664.11 | O35: =SUM(E35:N35) -> 6288946.3
B36: Facilities | E36: ='ROI Results'!E75 -> 2484867.3 | F36: ='ROI Results'!F75 -> 2687384 | G36: ='ROI Results'!G75 -> 2906405.8 | H36: ='ROI Results'!H75 -> 3143277.9 | I36: ='ROI Results'!I75 -> 3399455 | J36: ='ROI Results'!J75 -> 3860336.1 | K36: ='ROI Results'!K75 -> 4174953.5 | L36: ='ROI Results'!L75 -> 4515212.2 | ... N36: ='ROI Results'!N75 -> 5281183 | O36: =SUM(E36:N36) -> 37336277
B37: Labor | E37: ='ROI Results'!E76 -> 4587954.8 | F37: ='ROI Results'!F76 -> 4961873.2 | G37: ='ROI Results'!G76 -> 5366265.8 | H37: ='ROI Results'!H76 -> 5803616.5 | I37: ='ROI Results'!I76 -> 6276611.2 | J37: ='ROI Results'!J76 -> 7127562.8 | K37: ='ROI Results'!K76 -> 7708459.2 | L37: ='ROI Results'!L76 -> 8336698.6 | ... N37: ='ROI Results'!N76 -> 9750954.9 | O37: =SUM(E37:N37) -> 68936136
B38: Support | E38: ='ROI Results'!E77 -> 125000 | F38: ='ROI Results'!F77 -> 125000 | G38: ='ROI Results'!G77 -> 125000 | H38: ='ROI Results'!H77 -> 125000 | I38: ='ROI Results'!I77 -> 125000 | J38: ='ROI Results'!J77 -> 125000 | K38: ='ROI Results'!K77 -> 125000 | L38: ='ROI Results'!L77 -> 125000 | ... N38: ='ROI Results'!N77 -> 125000 | O38: =SUM(E38:N38) -> 1250000
B39: Migration | E39: 0 | F39: 0 | G39: 0 | H39: 0 | I39: 0 | J39: 0 | K39: 0 | L39: 0 | M39: 0 | N39: 0 | O39: =SUM(E39:N39) -> 0
B40: One-time Reskilling | E40: ='ROI Results'!E79 -> 39000 | F40: ='ROI Results'!F79 -> 0 | G40: ='ROI Results'!G79 -> 0 | H40: ='ROI Results'!H79 -> 0 | I40: ='ROI Results'!I79 -> 0 | J40: ='ROI Results'!J79 -> 0 | K40: ='ROI Results'!K79 -> 0 | L40: ='ROI Results'!L79 -> 0 | ... N40: ='ROI Results'!N79 -> 0 | O40: =SUM(E40:N40) -> 39000
N41: Total OpEx | O41: =SUM(O32:O40) -> 1.5810429e+08
E42: CapEx
B43: Future State Brownfield (TCO) | E43: Year 1 | F43: Year 2 | G43: Year 3 | H43: =H$18 -> 4 | I43: =I$18 -> 5 | J43: =J$18 -> 6 | K43: =K$18 -> 7 | L43: =L$18 -> 8 | M43: =M$18 -> 9 | N43: =N$18 -> 10 | O43: Total
B44: Compute | E44: =(Hardware_Refreshcylce+Growth)*'ROI Results'!$C85 -> 899246.88 | F44: =((Hardware_Refreshcylce+(1+Growth)^2-(1+Growth))*'ROI Results'!$C85)*(1+Inflation)^1 -> 935486.52 | G44: =((Hardware_Refreshcylce+(1+Growth)^3-(1+Growth)^2)*'ROI Results'!$C85)*(1+Inflation)^2 -> 973568.24 | H44: =IF(AnalysisTerm>3,((Hardware_Refreshcylce+(1+Growth)^4-(1+Growth)^3)*'ROI Results'!$C85)*(1+Inflation)^3," ") -> 1013608.8 | I44: =IF(AnalysisTerm>3,((Hardware_Refreshcylce+(1+Growth)^5-(1+Growth)^4)*'ROI Results'!$C85)*(1+Inflation)^4," ") -> 1055733.5 | J44: =IF(AnalysisTerm>5,((Hardware_Refreshcylce+(1+Growth)^J$43-(1+Growth)^I$43)*'ROI Results'!$C85)*(1+Inflation)^I$43," ") -> 1100076.8 | K44: =IF(AnalysisTerm>5,((Hardware_Refreshcylce+(1+Growth)^K$43-(1+Growth)^J$43)*'ROI Results'!$C85)*(1+Inflation)^J$43," ") -> 1146783.2 | L44: =IF(AnalysisTerm>7,((Hardware_Refreshcylce+(1+Growth)^L$43-(1+Growth)^K$43)*'ROI Results'!$C85)*(1+Inflation)^K$43," ") -> 1196007.6 | M44: =IF(AnalysisTerm>7,((Hardware_Refreshcylce+(1+Growth)^M$43-(1+Growth)^L$43)*'ROI Results'!$C85)*(1+Inflation)^L$43," ") -> 1247916.7 | N44: =IF(AnalysisTerm>7,((Hardware_Refreshcylce+(1+Growth)^N$43-(1+Growth)^M$43)*'ROI Results'!$C85)*(1+Inflation)^M$43," ") -> 1302689.3 | O44: =SUM(E44:N44) -> 10871118 | P44: =SUM(E44+E57)='ROI Results'!E85 -> TRUE | Q44: =SUM(F44+F57)='ROI Results'!F85 -> TRUE | R44: =SUM(G44+G57)='ROI Results'!G85 -> TRUE | S44: =SUM(H44+H57)='ROI Results'!H85 -> TRUE | T44: =SUM(I44+I57)='ROI Results'!I85 -> FALSE | U44: =SUM(J44+J57)='ROI Results'!J85 -> TRUE | V44: =SUM(K44+K57)='ROI Results'!K85 -> TRUE | W44: =SUM(L44+L57)='ROI Results'!L85 -> TRUE | ... Z44: =SUM(O44+O57)='ROI Results'!O85 -> TRUE
B45: Storage | E45: =(Hardware_Refreshcylce+Growth)*'ROI Results'!$C86 -> 294000 | F45: =((Hardware_Refreshcylce+(1+Growth)^2-(1+Growth))*'ROI Results'!$C86)*(1+Inflation)^1 -> 305848.2 | G45: =((Hardware_Refreshcylce+(1+Growth)^3-(1+Growth)^2)*'ROI Results'!$C86)*(1+Inflation)^2 -> 318298.64 | H45: =IF(AnalysisTerm>3,((Hardware_Refreshcylce+(1+Growth)^4-(1+Growth)^3)*'ROI Results'!$C86)*(1+Inflation)^3," ") -> 331389.51 | I45: =IF(AnalysisTerm>3,((Hardware_Refreshcylce+(1+Growth)^5-(1+Growth)^4)*'ROI Results'!$C86)*(1+Inflation)^4," ") -> 345161.78 | J45: =IF(AnalysisTerm>5,((Hardware_Refreshcylce+(1+Growth)^J$43-(1+Growth)^I$43)*'ROI Results'!$C86)*(1+Inflation)^I$43," ") -> 359659.4 | K45: =IF(AnalysisTerm>5,((Hardware_Refreshcylce+(1+Growth)^K$43-(1+Growth)^J$43)*'ROI Results'!$C86)*(1+Inflation)^J$43," ") -> 374929.58 | L45: =IF(AnalysisTerm>7,((Hardware_Refreshcylce+(1+Growth)^L$43-(1+Growth)^K$43)*'ROI Results'!$C86)*(1+Inflation)^K$43," ") -> 391023.03 | M45: =IF(AnalysisTerm>7,((Hardware_Refreshcylce+(1+Growth)^M$43-(1+Growth)^L$43)*'ROI Results'!$C86)*(1+Inflation)^L$43," ") -> 407994.19 | N45: =IF(AnalysisTerm>7,((Hardware_Refreshcylce+(1+Growth)^N$43-(1+Growth)^M$43)*'ROI Results'!$C86)*(1+Inflation)^M$43," ") -> 425901.58 | O45: =SUM(E45:N45) -> 3554205.9 | P45: =SUM(E45+E58)='ROI Results'!E86 -> TRUE | Q45: =SUM(F45+F58)='ROI Results'!F86 -> TRUE | R45: =SUM(G45+G58)='ROI Results'!G86 -> TRUE | S45: =SUM(H45+H58)='ROI Results'!H86 -> TRUE | T45: =SUM(I45+I58)='ROI Results'!I86 -> TRUE | U45: =SUM(J45+J58)='ROI Results'!J86 -> TRUE | V45: =SUM(K45+K58)='ROI Results'!K86 -> TRUE | W45: =SUM(L45+L58)='ROI Results'!L86 -> TRUE | ... Z45: =SUM(O45+O58)='ROI Results'!O86 -> TRUE
B46: Network | E46: =(Hardware_Refreshcylce+Growth)*'ROI Results'!$C87 -> 89375 | F46: =((Hardware_Refreshcylce+(1+Growth)^2-(1+Growth))*'ROI Results'!$C87)*(1+Inflation)^1 -> 92976.812 | G46: =((Hardware_Refreshcylce+(1+Growth)^3-(1+Growth)^2)*'ROI Results'!$C87)*(1+Inflation)^2 -> 96761.705 | H46: =IF(AnalysisTerm>3,((Hardware_Refreshcylce+(1+Growth)^4-(1+Growth)^3)*'ROI Results'!$C87)*(1+Inflation)^3," ") -> 100741.29 | I46: =IF(AnalysisTerm>3,((Hardware_Refreshcylce+(1+Growth)^5-(1+Growth)^4)*'ROI Results'!$C87)*(1+Inflation)^4," ") -> 104928.01 | J46: =IF(AnalysisTerm>5,((Hardware_Refreshcylce+(1+Growth)^J$43-(1+Growth)^I$43)*'ROI Results'!$C87)*(1+Inflation)^I$43," ") -> 109335.23 | K46: =IF(AnalysisTerm>5,((Hardware_Refreshcylce+(1+Growth)^K$43-(1+Growth)^J$43)*'ROI Results'!$C87)*(1+Inflation)^J$43," ") -> 113977.32 | L46: =IF(AnalysisTerm>7,((Hardware_Refreshcylce+(1+Growth)^L$43-(1+Growth)^K$43)*'ROI Results'!$C87)*(1+Inflation)^K$43," ") -> 118869.67 | M46: =IF(AnalysisTerm>7,((Hardware_Refreshcylce+(1+Growth)^M$43-(1+Growth)^L$43)*'ROI Results'!$C87)*(1+Inflation)^L$43," ") -> 124028.85 | N46: =IF(AnalysisTerm>7,((Hardware_Refreshcylce+(1+Growth)^N$43-(1+Growth)^M$43)*'ROI Results'!$C87)*(1+Inflation)^M$43," ") -> 129472.63 | O46: =SUM(E46:N46) -> 1080466.5 | P46: =SUM(E46+E59)='ROI Results'!E87 -> TRUE | Q46: =SUM(F46+F59)='ROI Results'!F87 -> TRUE | R46: =SUM(G46+G59)='ROI Results'!G87 -> TRUE | S46: =SUM(H46+H59)='ROI Results'!H87 -> TRUE | T46: =SUM(I46+I59)='ROI Results'!I87 -> TRUE | U46: =SUM(J46+J59)='ROI Results'!J87 -> TRUE | V46: =SUM(K46+K59)='ROI Results'!K87 -> TRUE | W46: =SUM(L46+L59)='ROI Results'!L87 -> TRUE | ... Z46: =SUM(O46+O59)='ROI Results'!O87 -> TRUE
B47: Software | E47: 0 | F47: 0 | G47: 0 | H47: 0 | I47: 0 | J47: 0 | K47: 0 | L47: 0 | M47: 0 | N47: 0 | O47: =SUM(E47:N47) -> 0 | P47: =SUM(E47+E60)='ROI Results'!E88 -> TRUE | Q47: =SUM(F47+F60)='ROI Results'!F88 -> TRUE | R47: =SUM(G47+G60)='ROI Results'!G88 -> TRUE | S47: =SUM(H47+H60)='ROI Results'!H88 -> TRUE | T47: =SUM(I47+I60)='ROI Results'!I88 -> TRUE | U47: =SUM(J47+J60)='ROI Results'!J88 -> TRUE | V47: =SUM(K47+K60)='ROI Results'!K88 -> TRUE | W47: =SUM(L47+L60)='ROI Results'!L88 -> TRUE | ... Z47: =SUM(O47+O60)='ROI Results'!O88 -> TRUE
B48: Facilities | E48: 0 | F48: 0 | G48: 0 | H48: 0 | I48: 0 | J48: 0 | K48: 0 | L48: 0 | M48: 0 | N48: 0 | O48: =SUM(E48:N48) -> 0 | P48: =SUM(E48+E61)='ROI Results'!E89 -> TRUE | Q48: =SUM(F48+F61)='ROI Results'!F89 -> TRUE | R48: =SUM(G48+G61)='ROI Results'!G89 -> TRUE | S48: =SUM(H48+H61)='ROI Results'!H89 -> TRUE | T48: =SUM(I48+I61)='ROI Results'!I89 -> TRUE | U48: =SUM(J48+J61)='ROI Results'!J89 -> TRUE | V48: =SUM(K48+K61)='ROI Results'!K89 -> TRUE | W48: =SUM(L48+L61)='ROI Results'!L89 -> TRUE | ... Z48: =SUM(O48+O61)='ROI Results'!O89 -> TRUE
B49: Labor | E49: 0 | F49: 0 | G49: 0 | H49: 0 | I49: 0 | J49: 0 | K49: 0 | L49: 0 | M49: 0 | N49: 0 | O49: =SUM(E49:N49) -> 0 | P49: =SUM(E49+E62)='ROI Results'!E90 -> TRUE | Q49: =SUM(F49+F62)='ROI Results'!F90 -> TRUE | R49: =SUM(G49+G62)='ROI Results'!G90 -> TRUE | S49: =SUM(H49+H62)='ROI Results'!H90 -> TRUE | T49: =SUM(I49+I62)='ROI Results'!I90 -> TRUE | U49: =SUM(J49+J62)='ROI Results'!J90 -> TRUE | V49: =SUM(K49+K62)='ROI Results'!K90 -> TRUE | W49: =SUM(L49+L62)='ROI Results'!L90 -> TRUE | ... Z49: =SUM(O49+O62)='ROI Results'!O90 -> TRUE
B50: Support | E50: 0 | F50: 0 | G50: 0 | H50: 0 | I50: 0 | J50: 0 | K50: 0 | L50: 0 | M50: 0 | N50: 0 | O50: =SUM(E50:N50) -> 0 | P50: =SUM(E50+E63)='ROI Results'!E91 -> TRUE | Q50: =SUM(F50+F63)='ROI Results'!F91 -> TRUE | R50: =SUM(G50+G63)='ROI Results'!G91 -> TRUE | S50: =SUM(H50+H63)='ROI Results'!H91 -> TRUE | T50: =SUM(I50+I63)='ROI Results'!I91 -> TRUE | U50: =SUM(J50+J63)='ROI Results'!J91 -> TRUE | V50: =SUM(K50+K63)='ROI Results'!K91 -> TRUE | W50: =SUM(L50+L63)='ROI Results'!L91 -> TRUE | ... Z50: =SUM(O50+O63)='ROI Results'!O91 -> TRUE
B51: Migration | E51: ='ROI Results'!E92 -> 124921.87 | F51: ='ROI Results'!F92 -> 135103.01 | G51: ='ROI Results'!G92 -> 146113.9 | H51: ='ROI Results'!H92 -> 158022.19 | I51: ='ROI Results'!I92 -> 170900.99 | J51: ='ROI Results'!J92 -> 194070.9 | K51: ='ROI Results'!K92 -> 209887.67 | L51: ='ROI Results'!L92 -> 226993.52 | ... N51: ='ROI Results'!N92 -> 265501.21 | O51: =SUM(E51:N51) -> 1877008.8 | P51: =SUM(E51+E64)='ROI Results'!E92 -> TRUE | Q51: =SUM(F51+F64)='ROI Results'!F92 -> TRUE | R51: =SUM(G51+G64)='ROI Results'!G92 -> TRUE | S51: =SUM(H51+H64)='ROI Results'!H92 -> TRUE | T51: =SUM(I51+I64)='ROI Results'!I92 -> TRUE | U51: =SUM(J51+J64)='ROI Results'!J92 -> TRUE | V51: =SUM(K51+K64)='ROI Results'!K92 -> TRUE | W51: =SUM(L51+L64)='ROI Results'!L92 -> TRUE | ... Z51: =SUM(O51+O64)='ROI Results'!O92 -> TRUE
B52: One-time Reskilling | E52: 0 | F52: 0 | G52: 0 | H52: 0 | I52: 0 | J52: 0 | K52: 0 | L52: 0 | M52: 0 | N52: 0 | O52: =SUM(E52:N52) -> 0 | P52: =SUM(E52+E65)='ROI Results'!E93 -> TRUE | Q52: =SUM(F52+F65)='ROI Results'!F93 -> TRUE | R52: =SUM(G52+G65)='ROI Results'!G93 -> TRUE | S52: =SUM(H52+H65)='ROI Results'!H93 -> TRUE | T52: =SUM(I52+I65)='ROI Results'!I93 -> TRUE | U52: =SUM(J52+J65)='ROI Results'!J93 -> TRUE | V52: =SUM(K52+K65)='ROI Results'!K93 -> TRUE | W52: =SUM(L52+L65)='ROI Results'!L93 -> TRUE | ... Z52: =SUM(O52+O65)='ROI Results'!O93 -> TRUE
N53: Total CapEx | O53: =SUM(O44:O52) -> 17382799
E55: OpEx
B56: Future State Brownfield (TCO) | E56: Year 1 | F56: Year 2 | G56: Year 3 | H56: =H$18 -> 4 | I56: =I$18 -> 5 | J56: =J$18 -> 6 | K56: =K$18 -> 7 | L56: =L$18 -> 8 | M56: =M$18 -> 9 | N56: =N$18 -> 10 | O56: Total
B57: Compute | E57: =MIN(SUM('ROI Results'!$E56:E56),1)*'ROI Results'!$D85*(1+Growth)/AnalysisTerm+(1-MIN(SUM('ROI Results'!$E56:E56),1))*'ROI Results'!$D71*(1+Growth)/AnalysisTerm -> 1923050.6 | F57: =(MIN(SUM('ROI Results'!$E56:F56),1)*'ROI Results'!$D85*((1+Growth)^2)/AnalysisTerm+(1-MIN(SUM('ROI Results'!$E56:F56),1))*'ROI Results'!$D71*((1+Growth)^2)/AnalysisTerm)*(1+Inflation)^1 -> 1916797.9 | G57: =(MIN(SUM('ROI Results'!$E56:G56),1)*'ROI Results'!$D85*((1+Growth)^3)/AnalysisTerm+(1-MIN(SUM('ROI Results'!$E56:G56),1))*'ROI Results'!$D71*((1+Growth)^3)/AnalysisTerm)*(1+Inflation)^2 -> 1896752.6 | H57: =IF(AnalysisTerm>3,(MIN(SUM('ROI Results'!$E56:H56),1)*'ROI Results'!$D85*((1+Growth)^4)/AnalysisTerm+(1-MIN(SUM('ROI Results'!$E56:H56),1))*'ROI Results'!$D71*((1+Growth)^4)/AnalysisTerm)*(1+Inflation)^3," ") -> 1860708.1 | I57: =IF(AnalysisTerm>3,(MIN(SUM('ROI Results'!$E56:I56),1)*'ROI Results'!$D85*((1+Growth)^5)/AnalysisTerm+(1-MIN(SUM('ROI Results'!$E56:I56),1))*'ROI Results'!$D71*((1+Growth)^5)/AnalysisTerm)*(1+Inflation)^4," ") -> 1806189.5 | J57: =IF(AnalysisTerm>5,(MIN(SUM('ROI Results'!$E56:J56),1)*'ROI Results'!$D85*((1+Growth)^J$56)/AnalysisTerm+(1-MIN(SUM('ROI Results'!$E56:J56),1))*'ROI Results'!$D71*((1+Growth)^J$56)/AnalysisTerm)*(1+Inflation)^I$56," ") -> 1730425.2 | K57: =IF(AnalysisTerm>5,(MIN(SUM('ROI Results'!$E56:K56),1)*'ROI Results'!$D85*((1+Growth)^K$56)/AnalysisTerm+(1-MIN(SUM('ROI Results'!$E56:K56),1))*'ROI Results'!$D71*((1+Growth)^K$56)/AnalysisTerm)*(1+Inflation)^J$56," ") -> 1630314.2 | L57: =IF(AnalysisTerm>7,(MIN(SUM('ROI Results'!$E56:L56),1)*'ROI Results'!$D85*((1+Growth)^L$56)/AnalysisTerm+(1-MIN(SUM('ROI Results'!$E56:L56),1))*'ROI Results'!$D71*((1+Growth)^L$56)/AnalysisTerm)*(1+Inflation)^K$56," ") -> 1502391.1 | M57: =IF(AnalysisTerm>7,(MIN(SUM('ROI Results'!$E56:M56),1)*'ROI Results'!$D85*((1+Growth)^M$56)/AnalysisTerm+(1-MIN(SUM('ROI Results'!$E56:M56),1))*'ROI Results'!$D71*((1+Growth)^M$56)/AnalysisTerm)*(1+Inflation)^L$56," ") -> 1342787.6 | N57: =IF(AnalysisTerm>7,(MIN(SUM('ROI Results'!$E56:N56),1)*'ROI Results'!$D85*((1+Growth)^N$56)/AnalysisTerm+(1-MIN(SUM('ROI Results'!$E56:N56),1))*'ROI Results'!$D71*((1+Growth)^N$56)/AnalysisTerm)*(1+Inflation)^M$56," ") -> 1147189.5 | O57: =SUM(E57:N57) -> 16756606
B58: Storage | E58: =MIN(SUM('ROI Results'!$E57:E57),1)*'ROI Results'!$D86*(1+Growth)/AnalysisTerm+(1-MIN(SUM('ROI Results'!$E57:E57),1))*'ROI Results'!$D72*(1+Growth)/AnalysisTerm -> 696896.96 | F58: =(MIN(SUM('ROI Results'!$E57:F57),1)*'ROI Results'!$D86*((1+Growth)^2)/AnalysisTerm+(1-MIN(SUM('ROI Results'!$E57:F57),1))*'ROI Results'!$D72*((1+Growth)^2)/AnalysisTerm)*(1+Inflation)^1 -> 692207.55 | G58: =(MIN(SUM('ROI Results'!$E57:G57),1)*'ROI Results'!$D86*((1+Growth)^3)/AnalysisTerm+(1-MIN(SUM('ROI Results'!$E57:G57),1))*'ROI Results'!$D72*((1+Growth)^3)/AnalysisTerm)*(1+Inflation)^2 -> 682124.8 | H58: =IF(AnalysisTerm>3,(MIN(SUM('ROI Results'!$E57:H57),1)*'ROI Results'!$D86*((1+Growth)^4)/AnalysisTerm+(1-MIN(SUM('ROI Results'!$E57:H57),1))*'ROI Results'!$D72*((1+Growth)^4)/AnalysisTerm)*(1+Inflation)^3," ") -> 665800.74 | I58: =IF(AnalysisTerm>3,(MIN(SUM('ROI Results'!$E57:I57),1)*'ROI Results'!$D86*((1+Growth)^5)/AnalysisTerm+(1-MIN(SUM('ROI Results'!$E57:I57),1))*'ROI Results'!$D72*((1+Growth)^5)/AnalysisTerm)*(1+Inflation)^4," ") -> 642285.02 | J58: =IF(AnalysisTerm>5,(MIN(SUM('ROI Results'!$E57:J57),1)*'ROI Results'!$D86*((1+Growth)^J$56)/AnalysisTerm+(1-MIN(SUM('ROI Results'!$E57:J57),1))*'ROI Results'!$D72*((1+Growth)^J$56)/AnalysisTerm)*(1+Inflation)^I$56," ") -> 610513.83 | K58: =IF(AnalysisTerm>5,(MIN(SUM('ROI Results'!$E57:K57),1)*'ROI Results'!$D86*((1+Growth)^K$56)/AnalysisTerm+(1-MIN(SUM('ROI Results'!$E57:K57),1))*'ROI Results'!$D72*((1+Growth)^K$56)/AnalysisTerm)*(1+Inflation)^J$56," ") -> 569297.71 | L58: =IF(AnalysisTerm>7,(MIN(SUM('ROI Results'!$E57:L57),1)*'ROI Results'!$D86*((1+Growth)^L$56)/AnalysisTerm+(1-MIN(SUM('ROI Results'!$E57:L57),1))*'ROI Results'!$D72*((1+Growth)^L$56)/AnalysisTerm)*(1+Inflation)^K$56," ") -> 517308.18 | M58: =IF(AnalysisTerm>7,(MIN(SUM('ROI Results'!$E57:M57),1)*'ROI Results'!$D86*((1+Growth)^M$56)/AnalysisTerm+(1-MIN(SUM('ROI Results'!$E57:M57),1))*'ROI Results'!$D72*((1+Growth)^M$56)/AnalysisTerm)*(1+Inflation)^L$56," ") -> 453062.94 | N58: =IF(AnalysisTerm>7,(MIN(SUM('ROI Results'!$E57:N57),1)*'ROI Results'!$D86*((1+Growth)^N$56)/AnalysisTerm+(1-MIN(SUM('ROI Results'!$E57:N57),1))*'ROI Results'!$D72*((1+Growth)^N$56)/AnalysisTerm)*(1+Inflation)^M$56," ") -> 374909.63 | O58: =SUM(E58:N58) -> 5904407.3
B59: Network | E59: =MIN(SUM('ROI Results'!$E58:E58),1)*'ROI Results'!$D87*(1+Growth)/AnalysisTerm+(1-MIN(SUM('ROI Results'!$E58:E58),1))*'ROI Results'!$D73*(1+Growth)/AnalysisTerm -> 190702.45 | F59: =(MIN(SUM('ROI Results'!$E58:F58),1)*'ROI Results'!$D87*((1+Growth)^2)/AnalysisTerm+(1-MIN(SUM('ROI Results'!$E58:F58),1))*'ROI Results'!$D73*((1+Growth)^2)/AnalysisTerm)*(1+Inflation)^1 -> 190094.76 | G59: =(MIN(SUM('ROI Results'!$E58:G58),1)*'ROI Results'!$D87*((1+Growth)^3)/AnalysisTerm+(1-MIN(SUM('ROI Results'!$E58:G58),1))*'ROI Results'!$D73*((1+Growth)^3)/AnalysisTerm)*(1+Inflation)^2 -> 188121.31 | H59: =IF(AnalysisTerm>3,(MIN(SUM('ROI Results'!$E58:H58),1)*'ROI Results'!$D87*((1+Growth)^4)/AnalysisTerm+(1-MIN(SUM('ROI Results'!$E58:H58),1))*'ROI Results'!$D73*((1+Growth)^4)/AnalysisTerm)*(1+Inflation)^3," ") -> 184563.55 | I59: =IF(AnalysisTerm>3,(MIN(SUM('ROI Results'!$E58:I58),1)*'ROI Results'!$D87*((1+Growth)^5)/AnalysisTerm+(1-MIN(SUM('ROI Results'!$E58:I58),1))*'ROI Results'!$D73*((1+Growth)^5)/AnalysisTerm)*(1+Inflation)^4," ") -> 179176.31 | J59: =IF(AnalysisTerm>5,(MIN(SUM('ROI Results'!$E58:J58),1)*'ROI Results'!$D87*((1+Growth)^J$56)/AnalysisTerm+(1-MIN(SUM('ROI Results'!$E58:J58),1))*'ROI Results'!$D73*((1+Growth)^J$56)/AnalysisTerm)*(1+Inflation)^I$56," ") -> 171685.04 | K59: =IF(AnalysisTerm>5,(MIN(SUM('ROI Results'!$E58:K58),1)*'ROI Results'!$D87*((1+Growth)^K$56)/AnalysisTerm+(1-MIN(SUM('ROI Results'!$E58:K58),1))*'ROI Results'!$D73*((1+Growth)^K$56)/AnalysisTerm)*(1+Inflation)^J$56," ") -> 161782.56 | L59: =IF(AnalysisTerm>7,(MIN(SUM('ROI Results'!$E58:L58),1)*'ROI Results'!$D87*((1+Growth)^L$56)/AnalysisTerm+(1-MIN(SUM('ROI Results'!$E58:L58),1))*'ROI Results'!$D73*((1+Growth)^L$56)/AnalysisTerm)*(1+Inflation)^K$56," ") -> 149125.6 | M59: =IF(AnalysisTerm>7,(MIN(SUM('ROI Results'!$E58:M58),1)*'ROI Results'!$D87*((1+Growth)^M$56)/AnalysisTerm+(1-MIN(SUM('ROI Results'!$E58:M58),1))*'ROI Results'!$D73*((1+Growth)^M$56)/AnalysisTerm)*(1+Inflation)^L$56," ") -> 133330.95 | N59: =IF(AnalysisTerm>7,(MIN(SUM('ROI Results'!$E58:N58),1)*'ROI Results'!$D87*((1+Growth)^N$56)/AnalysisTerm+(1-MIN(SUM('ROI Results'!$E58:N58),1))*'ROI Results'!$D73*((1+Growth)^N$56)/AnalysisTerm)*(1+Inflation)^M$56," ") -> 113971.25 | O59: =SUM(E59:N59) -> 1662553.8
B60: Software | E60: ='ROI Results'!E88 -> 1638140.8 | F60: ='ROI Results'!F88 -> 1638140.8 | G60: ='ROI Results'!G88 -> 1638140.8 | H60: ='ROI Results'!H88 -> 1638140.8 | I60: ='ROI Results'!I88 -> 1638140.8 | J60: ='ROI Results'!J88 -> 138140.8 | K60: ='ROI Results'!K88 -> 138140.8 | L60: ='ROI Results'!L88 -> 138140.8 | ... N60: ='ROI Results'!N88 -> 138140.8 | O60: =SUM(E60:N60) -> 8881408
B61: Facilities | E61: ='ROI Results'!E89 -> 2315956.2 | F61: ='ROI Results'!F89 -> 2322029.2 | G61: ='ROI Results'!G89 -> 2313708.9 | H61: ='ROI Results'!H89 -> 2288608.9 | I61: ='ROI Results'!I89 -> 2244049.5 | J61: ='ROI Results'!J89 -> 2285876.5 | K61: ='ROI Results'!K89 -> 2188379.1 | L61: ='ROI Results'!L89 -> 2059806.3 | ... N61: ='ROI Results'!N89 -> 1691249.8 | O61: =SUM(E61:N61) -> 21605405
B62: Labor | E62: ='ROI Results'!E90 -> 4372744.5 | F62: ='ROI Results'!F90 -> 4496373.3 | G62: ='ROI Results'!G90 -> 4611108.7 | H62: ='ROI Results'!H90 -> 4714679.9 | I62: ='ROI Results'!I90 -> 4804505.1 | J62: ='ROI Results'!J90 -> 5121538.5 | K62: ='ROI Results'!K90 -> 5177358 | L62: ='ROI Results'!L90 -> 5208257.5 | ... N62: ='ROI Results'!N90 -> 5177008.8 | O62: =SUM(E62:N62) -> 48893379
B63: Support | E63: ='ROI Results'!E91 -> 137500 | F63: ='ROI Results'!F91 -> 137500 | G63: ='ROI Results'!G91 -> 137500 | H63: ='ROI Results'!H91 -> 137500 | I63: ='ROI Results'!I91 -> 137500 | J63: ='ROI Results'!J91 -> 137500 | K63: ='ROI Results'!K91 -> 137500 | L63: ='ROI Results'!L91 -> 137500 | ... N63: ='ROI Results'!N91 -> 137500 | O63: =SUM(E63:N63) -> 1375000
B64: Migration | E64: 0 | F64: 0 | G64: 0 | H64: 0 | I64: 0 | J64: 0 | K64: 0 | L64: 0 | M64: 0 | N64: 0 | O64: =SUM(E64:N64) -> 0
B65: One-time Reskilling | E65: ='ROI Results'!E93 -> 156000 | F65: ='ROI Results'!F93 -> 0 | G65: ='ROI Results'!G93 -> 0 | H65: ='ROI Results'!H93 -> 0 | I65: ='ROI Results'!I93 -> 0 | J65: ='ROI Results'!J93 -> 0 | K65: ='ROI Results'!K93 -> 0 | L65: ='ROI Results'!L93 -> 0 | ... N65: ='ROI Results'!N93 -> 0 | O65: =SUM(E65:N65) -> 156000
N66: Total OpEx | O66: =SUM(O57:O65) -> 1.0523476e+08
B68: For PPT VVM TCO Slide
B70: For per VM cost graphic
B71: Current State Average Annual Cost per VM | C71: =ROUND('Excel Output'!C39/AnalysisTerm/Transition!B25,0) -> 4294
B72: Future State Average Annual Cost per VM | C72: =ROUND(Transition!B20/AnalysisTerm/(Transition!D25*(1+Growth)^AnalysisTerm),0) -> 1664
B75: For CapEx/OpEx cost graphic
B76: Ongoing Current State | C76: (these values are in millions)
B77: CapEx | C77: =O28/1000000 -> 56.578575 | D77: M
B78: OpEx | C78: =O41/1000000 -> 158.10429 | D78: M
B80: Future State | C80: (these values are in millions)
B81: CapEx | C81: =Misc!O53/1000000 -> 17.382799 | D81: M
B82: OpEx | C82: =Misc!O66/1000000 -> 105.23476 | D82: M
B85: For TCO Solution Comparison Tile
B87: Private Cloud Platform | C87: =IF('Initial Screens'!C13="VCF","VMware Cloud Foundation",IF('Initial Screens'!C13="VVF","VMware vSphere Foundation","VMware vSphere Foundation w/ vSAN")) -> VMware vSphere Foundation w/ vSAN
B88: Savings | C88: ='Excel Output'!C39-Transition!D20 -> 1.5825899e+08
B89: Improvement | C89: =('Excel Output'!C39-Transition!D20)/'Excel Output'!C39 -> 0.73717568
B91: Note: Private Cloud Platform in Competitive TCO Comparison is limited to the solution selected in the Value Model
B93: Yes/No Drop Down
B96: Yes
B97: No
B99: Capacity Disk Size Options
B101: 1600
B102: 1920
B103: 3200
B104: 3840
B105: 6400
B106: 7680
B107: =12.8*1000 -> 12800
B108: =15.36*1000 -> 15360
B110: Area conversion for Facilities
B112: Sq. Meter
B113: Sq. Feet
B114: 0.092903 | C114: Conversion rate (sq ft to sq m)
B117: Mapping Advanced Services to Risk Reduction | P117: =(99.7%-99.4%)/99.4% -> 0.0030181087
B119: base solution | C119: ='Initial Screens'!C13 -> VCF 9 | O119: for drop downs
B120: Business Benefit | C120: Avi | D120: vDefend | E120: DSM | F120: VLR | G120: VCF Operations | H120: VCF Automation
B121: Reduced Downtime | C121: =IF('Initial Screens'!$D$26="Yes",0.8,0) -> 0 | D121: 0 | E121: 0 | F121: =IF('Initial Screens'!$D$29="Yes",0.8,0) -> 0 | G121: =IF('Initial Screens'!D21>0%,0.7*E136,0) -> 0.7 | H121: =IF('Initial Screens'!D22>0%,0.73*E137,0) -> 0.73 | O121: Yes
B122: Reduced Risk of a Security or Data Breach | C122: 0 | D122: =IF(AND(C119="VCF",'Initial Screens'!$D$27="Yes"),0.35,0) -> 0 | E122: =IF('Initial Screens'!$D$28="Yes",0.35,0) -> 0 | F122: 0 | O122: No
B123: Reduced Risk of a Ransomware Attack | C123: 0 | D123: 0 | E123: 0 | F123: =IF('Initial Screens'!$D$29="Yes",0.4,0) -> 0
B124: Weightage on Impact | C124: 0.35 | F124: =IF('Initial Screens'!$D$29="Yes",100%-SUM(C124,G124:H124),0%) -> 0 | G124: 0.2 | H124: 0.1
...

Sheet Business impact
B2: Some Inputs | G2: Return button
F3: For illustration
B4: =IF('Initial Screens'!C8="Government and Non-Profit","Annual operating budget","Annual revenue") -> Annual revenue | F4: 1000000000 | H4: From 10-k
A5: =IF('Initial Screens'!C8="Government","Hide","Show") -> Show | B5: Operating margin | F5: 0.1 | H5: From 10-k
B6: Number of employees | F6: 2500 | H6: From 10-k
B8: Average fully burdened IT cost per hour | F8: =ROUND(Benchmarks!$D$10,2) -> 97.5 | H8: ="Skillsoft 2024 IT Skills and Salary Report Benchmark for "&'Initial Screens'!$C$9&" "&'Initial Screens'!$C$8&" + conservative "&FIXED(Benchmarks!$D$45*100,1)&"% burden rate per" -> Skillsoft 2024 IT Skills and Salary Report Benchmark for AMER Financial Services + conservative 45.0% burden rate per
C9: to illustrate override | D9: default from table -->
A10: =IF('Initial Screens'!$C$8="Government","Show","hide") -> hide | B10: Include Increased Revenue | D10: =IF('Initial Screens'!$C$8="Government","No",IF(C10="","No",C10)) -> No | H10: Don't use if Government or non-profit
A12: =IF(AND($A$10="Show",$D$10="Yes"),"Show","Hide") -> Hide | B12: Increased Revenue via Velocity of innovation
A14: =$A$12 -> Hide | H14: Sourcing & Comments
A15: =$A$12 -> Hide | B15: Annual revenue | F15: =F4 -> 1000000000 | H15: =$H$4 -> From 10-k
A16: =$A$12 -> Hide | B16: Increase in revenue via accelerated innovation, better collaboration, and/or data locality | F16: =IF(D10="Yes",0.5%,0) -> 0 | H16: Placeholder estimate
A17: =$A$12 -> Hide | B17: Estimated incremental revenue | F17: =ROUND(F15*F16,0) -> 0 | H17: Calculation
A18: =$A$12 -> Hide | B18: Operating margin | F18: =F5 -> 0.1 | H18: =$H$5 -> From 10-k
A19: =$A$12 -> Hide | B19: Annual associated value | F19: =ROUND(F17*F18,0) -> 0 | H19: Calculation
A21: =IF('Initial Screens'!$C$8="Government","Show","hide") -> hide | B21: Include Avoided Lost Revenue | D21: =IF('Initial Screens'!$C$8="Government","No",IF(C21="","No",C21)) -> No | H21: Don't use if Government or non-profit
A23: =IF(AND($A$21="Show",$D$21="Yes"),"Show","Hide") -> Hide | B23: Avoided lost Revenue via Improved Application Performance
A24: =$A$23 -> Hide
A25: =$A$23 -> Hide | H25: Sourcing & Comments
A26: =$A$23 -> Hide | B26: Annual revenue | F26: =F4 -> 1000000000 | H26: =$H$4 -> From 10-k
A27: =$A$23 -> Hide | B27: Anticipated percent annual revenue growth via scale of customers and associated applications | F27: =ROUND(5%,3) -> 0.05 | H27: Placeholder Estimate
A28: =$A$23 -> Hide | B28: Estimated annual revenue based on new customer growth | F28: =ROUND(F26*F27,0) -> 50000000 | H28: Calculation
A29: =$A$23 -> Hide | B29: Percent of annual revenue growth at risk due to current architecture | F29: =ROUND(10%,3) -> 0.1 | H29: Placeholder estimate
A30: =$A$23 -> Hide | B30: Estimated annual growth revenue at risk | F30: =ROUND(F28*F29,0) -> 5000000 | H30: Calculation
A31: =$A$23 -> Hide | B31: Percent reduction in revenue at risk via modernization to improve application scale and performance | F31: =ROUND(IF(D21="Yes",75%,0),3) -> 0 | H31: Placeholder estimate
A32: =$A$23 -> Hide | B32: Estimated lost revenue recovered | F32: =ROUND(F30*F31,0) -> 0 | H32: Calculation
A33: =$A$23 -> Hide | B33: Operating margin | F33: =F5 -> 0.1 | H33: =$H$5 -> From 10-k
A34: =$A$23 -> Hide | B34: Annual associated value | F34: =ROUND(F32*F33,0) -> 0 | H34: Calculation
B36: Include Downtime Reduction? | C36: No | D36: =IF(C36="",IF(SUM(Misc!$C$121:$FM$121)>0,"Yes","No"),C36) -> No | G36: Return button | H36: Note to Mediafly: need inputs above here if not filled out for revenue (rows 2-8)
B38: Reduced Downtime | H38: Note to self.. Updated based on TEI report of VCF operations
A40: =IF(D36="Yes","Show","hide") -> hide | B40: Current State
A41: =$A$40 -> hide | B41: Estimated uptime | F41: =ROUND(99.7%,5) -> 0.997 | H41: Placeholder estimate
A42: =$A$40 -> hide | B42: Resultant down hours per year | F42: =ROUND(365*24*(1-F41),1) -> 26.3 | H42: Calculation
A43: =IF(AND(D36="Yes",AND('Initial Screens'!C13="VCF 9",'Initial Screens'!D21>0%)),"Show","hide") -> hide | B43: Impact on Internal Productivity
A44: =$A$43 -> hide | B44: Downtime effect on internal productivity | F44: =IF($A$43="Show",90%*(0.8*Misc!E136+0.2*Misc!E137),0%) -> 0 | H44: Placeholder estimate based on the VCF operations and automation coverage
A45: =$A$43 -> hide | B45: Percentage of FTEs impacted | F45: =IF($A$43="Show",5%,0%) -> 0 | H45: Placeholder estimate
A46: =$A$43 -> hide | B46: Estimated cost per downtime on internal producitivity | F46: =F42*F45*F6*F8*F44 -> 0 | H46: Calculation
A47: =IF(AND(D36="Yes",OR('Initial Screens'!D21>0%,'Initial Screens'!D29="Yes",'Initial Screens'!D26="Yes")),"Show","hide") -> hide | B47: Impact on Revenue
A48: =IF(AND(D36="Yes",OR('Initial Screens'!D22>0%,'Initial Screens'!D30="Yes",'Initial Screens'!D27="Yes")),"Show","hide") -> hide | B48: Downtime effect on sales/revenue | F48: =IF($A$47="Show",10%,0%) -> 0 | H48: Placeholder estimate
A49: =IF(AND(D36="Yes",OR('Initial Screens'!D23>0%,'Initial Screens'!D31="Yes",'Initial Screens'!D28="Yes")),"Show","hide") -> hide | B49: Estimated cost per down hour | F49: =IF('Initial Screens'!C8="Government",ROUND(F6*F8,0),ROUND(F4*F5/(365*24)*F48*F42,0)) -> 0 | H49: =IF('Initial Screens'!C8="Government","Estimate based on 'Number of employees' times 'Average fully burdened employee cost per hour (modeled with IT cost per hour)' ","Estimate based on 'Annual revenue' times 'Operating margin' divided by number of hours in a year (24 x 365)") -> Estimate based on 'Annual revenue' times 'Operating margin' divided by number of hours in a year (24 x 365)
A50: =$A$40 -> hide | B50: Annual Current State Cost | F50: =IF(D36="Yes",SUM(F46,F49*F42),0) -> 0 | H50: Calculation
A51: =$A$40 -> hide | B51: Future State
A52: =$A$40 -> hide | B52: Anticipated percent risk reduction via VMware | F52: =ROUND(IF(D36="Yes",MIN(70%,SUMPRODUCT(Misc!C121:H121,Misc!C124:H124)),0),2) -> 0 | H52: Placeholder estimate
A53: =$A$40 -> hide | B53: Annual Future State Cost | F53: =F50*(1-F52) -> 0 | H53: Calculation
A54: =$A$40 -> hide | B54: Annual associated value | F54: =F50-F53 -> 0 | H54: Calculation
B56: Include Security Breach Reduction? | D56: =IF(C56="",IF(SUM(Misc!$C$122:$F$122)>0,"Yes","No"),C56) -> No
B58: Reduced Risk of a Significant Security or Data Breach
H60: Sourcing & Comments
B61: Potential cost of a security breach (lost revenue, lost productivity, fines, lawsuits, etc.) | F61: =ROUND(Benchmarks!D91,0) -> 11660000 | H61: The 2024 Cost of a Data Breach Report by Ponemon Institute and IBM Security
B62: Annual percent risk of a breach (including due to use of open source data solutions) | F62: =ROUND(1/3,3) -> 0.333 | H62: ="Chance of a significant breach in next "&FIXED(1/F62,1)&" years" -> Chance of a significant breach in next 3.0 years
B63: Calculated annual risk value | F63: =ROUND(F61*F62,0) -> 3882780 | H63: Calculation
B64: Anticipated percent risk reduction of data breach (including due to open source DB via VMware) | F64: =ROUND(IF(D56="Yes",SUM(Misc!C122:F122),0),3) -> 0 | H64: Placeholder estimate
B65: Annual associated value | F65: =ROUND(F63*F64,0) -> 0 | H65: Calculation
B68: Include Ransomware Reduction? | D68: =IF(C68="",IF(SUM(Misc!$C$123:$F$123)>0,"Yes","No"),C68) -> No
B70: Reduced Risk (and associated costs) of a Successful Ransomware Attack
H72: Sourcing & Comments
B73: Potential cost of a successful ransomware attack | F73: =ROUND(F113,0) -> 10313813 | G73: Worksheet | H73: Placeholder estimate (see below for detail)
B74: Annual percent risk of a ransomware attack | F74: =ROUND(1/3,3) -> 0.333 | H74: ="Chance of a significant breach in next "&FIXED(1/F74,1)&" years" -> Chance of a significant breach in next 3.0 years
B75: Calculated annual risk value | F75: =ROUND(F73*F74,0) -> 3434500 | H75: Calculation
B76: Anticipated percent risk reduction via VMware | F76: =IF(D68="Yes",ROUND(SUM(Misc!C123:F123),3),0) -> 0 | H76: Placeholder estimate
B77: Annual associated value | F77: =ROUND(F75*F76,0) -> 0 | H77: Calculation
B80: Potential Cost of a Successful Ransomware Attack
B82: Hours lost per ransomware Recovery | F82: =ROUND(24*7,0) -> 168 | H82: Conservatively assumes 1 week (24 hours x 7 days)
B84: Lost Business | F84: =SUM(F87,F92) -> 6075888 | H84: Calculation
B85: Revenue loss from system downtime
B86: Estimated cost per down hour | F86: =IF('Initial Screens'!C8="Government",ROUND(F6*F8,0),ROUND(F4*F5/(365*24),0)) -> 11416 | H86: =IF('Initial Screens'!C8="Government","Estimate based on 'Number of employees' times 'Average fully burdened employee cost per hour (modeled with IT cost per hour)' ","Estimate based on 'Annual revenue' times 'Operating margin' divided by number of hours in a year (24 x 365)") -> Estimate based on 'Annual revenue' times 'Operating margin' divided by number of hours in a year (24 x 365)
B87: Total profit associated with revenue losses from system downtime | F87: =ROUND(F86*F82,0) -> 1917888 | H87: Calculation
B88: Impact on business operations
B89: % of Employees impacted by ransomware attack | F89: =ROUND(0.3,2) -> 0.3 | H89: Placeholder estimate
B90: Average cost per hour per employee | F90: =IF('Initial Screens'!C9="AMER",100,IF('Initial Screens'!C9="Latam",35,65)) -> 100 | H90: Placeholder estimate
B91: % of productivity Impact | F91: =ROUND(0.33,2) -> 0.33 | H91: Placeholder estimate
B92: Total Productivity Impact | F92: =F6*F89*F90*F91*F82 -> 4158000 | H92: Calculation
B94: Detection & Escalation | F94: =SUM(F98,F102) -> 709800 | H94: Calculation
B95: Cost of ransomware forensics
B96: Number of external forensic specialists involved | F96: =ROUND('Excel Output'!D22/500,2) -> 10 | H96: Estimate based on number of VMs divided by 500
B97: Average cost per hour for each forensic specialist | F97: 325 | H97: Various sources show a range from $200 to $450 per hour (for reference $2,500/day / 8 hr/day = $312.50)
B98: Total cost of external forensic specialists' time during downtime | F98: =F96*F97*F82 -> 546000 | H98: Calculation
B99: Cost of data recovery
B100: Number of employees involved | F100: =ROUND('Excel Output'!D22/500,2) -> 10 | H100: Estimate based on number of VMs divided by 500
B101: Average cost per hour per IT employee | F101: =ROUND(F8,2) -> 97.5 | H101: From above
B102: Total cost of Data Recovery | F102: =F101*F100*F82 -> 163800 | H102: Calculation
B104: Post Breach Response | F104: =SUM(F108,F110,F111) -> 3528125 | H104: Calculation, Includes Help desk and inbound communications, Credit monitoring and identity protection services, Legal expenditures, Product discounts, Regulatory fines
B105: Ransomware payments
B106: Estimated ransom payment to attackers | F106: =ROUND(228125,0) -> 228125 | H106: Average ransom payment $228,125, Median $36,360 per Coveware | I106: https://www.coveware.com/blog/2022/7/27/fewer-ransomware-victims-pay-as-medium-ransom-falls-in-q2-2022#:~:text=Average%20and%20Median%20Ransom%20Payment%20in%20Q2%202022&text=The%20average%20ransom%20payment%20increased,51%25%20decrease%20from%20Q1%202022.
B107: Cost of third-party digital security forensics services | F107: =250000 -> 250000 | H107: Placeholder Estimate
B108: Total Ransomware Payments | F108: =SUM(F106:F107) -> 478125 | H108: Calculation
B109: Fines, claims & expenses
B110: Regulatory Fines | F110: =ROUND(3%*F4*F5,0) -> 3000000 | H110: Estimate based on 3% of operating profit | I110: https://cybelangel.com/the-true-cost-of-a-ransomware-attack/
B111: Other Expenses | F111: =ROUND(0.05%*F4*F5,0) -> 50000 | H111: Estimate based on 0.05% of operating profit
B113: Total potential cost of successful ransomware attack | F113: =SUM(F84,F94,F104) -> 10313813 | H113: Calculation

Sheet ROI Results
B2: ROI Output
B3: =TODAY() -> 45982
B5: Multi-year Impact Summary
B7: Key Financial Metrics | H7: Weighted Average Cost of Capital | I7: 0.09 | J7: (i)
B8: =AnalysisTerm&"-Year Net Present Value (NPV)" -> 10-Year Net Present Value (NPV) | E8: =ROUND(NPV(I7,F47:K47)+E47,0) -> 31216461 | H8: Average Annual Growth | I8: =5% -> 0.05 | J8: (i)
B9: =AnalysisTerm&"-Year Return on Investment (ROI)" -> 10-Year Return on Investment (ROI) | E9: =ROUND(O47/O46,2) -> 9.75 | H9: Annual Inflation Adjustment | I9: =3% -> 0.03 | J9: (i)
B10: Payback | E10: =ROUND(O115,0)&" Months" -> 12 Months | I10: Review Value Realization
B11: Monthly cost of delayed customer buying decision | E11: =E8/(AnalysisTerm*12) -> 260137.17 | I11: Review Sustainability
H12: =IF(AnalysisTerm<=3,"hide column","show column") -> show column | I12: =IF(AnalysisTerm<=4,"hide column","show column") -> show column
B13: Net Benefits | E13: Year 1 | F13: Year 2 | G13: Year 3 | H13: =IF(AnalysisTerm>3,"Year 4","") -> Year 4 | I13: =IF(AnalysisTerm>4,"Year 5","") -> Year 5 | J13: =IF(AnalysisTerm>5,6,"") -> 6 | K13: =IF(AnalysisTerm>6,7,"") -> 7 | L13: =IF(AnalysisTerm>7,8,"") -> 8 | M13: =IF(AnalysisTerm>7,9,"") -> 9 | N13: =IF(AnalysisTerm>7,10,"") -> 10 | O13: Total
B14: Gross Benefits | E14: =SUM(E$21:E$31) -> 4145663.2 | F14: =SUM(F$21:F$31) -> 5136305.8 | G14: =SUM(G$21:G$31) -> 6130376.5 | H14: =SUM(H$21:H$31) -> 7258904.9 | I14: =SUM(I$21:I$31) -> 8537414 | J14: =SUM(J$21:J$31) -> 10144328 | K14: =SUM(K$21:K$31) -> 11819983 | L14: =SUM(L$21:L$31) -> 13571309 | ... N14: =SUM(N$21:N$31) -> 18086368 | O14: =ROUND(SUM(E14:N14),0) -> 100527811
B15: Estimated Investment | E15: =ROUND(SUM(E$37:E$41),0) -> 2750000 | F15: =ROUND(SUM(F$37:F$41),0) -> 1650000 | G15: =ROUND(SUM(G$37:G$41),0) -> 1650000 | H15: =ROUND(SUM(H$37:H$41),0) -> 1650000 | I15: =ROUND(SUM(I$37:I$41),0) -> 1650000 | J15: =ROUND(SUM(J$37:J$41),0) -> 0 | K15: =ROUND(SUM(K$37:K$41),0) -> 0 | L15: =ROUND(SUM(L$37:L$41),0) -> 0 | ... N15: =ROUND(SUM(N$37:N$41),0) -> 0 | O15: =ROUND(SUM(E15:N15),0) -> 9350000
B16: Net Benefit | E16: =ROUND(E14-E15,0) -> 1395663 | F16: =ROUND(F14-F15,0) -> 3486306 | G16: =ROUND(G14-G15,0) -> 4480377 | H16: =ROUND(H14-H15,0) -> 5608905 | I16: =ROUND(I14-I15,0) -> 6887414 | J16: =ROUND(J14-J15,0) -> 10144328 | K16: =ROUND(K14-K15,0) -> 11819983 | O16: =ROUND(O14-O15,0) -> 91177811
B18: Multi-year Impact Detail
H19: =IF(AnalysisTerm<=3,"hide column","show column") -> show column | I19: =IF(AnalysisTerm<=4,"hide column","show column") -> show column | J19: =IF(AnalysisTerm<=5,"hide column","show column") -> show column | K19: =IF(AnalysisTerm<=5,"hide column","show column") -> show column
B20: Gross Benefits | E20: Year 1 | F20: Year 2 | G20: Year 3 | H20: =IF(AnalysisTerm>3,"Year 4","") -> Year 4 | I20: =IF(AnalysisTerm>4,"Year 5","") -> Year 5 | J20: =$J$13 -> 6 | K20: =K$13 -> 7 | L20: =L$13 -> 8 | M20: =M$13 -> 9 | N20: =N$13 -> 10 | O20: Total
B21: ='ROI Results'!B56 -> Compute | E21: ='ROI Results'!E71-'ROI Results'!E85 -> 1870202.5 | F21: ='ROI Results'!F71-'ROI Results'!F85 -> 2114761.8 | G21: ='ROI Results'!G71-'ROI Results'!G85 -> 2390410.4 | H21: =IF(AnalysisTerm>3,'ROI Results'!H71-'ROI Results'!H85,"") -> 2700700.8 | I21: =IF(AnalysisTerm>3,'ROI Results'!I71-'ROI Results'!I85,"") -> 3049561.5 | J21: =IF(AnalysisTerm>5,'ROI Results'!J71-'ROI Results'!J85,"") -> 3441334.6 | K21: =IF(AnalysisTerm>5,'ROI Results'!K71-'ROI Results'!K85,"") -> 3880817 | L21: =IF(AnalysisTerm>7,'ROI Results'!L71-'ROI Results'!L85,"") -> 4373306.4 | M21: =IF(AnalysisTerm>7,'ROI Results'!M71-'ROI Results'!M85,"") -> 4924650.6 | N21: =IF(AnalysisTerm>7,'ROI Results'!N71-'ROI Results'!N85,"") -> 5541302.5 | O21: =ROUND(SUM(E21:N21),0) -> 34287048
B22: ='ROI Results'!B57 -> Storage | E22: ='ROI Results'!E72-'ROI Results'!E86 -> 959281.5 | F22: ='ROI Results'!F72-'ROI Results'!F86 -> 1061769.4 | G22: ='ROI Results'!G72-'ROI Results'!G86 -> 1176505.8 | H22: =IF(AnalysisTerm>3,'ROI Results'!H72-'ROI Results'!H86,"") -> 1304863.9 | I22: =IF(AnalysisTerm>3,'ROI Results'!I72-'ROI Results'!I86,"") -> 1448361.2 | J22: =IF(AnalysisTerm>5,'ROI Results'!J72-'ROI Results'!J86,"") -> 1608673.6 | K22: =IF(AnalysisTerm>5,'ROI Results'!K72-'ROI Results'!K86,"") -> 1787651.6 | L22: =IF(AnalysisTerm>7,'ROI Results'!L72-'ROI Results'!L86,"") -> 1987337.6 | M22: =IF(AnalysisTerm>7,'ROI Results'!M72-'ROI Results'!M86,"") -> 2209984.6 | N22: =IF(AnalysisTerm>7,'ROI Results'!N72-'ROI Results'!N86,"") -> 2458077.8 | O22: =ROUND(SUM(E22:N22),0) -> 16002507
B23: ='ROI Results'!B58 -> Network | E23: ='ROI Results'!E73-'ROI Results'!E87 -> 187432.91 | F23: ='ROI Results'!F73-'ROI Results'!F87 -> 211751.64 | G23: ='ROI Results'!G73-'ROI Results'!G87 -> 239155.35 | H23: =IF(AnalysisTerm>3,'ROI Results'!H73-'ROI Results'!H87,"") -> 269996.35 | I23: =IF(AnalysisTerm>3,'ROI Results'!I73-'ROI Results'!I87,"") -> 304664.2 | J23: =IF(AnalysisTerm>5,'ROI Results'!J73-'ROI Results'!J87,"") -> 343589.48 | K23: =IF(AnalysisTerm>5,'ROI Results'!K73-'ROI Results'!K87,"") -> 387247.88 | L23: =IF(AnalysisTerm>7,'ROI Results'!L73-'ROI Results'!L87,"") -> 436164.69 | M23: =IF(AnalysisTerm>7,'ROI Results'!M73-'ROI Results'!M87,"") -> 490919.78 | N23: =IF(AnalysisTerm>7,'ROI Results'!N73-'ROI Results'!N87,"") -> 552152.98 | O23: =ROUND(SUM(E23:N23),0) -> 3423075
B24: ='ROI Results'!B59 -> Software | E24: ='ROI Results'!E74-'ROI Results'!E88+E37 -> 361859.2 | F24: ='ROI Results'!F74-'ROI Results'!F88+F37 -> 386859.2 | G24: ='ROI Results'!G74-'ROI Results'!G88+G37 -> 413109.2 | H24: =IF(AnalysisTerm>3,'ROI Results'!H74-'ROI Results'!H88+H37,"") -> 440671.7 | I24: =IF(AnalysisTerm>3,'ROI Results'!I74-'ROI Results'!I88+I37,"") -> 469612.32 | J24: =IF(AnalysisTerm>5,'ROI Results'!J74-'ROI Results'!J88+J37,"") -> 499999.98 | K24: =IF(AnalysisTerm>5,'ROI Results'!K74-'ROI Results'!K88+K37,"") -> 531907.02 | L24: =IF(AnalysisTerm>7,'ROI Results'!L74-'ROI Results'!L88,"") -> 565409.41 | M24: =IF(AnalysisTerm>7,'ROI Results'!M74-'ROI Results'!M88,"") -> 600586.92 | N24: =IF(AnalysisTerm>7,'ROI Results'!N74-'ROI Results'!N88,"") -> 637523.31 | O24: =ROUND(SUM(E24:N24),0) -> 4907538
B25: ='ROI Results'!B60 -> Facilities | E25: ='ROI Results'!E75-'ROI Results'!E89 -> 168911.16 | F25: ='ROI Results'!F75-'ROI Results'!F89 -> 365354.85 | G25: ='ROI Results'!G75-'ROI Results'!G89 -> 592696.9 | H25: =IF(AnalysisTerm>3,'ROI Results'!H75-'ROI Results'!H89,"") -> 854668.93 | I25: =IF(AnalysisTerm>3,'ROI Results'!I75-'ROI Results'!I89,"") -> 1155405.6 | J25: =IF(AnalysisTerm>5,'ROI Results'!J75-'ROI Results'!J89,"") -> 1574459.6 | K25: =IF(AnalysisTerm>5,'ROI Results'!K75-'ROI Results'!K89,"") -> 1986574.4 | L25: =IF(AnalysisTerm>7,'ROI Results'!L75-'ROI Results'!L89,"") -> 2455406 | M25: =IF(AnalysisTerm>7,'ROI Results'!M75-'ROI Results'!M89,"") -> 2987461.8 | N25: =IF(AnalysisTerm>7,'ROI Results'!N75-'ROI Results'!N89,"") -> 3589933.2 | O25: =ROUND(SUM(E25:N25),0) -> 15730872
B26: ='ROI Results'!B61 -> Labor | E26: ='ROI Results'!E76-'ROI Results'!E90 -> 215210.29 | F26: ='ROI Results'!F76-'ROI Results'!F90 -> 465499.85 | G26: ='ROI Results'!G76-'ROI Results'!G90 -> 755157.14 | H26: =IF(AnalysisTerm>3,'ROI Results'!H76-'ROI Results'!H90,"") -> 1088936.6 | I26: =IF(AnalysisTerm>3,'ROI Results'!I76-'ROI Results'!I90,"") -> 1472106.2 | J26: =IF(AnalysisTerm>5,'ROI Results'!J76-'ROI Results'!J90,"") -> 2006024.3 | K26: =IF(AnalysisTerm>5,'ROI Results'!K76-'ROI Results'!K90,"") -> 2531101.2 | L26: =IF(AnalysisTerm>7,'ROI Results'!L76-'ROI Results'!L90,"") -> 3128441.1 | M26: =IF(AnalysisTerm>7,'ROI Results'!M76-'ROI Results'!M90,"") -> 3806335.2 | N26: =IF(AnalysisTerm>7,'ROI Results'!N76-'ROI Results'!N90,"") -> 4573946.1 | O26: =ROUND(SUM(E26:N26),0) -> 20042758
B27: ='ROI Results'!B62 -> Support | E27: ='ROI Results'!E77 -> 125000 | F27: ='ROI Results'!F77 -> 125000 | G27: ='ROI Results'!G77 -> 125000 | H27: =IF(AnalysisTerm>3,'ROI Results'!H77,"") -> 125000 | I27: =IF(AnalysisTerm>3,'ROI Results'!I77,"") -> 125000 | J27: =IF(AnalysisTerm>5,'ROI Results'!J77,"") -> 125000 | K27: =IF(AnalysisTerm>5,'ROI Results'!K77,"") -> 125000 | L27: =IF(AnalysisTerm>7,'ROI Results'!L77-'ROI Results'!L91,"") -> -12500 | M27: =IF(AnalysisTerm>7,'ROI Results'!M77-'ROI Results'!M91,"") -> -12500 | N27: =IF(AnalysisTerm>7,'ROI Results'!N77-'ROI Results'!N91,"") -> -12500 | O27: =ROUND(SUM(E27:N27),0) -> 837500
B28: ='ROI Results'!B63 -> Migration | E28: ='ROI Results'!E78-IF('Migration - Reskilling'!$F$14>$O$38,'ROI Results'!E92,0) -> 374765.62 | F28: ='ROI Results'!F78-IF('Migration - Reskilling'!$F$14>$O$38,'ROI Results'!F92,0) -> 405309.02 | G28: ='ROI Results'!G78-IF('Migration - Reskilling'!$F$14>$O$38,'ROI Results'!G92,0) -> 438341.71 | H28: =IF(AnalysisTerm>3,'ROI Results'!H78-IF('Migration - Reskilling'!$F$14>$O$38,'ROI Results'!H92,0),"") -> 474066.56 | I28: =IF(AnalysisTerm>3,'ROI Results'!I78-IF('Migration - Reskilling'!$F$14>$O$38,'ROI Results'!I92,0),"") -> 512702.98 | J28: =IF(AnalysisTerm>5,'ROI Results'!J78-IF('Migration - Reskilling'!$F$14>$O$38,'ROI Results'!J92,0),"") -> 545246.8 | K28: =IF(AnalysisTerm>5,'ROI Results'!K78-IF('Migration - Reskilling'!$F$14>$O$38,'ROI Results'!K92,0),"") -> 589684.42 | L28: =IF(AnalysisTerm>7,'ROI Results'!L78-'ROI Results'!L92,"") -> 637743.7 | M28: =IF(AnalysisTerm>7,'ROI Results'!M78-'ROI Results'!M92,"") -> 689719.81 | N28: =IF(AnalysisTerm>7,'ROI Results'!N78-'ROI Results'!N92,"") -> 745931.98 | O28: =ROUND(SUM(E28:N28),0) -> 5413513
B29: ='ROI Results'!B64 -> One-time Reskilling | E29: ='ROI Results'!E79-IF('Migration - Reskilling'!$F$29>$O$39,'ROI Results'!E93,0) -> -117000 | F29: ='ROI Results'!F79-IF('Migration - Reskilling'!$F$29>$O$39,'ROI Results'!F93,0) -> 0 | G29: ='ROI Results'!G79-IF('Migration - Reskilling'!$F$29>$O$39,'ROI Results'!G93,0) -> 0 | H29: =IF(AnalysisTerm>3,'ROI Results'!H79-IF('Migration - Reskilling'!$F$29>$O$39,'ROI Results'!H93,0),"") -> 0 | I29: =IF(AnalysisTerm>3,'ROI Results'!I79-IF('Migration - Reskilling'!$F$29>$O$39,'ROI Results'!I93,0),"") -> 0 | J29: =IF(AnalysisTerm>5,'ROI Results'!J79-IF('Migration - Reskilling'!$F$29>$O$39,'ROI Results'!J93,0),"") -> 0 | K29: =IF(AnalysisTerm>5,'ROI Results'!K79-IF('Migration - Reskilling'!$F$29>$O$39,'ROI Results'!K93,0),"") -> 0 | L29: =IF(AnalysisTerm>7,'ROI Results'!L79-'ROI Results'!L93,"") -> 0 | M29: =IF(AnalysisTerm>7,'ROI Results'!M79-'ROI Results'!M93,"") -> 0 | N29: =IF(AnalysisTerm>7,'ROI Results'!N79-'ROI Results'!N93,"") -> 0 | O29: =ROUND(SUM(E29:N29),0) -> -117000
B30: ='ROI Results'!B65 -> Revenue Impact | E30: ='ROI Results'!E94 -> 0 | F30: ='ROI Results'!F94 -> 0 | G30: ='ROI Results'!G94 -> 0 | H30: ='ROI Results'!H94 -> 0 | I30: ='ROI Results'!I94 -> 0 | J30: ='ROI Results'!J94 -> 0 | K30: ='ROI Results'!K94 -> 0 | L30: ='ROI Results'!L94 -> 0 | ... N30: ='ROI Results'!N94 -> 0 | O30: =ROUND(SUM(E30:N30),0) -> 0 | Q30: <-- growth and inflation NOT applied to revenue impact?
B31: ='ROI Results'!B66 -> Risk Reduction | E31: ='ROI Results'!E95 -> 0 | F31: ='ROI Results'!F95 -> 0 | G31: ='ROI Results'!G95 -> 0 | H31: ='ROI Results'!H95 -> 0 | I31: ='ROI Results'!I95 -> 0 | J31: ='ROI Results'!J95 -> 0 | K31: ='ROI Results'!K95 -> 0 | L31: ='ROI Results'!L95 -> 0 | ... N31: ='ROI Results'!N95 -> 0 | O31: =ROUND(SUM(E31:N31),0) -> 0 | Q31: <-- growth and inflation NOT applied to risk reduction?
B32: Total Gross Benefits | E32: =ROUND(SUM(E21:E31),0) -> 4145663 | F32: =ROUND(SUM(F21:F31),0) -> 5136306 | G32: =ROUND(SUM(G21:G31),0) -> 6130377 | H32: =ROUND(SUM(H21:H31),0) -> 7258905 | I32: =ROUND(SUM(I21:I31),0) -> 8537414 | J32: =ROUND(SUM(J21:J31),0) -> 10144328 | K32: =ROUND(SUM(K21:K31),0) -> 11819983 | L32: =ROUND(SUM(L21:L31),0) -> 13571309 | ... N32: =ROUND(SUM(N21:N31),0) -> 18086368 | O32: =SUM(O21:O31) -> 100527811
B34: ="Estimated VCF discount (to be used in competitive comparison)" -> Estimated VCF discount (to be used in competitive comparison) | F34: 0.25 | G34: (i) | P34: <-- required input, not less than 0%, nothing greater than 100%
H35: =IF(AnalysisTerm<=3,"hide column","show column") -> show column | I35: =IF(AnalysisTerm<=4,"hide column","show column") -> show column | J35: =IF(AnalysisTerm<=5,"hide column","show column") -> show column | K35: =IF(AnalysisTerm<=5,"hide column","show column") -> show column | L35: =IF(AnalysisTerm<=7,"hide column","show column") -> show column | M35: =IF(AnalysisTerm<=7,"hide column","show column") -> show column | N35: =IF(AnalysisTerm<=7,"hide column","show column") -> show column
B36: =InvestmentBVA!B9 -> Estimated Investment | E36: Year 1 | F36: Year 2 | G36: Year 3 | H36: =IF(AnalysisTerm>3,"Year 4","") -> Year 4 | I36: =IF(AnalysisTerm>4,"Year 5","") -> Year 5 | J36: =$J$13 -> 6 | K36: =K$13 -> 7 | L36: =L$13 -> 8 | M36: =M$13 -> 9 | N36: =N$13 -> 10 | O36: Total
A37: (i) | B37: Subscription | E37: 1500000 | F37: 1500000 | G37: 1500000 | H37: 1500000 | I37: 1500000 | O37: =ROUND(SUM(E37:N37),0) -> 7500000 | Q37: any values in yellow input cells for illustration only
B38: Professional Services | E38: 1000000 | O38: =ROUND(SUM(E38:N38),0) -> 1000000
B39: Education / Training | E39: 100000 | O39: =ROUND(SUM(E39:N39),0) -> 100000
B40: TAM / SAM / DTSE | E40: 150000 | F40: 150000 | G40: 150000 | H40: 150000 | I40: 150000 | O40: =ROUND(SUM(E40:N40),0) -> 750000
A41: hide | B41: Other | O41: =ROUND(SUM(E41:N41),0) -> 0
B42: Total Investment | E42: =SUM(E37:E41) -> 2750000 | F42: =SUM(F37:F41) -> 1650000 | G42: =SUM(G37:G41) -> 1650000 | H42: =IF(AnalysisTerm>3,SUM(H37:H41),0) -> 1650000 | I42: =IF(AnalysisTerm>4,SUM(I37:I41),0) -> 1650000 | J42: =IF(AnalysisTerm>5,SUM(J37:J41),0) -> 0 | K42: =IF(AnalysisTerm>6,SUM(K37:K41),0) -> 0 | L42: =IF(AnalysisTerm>6,SUM(L37:L41),0) -> 0 | M42: =IF(AnalysisTerm>6,SUM(M37:M41),0) -> 0 | N42: =IF(AnalysisTerm>6,SUM(N37:N41),0) -> 0 | O42: =SUM(O37:O41) -> 9350000
H43: =IF(AnalysisTerm<=3,"hide column","show column") -> show column | I43: =IF(AnalysisTerm<=4,"hide column","show column") -> show column | J43: =IF(AnalysisTerm<=5,"hide column","show column") -> show column | K43: =IF(AnalysisTerm<=5,"hide column","show column") -> show column | L43: =$L$35 -> show column | M43: =$L$35 -> show column | N43: =$L$35 -> show column
B44: Net Benefits | E44: Year 1 | F44: Year 2 | G44: Year 3 | H44: =IF(AnalysisTerm>3,"Year 4","") -> Year 4 | I44: =IF(AnalysisTerm>4,"Year 5","") -> Year 5 | J44: =$J$13 -> 6 | K44: =K$13 -> 7 | L44: =L$13 -> 8 | M44: =M$13 -> 9 | N44: =N$13 -> 10 | O44: Total
B45: =B20 -> Gross Benefits | E45: =E32 -> 4145663 | F45: =F32 -> 5136306 | G45: =G32 -> 6130377 | H45: =IF(AnalysisTerm>3,H32,0) -> 7258905 | I45: =IF(AnalysisTerm>4,I32,0) -> 8537414 | J45: =IF(AnalysisTerm>5,J32,0) -> 10144328 | K45: =IF(AnalysisTerm>6,K32,0) -> 11819983 | L45: =IF(AnalysisTerm>7,L32,0) -> 13571309 | M45: =IF(AnalysisTerm>7,M32,0) -> 15697159 | N45: =IF(AnalysisTerm>7,N32,0) -> 18086368 | O45: =SUM(E45:N45) -> 100527812
B46: =B36 -> Estimated Investment | E46: =E42 -> 2750000 | F46: =F42 -> 1650000 | G46: =G42 -> 1650000 | H46: =IF(AnalysisTerm>3,H42,0) -> 1650000 | I46: =IF(AnalysisTerm>4,I42,0) -> 1650000 | J46: =IF(AnalysisTerm>5,J42,0) -> 0 | K46: =IF(AnalysisTerm>6,K42,0) -> 0 | L46: =IF(AnalysisTerm>6,L42,0) -> 0 | M46: =IF(AnalysisTerm>6,M42,0) -> 0 | N46: =IF(AnalysisTerm>6,N42,0) -> 0 | O46: =SUM(E46:N46) -> 9350000
B47: Net Benefit | E47: =E45-E46 -> 1395663 | F47: =F45-F46 -> 3486306 | G47: =G45-G46 -> 4480377 | H47: =IF(AnalysisTerm>3,H45-H46,"") -> 5608905 | I47: =IF(AnalysisTerm>4,I45-I46,"") -> 6887414 | J47: =IF(AnalysisTerm>5,J45-J46,"") -> 10144328 | K47: =IF(AnalysisTerm>6,K45-K46,"") -> 11819983 | L47: =IF(AnalysisTerm>6,L45-L46,"") -> 13571309 | M47: =IF(AnalysisTerm>6,M45-M46,"") -> 15697159 | N47: =IF(AnalysisTerm>6,N45-N46,"") -> 18086368 | O47: =O45-O46 -> 91177812
B48: VMware Disclaimer: Although great care has been and will be taken to ensure the accuracy and completeness of this model. VMware will be unable to accept any legal responsibility for any actions taken based on the information contained herein and VMware makes no warranties of any kind.
B51: Incremental Value Realization by Year (Infrastructure items tied to migration percent per year)
B52: All values based on analysis term (3 or 5 years) except Revenue Impact and Risk Reduction (which are based on annualized impact).
B53: Hardware Refresh Cycle (Years) | E53: {=_xlfn.SWITCH(AnalysisTerm,3,3,5,5,7,5,10,5)} -> 5 | F53: =1/E53 -> 0.2
H54: =IF(AnalysisTerm<=3,"hide column","show column") -> show column | I54: =IF(AnalysisTerm<=4,"hide column","show column") -> show column | J54: =J43 -> show column | K54: =K43 -> show column | L54: =L43 -> show column | M54: =M43 -> show column | N54: =N43 -> show column
B55: Value Component/ Deployment Plan | E55: Year 1 | F55: Year 2 | G55: Year 3 | H55: =IF(AnalysisTerm>3,"Year 4","") -> Year 4 | I55: =IF(AnalysisTerm>3,"Year 5","") -> Year 5 | J55: =$J$13 -> 6 | K55: =K$13 -> 7 | L55: =L$13 -> 8 | M55: =M$13 -> 9 | N55: =N$13 -> 10 | O55: Total
B56: Compute | E56: =ROUND(1/AnalysisTerm,3) -> 0.1 | F56: =ROUND(1/AnalysisTerm,3) -> 0.1 | G56: =ROUND(1/AnalysisTerm,3) -> 0.1 | H56: =IF(AnalysisTerm>3,ROUND(1/AnalysisTerm,3),"") -> 0.1 | I56: =IF(AnalysisTerm>3,ROUND(1/AnalysisTerm,3),"") -> 0.1 | J56: =IF(AnalysisTerm>5,ROUND(1/AnalysisTerm,3),"") -> 0.1 | K56: =IF(AnalysisTerm>5,ROUND(1/AnalysisTerm,3),"") -> 0.1 | L56: =IF(AnalysisTerm>7,ROUND(1/AnalysisTerm,3),"") -> 0.1 | M56: =IF(AnalysisTerm>7,ROUND(1/AnalysisTerm,3),"") -> 0.1 | N56: =IF(AnalysisTerm>7,ROUND(1/AnalysisTerm,3),"") -> 0.1 | O56: =ROUND(SUM(E56:K56),0) -> 1
B57: Storage | E57: =ROUND(1/AnalysisTerm,3) -> 0.1 | F57: =ROUND(1/AnalysisTerm,3) -> 0.1 | G57: =ROUND(1/AnalysisTerm,3) -> 0.1 | H57: =IF(AnalysisTerm>3,ROUND(1/AnalysisTerm,3),"") -> 0.1 | I57: =IF(AnalysisTerm>3,ROUND(1/AnalysisTerm,3),"") -> 0.1 | J57: =IF(AnalysisTerm>5,ROUND(1/AnalysisTerm,3),"") -> 0.1 | K57: =IF(AnalysisTerm>5,ROUND(1/AnalysisTerm,3),"") -> 0.1 | L57: =IF(AnalysisTerm>7,ROUND(1/AnalysisTerm,3),"") -> 0.1 | M57: =IF(AnalysisTerm>7,ROUND(1/AnalysisTerm,3),"") -> 0.1 | N57: =IF(AnalysisTerm>7,ROUND(1/AnalysisTerm,3),"") -> 0.1 | O57: =ROUND(SUM(E57:K57),0) -> 1
B58: Network | E58: =ROUND(1/AnalysisTerm,3) -> 0.1 | F58: =ROUND(1/AnalysisTerm,3) -> 0.1 | G58: =ROUND(1/AnalysisTerm,3) -> 0.1 | H58: =IF(AnalysisTerm>3,ROUND(1/AnalysisTerm,3),"") -> 0.1 | I58: =IF(AnalysisTerm>3,ROUND(1/AnalysisTerm,3),"") -> 0.1 | J58: =IF(AnalysisTerm>5,ROUND(1/AnalysisTerm,3),"") -> 0.1 | K58: =IF(AnalysisTerm>5,ROUND(1/AnalysisTerm,3),"") -> 0.1 | L58: =IF(AnalysisTerm>7,ROUND(1/AnalysisTerm,3),"") -> 0.1 | M58: =IF(AnalysisTerm>7,ROUND(1/AnalysisTerm,3),"") -> 0.1 | N58: =IF(AnalysisTerm>7,ROUND(1/AnalysisTerm,3),"") -> 0.1 | O58: =ROUND(SUM(E58:K58),0) -> 1
A59: (i) | B59: Software | E59: =ROUND(1/AnalysisTerm,3) -> 0.1 | F59: =ROUND(1/AnalysisTerm,3) -> 0.1 | G59: =ROUND(1/AnalysisTerm,3) -> 0.1 | H59: =IF(AnalysisTerm>3,ROUND(1/AnalysisTerm,3),"") -> 0.1 | I59: =IF(AnalysisTerm>3,ROUND(1/AnalysisTerm,3),"") -> 0.1 | J59: =IF(AnalysisTerm>5,ROUND(1/AnalysisTerm,3),"") -> 0.1 | K59: =IF(AnalysisTerm>5,ROUND(1/AnalysisTerm,3),"") -> 0.1 | L59: =IF(AnalysisTerm>7,ROUND(1/AnalysisTerm,3),"") -> 0.1 | M59: =IF(AnalysisTerm>7,ROUND(1/AnalysisTerm,3),"") -> 0.1 | N59: =IF(AnalysisTerm>7,ROUND(1/AnalysisTerm,3),"") -> 0.1 | O59: =ROUND(SUM(E59:K59),0) -> 1
B60: Facilities | E60: =ROUND(1/AnalysisTerm,3) -> 0.1 | F60: =ROUND(1/AnalysisTerm,3) -> 0.1 | G60: =ROUND(1/AnalysisTerm,3) -> 0.1 | H60: =IF(AnalysisTerm>3,ROUND(1/AnalysisTerm,3),"") -> 0.1 | I60: =IF(AnalysisTerm>3,ROUND(1/AnalysisTerm,3),"") -> 0.1 | J60: =IF(AnalysisTerm>5,ROUND(1/AnalysisTerm,3),"") -> 0.1 | K60: =IF(AnalysisTerm>5,ROUND(1/AnalysisTerm,3),"") -> 0.1 | L60: =IF(AnalysisTerm>7,ROUND(1/AnalysisTerm,3),"") -> 0.1 | M60: =IF(AnalysisTerm>7,ROUND(1/AnalysisTerm,3),"") -> 0.1 | N60: =IF(AnalysisTerm>7,ROUND(1/AnalysisTerm,3),"") -> 0.1 | O60: =ROUND(SUM(E60:K60),0) -> 1
B61: Labor | E61: =ROUND(1/AnalysisTerm,3) -> 0.1 | F61: =ROUND(1/AnalysisTerm,3) -> 0.1 | G61: =ROUND(1/AnalysisTerm,3) -> 0.1 | H61: =IF(AnalysisTerm>3,ROUND(1/AnalysisTerm,3),"") -> 0.1 | I61: =IF(AnalysisTerm>3,ROUND(1/AnalysisTerm,3),"") -> 0.1 | J61: =IF(AnalysisTerm>5,ROUND(1/AnalysisTerm,3),"") -> 0.1 | K61: =IF(AnalysisTerm>5,ROUND(1/AnalysisTerm,3),"") -> 0.1 | L61: =IF(AnalysisTerm>7,ROUND(1/AnalysisTerm,3),"") -> 0.1 | M61: =IF(AnalysisTerm>7,ROUND(1/AnalysisTerm,3),"") -> 0.1 | N61: =IF(AnalysisTerm>7,ROUND(1/AnalysisTerm,3),"") -> 0.1 | O61: =ROUND(SUM(E61:K61),0) -> 1
A62: (i) | B62: Support | E62: 1 | F62: 0 | G62: 0 | H62: 0 | I62: 0 | J62: 0 | K62: 0 | L62: 0 | M62: 0 | N62: 0 | O62: =ROUND(SUM(E62:K62),0) -> 1
B63: Migration | E63: =ROUND(1/AnalysisTerm,3) -> 0.1 | F63: =ROUND(1/AnalysisTerm,3) -> 0.1 | G63: =ROUND(1/AnalysisTerm,3) -> 0.1 | H63: =IF(AnalysisTerm>3,ROUND(1/AnalysisTerm,3),"") -> 0.1 | I63: =IF(AnalysisTerm>3,ROUND(1/AnalysisTerm,3),"") -> 0.1 | J63: =IF(AnalysisTerm>5,ROUND(1/AnalysisTerm,3),"") -> 0.1 | K63: =IF(AnalysisTerm>5,ROUND(1/AnalysisTerm,3),"") -> 0.1 | L63: =IF(AnalysisTerm>7,ROUND(1/AnalysisTerm,3),"") -> 0.1 | M63: =IF(AnalysisTerm>7,ROUND(1/AnalysisTerm,3),"") -> 0.1 | N63: =IF(AnalysisTerm>7,ROUND(1/AnalysisTerm,3),"") -> 0.1 | O63: =ROUND(SUM(E63:K63),0) -> 1
B64: One-time Reskilling | E64: 1 | F64: 0 | G64: 0 | H64: 0 | I64: 0 | J64: 0 | K64: 0 | L64: 0 | M64: 0 | N64: 0 | O64: =ROUND(SUM(E64:K64),0) -> 1
A65: (i) | B65: Revenue Impact | E65: 0 | F65: 0.15 | G65: 0.4 | H65: 0 | I65: 0 | J65: 0 | K65: 0 | L65: 0 | M65: 0 | N65: 0
A66: (i) | B66: Risk Reduction | E66: =ROUND(1/AnalysisTerm,3) -> 0.1 | F66: =ROUND(2/AnalysisTerm,3) -> 0.2 | G66: =ROUND(3/AnalysisTerm,3) -> 0.3 | H66: =IF(AnalysisTerm>3,ROUND(4/AnalysisTerm,3),"") -> 0.4 | I66: =IF(AnalysisTerm>3,ROUND(5/AnalysisTerm,3),"") -> 0.5 | J66: =IF(AnalysisTerm>5,ROUND(6/AnalysisTerm,3),"") -> 0.6 | K66: =IF(AnalysisTerm>5,ROUND(7/AnalysisTerm,3),"") -> 0.7 | L66: =IF(AnalysisTerm>7,ROUND(8/AnalysisTerm,3),"") -> 0.8 | M66: =IF(AnalysisTerm>7,ROUND(9/AnalysisTerm,3),"") -> 0.9 | N66: =IF(AnalysisTerm>7,ROUND(10/AnalysisTerm,3),"") -> 1
B68: Intermediate Calcluations
H69: =IF(AnalysisTerm<=3,"hide column","show column") -> show column | I69: =IF(AnalysisTerm<=4,"hide column","show column") -> show column | J69: =J$54 -> show column | K69: =K$54 -> show column | L69: =L$54 -> show column | M69: =M$54 -> show column | N69: =N$54 -> show column
B70: Ongoing current state (TCO) | C70: CapEx | D70: OpEx | E70: Year 1 | F70: Year 2 | G70: Year 3 | H70: =IF(AnalysisTerm>3,"Year 4","") -> Year 4 | I70: =IF(AnalysisTerm>3,5,"") -> 5 | J70: =$J$13 -> 6 | K70: =K$13 -> 7 | L70: =L$13 -> 8 | M70: =M$13 -> 9 | N70: =N$13 -> 10 | O70: Total
B71: =B56 -> Compute | C71: =Compute!F12/(1+AnalysisTerm*Compute!F11)+Compute!F76/(1+AnalysisTerm*Compute!F75)+Compute!F96+Compute!F126/(1+AnalysisTerm*Compute!F125) -> 10475000 | D71: =Compute!F12/(1+AnalysisTerm*Compute!F11)*AnalysisTerm*Compute!F11+Compute!F76/(1+AnalysisTerm*Compute!F75)*AnalysisTerm*Compute!F75+Compute!F96*Compute!F99*AnalysisTerm+Compute!F126/(1+AnalysisTerm*Compute!F125)*AnalysisTerm -> 19750000 | E71: =(Hardware_Refreshcylce+Growth)*$C71+$D71/AnalysisTerm*(1+Growth) -> 4692500 | F71: =((Hardware_Refreshcylce+(1+Growth)^2-(1+Growth))*$C71+$D71/AnalysisTerm*(1+Growth)^2)*(1+Inflation)^1 -> 4967046.2 | G71: =((Hardware_Refreshcylce+(1+Growth)^3-(1+Growth)^2)*$C71+$D71/AnalysisTerm*(1+Growth)^3)*(1+Inflation)^2 -> 5260731.2 | H71: =IF(AnalysisTerm>3,((Hardware_Refreshcylce+(1+Growth)^4-(1+Growth)^3)*$C71+$D71/AnalysisTerm*(1+Growth)^4)*(1+Inflation)^3,"") -> 5575017.7 | I71: =IF(AnalysisTerm>3,((Hardware_Refreshcylce+(1+Growth)^5-(1+Growth)^4)*$C71+$D71/AnalysisTerm*(1+Growth)^5)*(1+Inflation)^4,"") -> 5911484.6 | J71: =IF(AnalysisTerm>$I$70,((Hardware_Refreshcylce+(1+Growth)^J$70-(1+Growth)^I$70)*$C71+$D71/AnalysisTerm*(1+Growth)^J$70)*(1+Inflation)^I$70,"") -> 6271836.6 | K71: =IF(AnalysisTerm>$I$70,((Hardware_Refreshcylce+(1+Growth)^K$70-(1+Growth)^J$70)*$C71+$D71/AnalysisTerm*(1+Growth)^K$70)*(1+Inflation)^J$70,"") -> 6657914.3 | L71: =IF(AnalysisTerm>$K$70,((Hardware_Refreshcylce+(1+Growth)^L$70-(1+Growth)^K$70)*$C71+$D71/AnalysisTerm*(1+Growth)^L$70)*(1+Inflation)^K$70,"") -> 7071705.1 | M71: =IF(AnalysisTerm>$K$70,((Hardware_Refreshcylce+(1+Growth)^M$70-(1+Growth)^L$70)*$C71+$D71/AnalysisTerm*(1+Growth)^M$70)*(1+Inflation)^L$70,"") -> 7515354.8 | N71: =IF(AnalysisTerm>$K$70,((Hardware_Refreshcylce+(1+Growth)^N$70-(1+Growth)^M$70)*$C71+$D71/AnalysisTerm*(1+Growth)^N$70)*(1+Inflation)^M$70,"") -> 7991181.3 | O71: =SUM(E71:N71) -> 61914772 | Q71: <-- growth applied in all years, inflation applied year 2+
B72: =B57 -> Storage | C72: =Storage!F21/(1+AnalysisTerm*Storage!F20)+Compute!F97 -> 4785714 | D72: =Storage!F21/(1+AnalysisTerm*Storage!F20)*AnalysisTerm*Storage!F20+Compute!F97*Compute!F99*AnalysisTerm -> 7178571 | E72: =(Hardware_Refreshcylce+Growth)*$C72+$D72/AnalysisTerm*(1+Growth) -> 1950178.5 | F72: =((Hardware_Refreshcylce+(1+Growth)^2-(1+Growth))*$C72+$D72/AnalysisTerm*(1+Growth)^2)*(1+Inflation)^1 -> 2059825.1 | G72: =((Hardware_Refreshcylce+(1+Growth)^3-(1+Growth)^2)*$C72+$D72/AnalysisTerm*(1+Growth)^3)*(1+Inflation)^2 -> 2176929.3 | H72: =IF(AnalysisTerm>3,((Hardware_Refreshcylce+(1+Growth)^4-(1+Growth)^3)*$C72+$D72/AnalysisTerm*(1+Growth)^4)*(1+Inflation)^3,"") -> 2302054.2 | I72: =IF(AnalysisTerm>3,((Hardware_Refreshcylce+(1+Growth)^5-(1+Growth)^4)*$C72+$D72/AnalysisTerm*(1+Growth)^5)*(1+Inflation)^4,"") -> 2435808 | J72: =IF(AnalysisTerm>$I$70,((Hardware_Refreshcylce+(1+Growth)^J$70-(1+Growth)^I$70)*$C72+$D72/AnalysisTerm*(1+Growth)^J$70)*(1+Inflation)^I$70,"") -> 2578846.8 | K72: =IF(AnalysisTerm>$I$70,((Hardware_Refreshcylce+(1+Growth)^K$70-(1+Growth)^J$70)*$C72+$D72/AnalysisTerm*(1+Growth)^K$70)*(1+Inflation)^J$70,"") -> 2731878.9 | L72: =IF(AnalysisTerm>$K$70,((Hardware_Refreshcylce+(1+Growth)^L$70-(1+Growth)^K$70)*$C72+$D72/AnalysisTerm*(1+Growth)^L$70)*(1+Inflation)^K$70,"") -> 2895668.8 | M72: =IF(AnalysisTerm>$K$70,((Hardware_Refreshcylce+(1+Growth)^M$70-(1+Growth)^L$70)*$C72+$D72/AnalysisTerm*(1+Growth)^M$70)*(1+Inflation)^L$70,"") -> 3071041.8 | N72: =IF(AnalysisTerm>$K$70,((Hardware_Refreshcylce+(1+Growth)^N$70-(1+Growth)^M$70)*$C72+$D72/AnalysisTerm*(1+Growth)^N$70)*(1+Inflation)^M$70,"") -> 3258889 | O72: =SUM(E72:N72) -> 25461120 | Q72: <-- growth applied in all years, inflation applied year 2+
B73: =B58 -> Network | C73: =Network!F11/(1+AnalysisTerm*Network!F10)+Network!F29/(1+AnalysisTerm*Network!F28)+Network!F51/(1+AnalysisTerm*Network!F50)+Compute!F98+Compute!F127/(1+AnalysisTerm*Compute!F125) -> 1047500 | D73: =Network!F11/(1+AnalysisTerm*Network!F10)*AnalysisTerm*Network!F10+Network!F29/(1+AnalysisTerm*Network!F28)*AnalysisTerm*Network!F28+Network!F51/(1+AnalysisTerm*Network!F50)*AnalysisTerm*Network!F50+Compute!F98*Compute!F99*AnalysisTerm+Compute!F128/(1+AnalysisTerm*Compute!F125)*AnalysisTerm -> 1958432 | E73: =(Hardware_Refreshcylce+Growth)*$C73+$D73/AnalysisTerm*(1+Growth) -> 467510.36 | F73: =((Hardware_Refreshcylce+(1+Growth)^2-(1+Growth))*$C73+$D73/AnalysisTerm*(1+Growth)^2)*(1+Inflation)^1 -> 494823.2 | G73: =((Hardware_Refreshcylce+(1+Growth)^3-(1+Growth)^2)*$C73+$D73/AnalysisTerm*(1+Growth)^3)*(1+Inflation)^2 -> 524038.37 | H73: =IF(AnalysisTerm>3,((Hardware_Refreshcylce+(1+Growth)^4-(1+Growth)^3)*$C73+$D73/AnalysisTerm*(1+Growth)^4)*(1+Inflation)^3,"") -> 555301.18 | I73: =IF(AnalysisTerm>3,((Hardware_Refreshcylce+(1+Growth)^5-(1+Growth)^4)*$C73+$D73/AnalysisTerm*(1+Growth)^5)*(1+Inflation)^4,"") -> 588768.52 | J73: =IF(AnalysisTerm>$I$70,((Hardware_Refreshcylce+(1+Growth)^J$70-(1+Growth)^I$70)*$C73+$D73/AnalysisTerm*(1+Growth)^J$70)*(1+Inflation)^I$70,"") -> 624609.76 | K73: =IF(AnalysisTerm>$I$70,((Hardware_Refreshcylce+(1+Growth)^K$70-(1+Growth)^J$70)*$C73+$D73/AnalysisTerm*(1+Growth)^K$70)*(1+Inflation)^J$70,"") -> 663007.76 | L73: =IF(AnalysisTerm>$K$70,((Hardware_Refreshcylce+(1+Growth)^L$70-(1+Growth)^K$70)*$C73+$D73/AnalysisTerm*(1+Growth)^L$70)*(1+Inflation)^K$70,"") -> 704159.96 | M73: =IF(AnalysisTerm>$K$70,((Hardware_Refreshcylce+(1+Growth)^M$70-(1+Growth)^L$70)*$C73+$D73/AnalysisTerm*(1+Growth)^M$70)*(1+Inflation)^L$70,"") -> 748279.58 | N73: =IF(AnalysisTerm>$K$70,((Hardware_Refreshcylce+(1+Growth)^N$70-(1+Growth)^M$70)*$C73+$D73/AnalysisTerm*(1+Growth)^N$70)*(1+Inflation)^M$70,"") -> 795596.87 | O73: =SUM(E73:N73) -> 6166095.6 | Q73: <-- growth applied in all years, inflation applied year 2+
B74: =B59 -> Software | C74: n/a | D74: =Software!F7+Software!F18+Software!F30 -> 2762815.6 | E74: =Software!$F$5+(Software!$F$18+Software!$F$30)/AnalysisTerm*(1+Growth) -> 500000 | F74: =Software!$F$5*(1+Software!$F$6)+(Software!$F$18+Software!$F$30)/AnalysisTerm*(1+Growth)^2*(1+Inflation)^1 -> 525000 | G74: =Software!$F$5*(1+Software!$F$6)^2+(Software!$F$18+Software!$F$30)/AnalysisTerm*(1+Growth)^3*(1+Inflation)^2 -> 551250 | H74: =IF(AnalysisTerm>3,Software!$F$5*(1+Software!$F$6)^3+(Software!$F$18+Software!$F$30)/AnalysisTerm*(1+Growth)^4*(1+Inflation)^3,"") -> 578812.5 | I74: =IF(AnalysisTerm>3,Software!$F$5*(1+Software!$F$6)^4+(Software!$F$18+Software!$F$30)/AnalysisTerm*(1+Growth)^5*(1+Inflation)^4,"") -> 607753.12 | J74: =IF(AnalysisTerm>$I$70,Software!$F$5*(1+Software!$F$6)^I$70+(Software!$F$18+Software!$F$30)/AnalysisTerm*(1+Growth)^J$70*(1+Inflation)^I$70,"") -> 638140.78 | K74: =IF(AnalysisTerm>$I$70,Software!$F$5*(1+Software!$F$6)^J$70+(Software!$F$18+Software!$F$30)/AnalysisTerm*(1+Growth)^K$70*(1+Inflation)^J$70,"") -> 670047.82 | L74: =IF(AnalysisTerm>$K$70,Software!$F$5*(1+Software!$F$6)^K$70+(Software!$F$18+Software!$F$30)/AnalysisTerm*(1+Growth)^L$70*(1+Inflation)^K$70,"") -> 703550.21 | M74: =IF(AnalysisTerm>$K$70,Software!$F$5*(1+Software!$F$6)^L$70+(Software!$F$18+Software!$F$30)/AnalysisTerm*(1+Growth)^M$70*(1+Inflation)^L$70,"") -> 738727.72 | N74: =IF(AnalysisTerm>$K$70,Software!$F$5*(1+Software!$F$6)^M$70+(Software!$F$18+Software!$F$30)/AnalysisTerm*(1+Growth)^N$70*(1+Inflation)^M$70,"") -> 775664.11 | O74: =SUM(E74:N74) -> 6288946.3 | Q74: <-- growth and inflation not applied to VMware SW, otherwise growth applied in all years, inflation applied year 2+
B75: =B60 -> Facilities | C75: n/a | D75: =Facilities!F13+Compute!F128 -> 24242608 | E75: =$D75/AnalysisTerm*(1+Growth/2) -> 2484867.3 | F75: =$D75/AnalysisTerm*(1+Growth/2)*(1+Growth)*(1+Inflation)^1 -> 2687384 | G75: =$D75/AnalysisTerm*(1+Growth/2)*(1+Growth)^2*(1+Inflation)^2 -> 2906405.8 | H75: =IF(AnalysisTerm>3,$D75/AnalysisTerm*(1+Growth/2)*(1+Growth)^3*(1+Inflation)^3,"") -> 3143277.9 | I75: =IF(AnalysisTerm>3,$D75/AnalysisTerm*(1+Growth/2)*(1+Growth)^4*(1+Inflation)^4,"") -> 3399455 | J75: =IF(AnalysisTerm>$I$70,$D75/AnalysisTerm*(1+Growth/2)*(1+Growth)^J$70*(1+Inflation)^I$70,"") -> 3860336.1 | K75: =IF(AnalysisTerm>$I$70,$D75/AnalysisTerm*(1+Growth/2)*(1+Growth)^K$70*(1+Inflation)^J$70,"") -> 4174953.5 | L75: =IF(AnalysisTerm>$K$70,$D75/AnalysisTerm*(1+Growth/2)*(1+Growth)^L$70*(1+Inflation)^K$70,"") -> 4515212.2 | M75: =IF(AnalysisTerm>$K$70,$D75/AnalysisTerm*(1+Growth/2)*(1+Growth)^M$70*(1+Inflation)^L$70,"") -> 4883202 | N75: =IF(AnalysisTerm>$K$70,$D75/AnalysisTerm*(1+Growth/2)*(1+Growth)^N$70*(1+Inflation)^M$70,"") -> 5281183 | O75: =SUM(E75:N75) -> 37336277 | Q75: <-- growth applied in all years, but only 50% of growth in year 1, inflation applied year 2+
B76: =B61 -> Labor | C76: n/a | D76: =Labor!F127 -> 44760535 | E76: =$D76/AnalysisTerm*(1+Growth/2) -> 4587954.8 | F76: =$D76/AnalysisTerm*(1+Growth/2)*(1+Growth)*(1+Inflation)^1 -> 4961873.2 | G76: =$D76/AnalysisTerm*(1+Growth/2)*(1+Growth)^2*(1+Inflation)^2 -> 5366265.8 | H76: =IF(AnalysisTerm>3,$D76/AnalysisTerm*(1+Growth/2)*(1+Growth)^3*(1+Inflation)^3,"") -> 5803616.5 | I76: =IF(AnalysisTerm>3,$D76/AnalysisTerm*(1+Growth/2)*(1+Growth)^4*(1+Inflation)^4,"") -> 6276611.2 | J76: =IF(AnalysisTerm>$I$70,$D76/AnalysisTerm*(1+Growth/2)*(1+Growth)^J$70*(1+Inflation)^I$70,"") -> 7127562.8 | K76: =IF(AnalysisTerm>$I$70,$D76/AnalysisTerm*(1+Growth/2)*(1+Growth)^K$70*(1+Inflation)^J$70,"") -> 7708459.2 | L76: =IF(AnalysisTerm>$K$70,$D76/AnalysisTerm*(1+Growth/2)*(1+Growth)^L$70*(1+Inflation)^K$70,"") -> 8336698.6 | M76: =IF(AnalysisTerm>$K$70,$D76/AnalysisTerm*(1+Growth/2)*(1+Growth)^M$70*(1+Inflation)^L$70,"") -> 9016139.5 | N76: =IF(AnalysisTerm>$K$70,$D76/AnalysisTerm*(1+Growth/2)*(1+Growth)^N$70*(1+Inflation)^M$70,"") -> 9750954.9 | O76: =SUM(E76:N76) -> 68936136 | Q76: <-- growth applied in all years, but only 50% of growth in year 1, inflation applied year 2+
B77: =B62 -> Support | C77: n/a | D77: =Support!F7 -> 1250000 | E77: =$D77/AnalysisTerm -> 125000 | F77: =$D77/AnalysisTerm -> 125000 | G77: =$D77/AnalysisTerm -> 125000 | H77: =IF(AnalysisTerm>3,$D77/AnalysisTerm,"") -> 125000 | I77: =IF(AnalysisTerm>3,$D77/AnalysisTerm,"") -> 125000 | J77: =IF(AnalysisTerm>$I$70,$D77/AnalysisTerm,"") -> 125000 | K77: =IF(AnalysisTerm>$I$70,$D77/AnalysisTerm,"") -> 125000 | L77: =IF(AnalysisTerm>$K$70,$D77/AnalysisTerm,"") -> 125000 | M77: =IF(AnalysisTerm>$K$70,$D77/AnalysisTerm,"") -> 125000 | N77: =IF(AnalysisTerm>$K$70,$D77/AnalysisTerm,"") -> 125000 | O77: =SUM(E77:N77) -> 1250000 | Q77: <-- growth and inflation NOT applied to VMware Support
B78: =B63 -> Migration | C78: ='Migration - Reskilling'!F11 -> 4875000 | D78: n/a | E78: =$C78/AnalysisTerm*(1+Growth/2) -> 499687.5 | F78: =$C78/AnalysisTerm*(1+Growth/2)*(1+Growth)*(1+Inflation)^1 -> 540412.03 | G78: =$C78/AnalysisTerm*(1+Growth/2)*(1+Growth)^2*(1+Inflation)^2 -> 584455.61 | H78: =IF(AnalysisTerm>3,$C78/AnalysisTerm*(1+Growth/2)*(1+Growth)^3*(1+Inflation)^3,"") -> 632088.74 | I78: =IF(AnalysisTerm>3,$C78/AnalysisTerm*(1+Growth/2)*(1+Growth)^4*(1+Inflation)^4,"") -> 683603.98 | J78: =IF(AnalysisTerm>$I$70,$C78/AnalysisTerm*(1+Growth/2)*(1+Growth)^I$70*(1+Inflation)^I$70,"") -> 739317.7 | K78: =IF(AnalysisTerm>$I$70,$C78/AnalysisTerm*(1+Growth/2)*(1+Growth)^J$70*(1+Inflation)^J$70,"") -> 799572.09 | L78: =IF(AnalysisTerm>$K$70,$C78/AnalysisTerm*(1+Growth/2)*(1+Growth)^K$70*(1+Inflation)^K$70,"") -> 864737.22 | M78: =IF(AnalysisTerm>$K$70,$C78/AnalysisTerm*(1+Growth/2)*(1+Growth)^L$70*(1+Inflation)^L$70,"") -> 935213.3 | N78: =IF(AnalysisTerm>$K$70,$C78/AnalysisTerm*(1+Growth/2)*(1+Growth)^M$70*(1+Inflation)^M$70,"") -> 1011433.2 | O78: =SUM(E78:N78) -> 7290521.4 | Q78: <-- growth applied in all years, but only 50% of growth in year 1, inflation applied year 2+
B79: =B64 -> One-time Reskilling | C79: n/a | D79: ='Migration - Reskilling'!F23 -> 39000 | E79: =$D$79*E64 -> 39000 | F79: =$D$79*F64 -> 0 | G79: =$D$79*G64 -> 0 | H79: =IF(AnalysisTerm>3,$D$79*H64,"") -> 0 | I79: =IF(AnalysisTerm>3,$D$79*I64,"") -> 0 | J79: =IF(AnalysisTerm>$I$70,$D$79*J64,"") -> 0 | K79: =IF(AnalysisTerm>$I$70,$D$79*K64,"") -> 0 | L79: =IF(AnalysisTerm>$K$70,$D$79*L64,"") -> 0 | M79: =IF(AnalysisTerm>$K$70,$D$79*M64,"") -> 0 | N79: =IF(AnalysisTerm>$K$70,$D$79*N64,"") -> 0 | O79: =SUM(E79:N79) -> 39000 | Q79: <-- growth and inflation NOT applied to reskilling
B80: =B65 -> Revenue Impact | C80: n/a | D80: n/a | E80: n/a | F80: n/a | G80: n/a | H80: =IF(AnalysisTerm>3,"n/a","") -> n/a | I80: =IF(AnalysisTerm>3,"n/a","") -> n/a | J80: =IF(AnalysisTerm>5,"n/a","") -> n/a | K80: =IF(AnalysisTerm>5,"n/a","") -> n/a | L80: =IF(AnalysisTerm>7,"n/a","") -> n/a | M80: =IF(AnalysisTerm>7,"n/a","") -> n/a | N80: =IF(AnalysisTerm>7,"n/a","") -> n/a | O80: =IF(AnalysisTerm>5,"n/a","") -> n/a
B81: =B66 -> Risk Reduction | C81: n/a | D81: n/a | E81: n/a | F81: n/a | G81: n/a | H81: =IF(AnalysisTerm>3,"n/a","") -> n/a | I81: =IF(AnalysisTerm>3,"n/a","") -> n/a | J81: =IF(AnalysisTerm>5,"n/a","") -> n/a | K81: =IF(AnalysisTerm>5,"n/a","") -> n/a | L81: =IF(AnalysisTerm>7,"n/a","") -> n/a | M81: =IF(AnalysisTerm>7,"n/a","") -> n/a | N81: =IF(AnalysisTerm>7,"n/a","") -> n/a | O81: =IF(AnalysisTerm>5,"n/a","") -> n/a
C83: Target Future State | H83: =IF(AnalysisTerm<=3,"hide column","show column") -> show column | I83: =IF(AnalysisTerm<=4,"hide column","show column") -> show column | J83: =J$54 -> show column | K83: =K$54 -> show column | L83: =L$54 -> show column | M83: =M$54 -> show column | N83: =N$54 -> show column
B84: Future State Brownfield (TCO) | C84: CapEx | D84: OpEx | E84: Year 1 | F84: Year 2 | G84: Year 3 | H84: =IF(AnalysisTerm>3,4,"") -> 4 | I84: =IF(AnalysisTerm>3,5,"") -> 5 | J84: =$J$13 -> 6 | K84: =K$13 -> 7 | L84: =L$13 -> 8 | M84: =M$13 -> 9 | N84: =N$13 -> 10 | O84: Total
B85: =B56 -> Compute | C85: =Compute!F24/(1+AnalysisTerm*Compute!F23)+Compute!F86/(1+AnalysisTerm*Compute!F85)+Compute!F108+Compute!F135*(1+AnalysisTerm*Compute!F125) -> 3596987.5 | D85: =Compute!F24/(1+AnalysisTerm*Compute!F23)*AnalysisTerm*Compute!F23+Compute!F86/(1+AnalysisTerm*Compute!F85)*AnalysisTerm*Compute!F85+Compute!F108*AnalysisTerm*Compute!F111+Compute!F135/(1+AnalysisTerm*Compute!F125)*AnalysisTerm -> 5397680 | E85: =(Hardware_Refreshcylce+Growth)*$C85+MIN(SUM($E56:E56),1)*$D85*(1+Growth)/AnalysisTerm+(1-MIN(SUM($E56:E56),1))*$D71*(1+Growth)/AnalysisTerm -> 2822297.5 | F85: =((Hardware_Refreshcylce+(1+Growth)^2-(1+Growth))*$C85+MIN(SUM($E56:F56),1)*$D85*(1+Growth)^2/AnalysisTerm+(1-MIN(SUM($E56:F56),1))*$D71*(1+Growth)^2/AnalysisTerm)*(1+Inflation)^1 -> 2852284.4 | G85: =((Hardware_Refreshcylce+(1+Growth)^3-(1+Growth)^2)*$C85+MIN(SUM($E56:G56),1)*$D85*(1+Growth)^3/AnalysisTerm+(1-MIN(SUM($E56:G56),1))*$D71*(1+Growth)^3/AnalysisTerm)*(1+Inflation)^2 -> 2870320.8 | H85: =IF(AnalysisTerm>3,((Hardware_Refreshcylce+(1+Growth)^4-(1+Growth)^3)*$C85+MIN(SUM($E56:H56),1)*$D85*(1+Growth)^4/AnalysisTerm+(1-MIN(SUM($E56:H56),1))*$D71*(1+Growth)^4/AnalysisTerm)*(1+Inflation)^3,"") -> 2874316.8 | I85: =IF(AnalysisTerm>3,((Hardware_Refreshcylce+(1+Growth)^5-(1+Growth)^4)*$C85+MIN(SUM($E56:I56),1)*$D85*(1+Growth)^5/AnalysisTerm+(1-MIN(SUM($E56:I56),1))*$D71*(1+Growth)^5/AnalysisTerm)*(1+Inflation)^4,"") -> 2861923 | J85: =IF(AnalysisTerm>5,((Hardware_Refreshcylce+(1+Growth)^J$84-(1+Growth)^I$84)*$C85+MIN(SUM($E56:J56),1)*$D85*(1+Growth)^J$84/AnalysisTerm+(1-MIN(SUM($E56:J56),1))*$D71*(1+Growth)^J$84/AnalysisTerm)*(1+Inflation)^I$84,"") -> 2830502.1 | K85: =IF(AnalysisTerm>5,((Hardware_Refreshcylce+(1+Growth)^K$84-(1+Growth)^J$84)*$C85+MIN(SUM($E56:K56),1)*$D85*(1+Growth)^K$84/AnalysisTerm+(1-MIN(SUM($E56:K56),1))*$D71*(1+Growth)^K$84/AnalysisTerm)*(1+Inflation)^J$84,"") -> 2777097.4 | L85: =IF(AnalysisTerm>$K$84,((Hardware_Refreshcylce+(1+Growth)^L$84-(1+Growth)^K$84)*$C85+MIN(SUM($E56:L56),1)*$D85*(1+Growth)^L$84/AnalysisTerm+(1-MIN(SUM($E56:L56),1))*$D71*(1+Growth)^L$84/AnalysisTerm)*(1+Inflation)^K$84,"") -> 2698398.7 | M85: =IF(AnalysisTerm>$K$84,((Hardware_Refreshcylce+(1+Growth)^M$84-(1+Growth)^L$84)*$C85+MIN(SUM($E56:M56),1)*$D85*(1+Growth)^M$84/AnalysisTerm+(1-MIN(SUM($E56:M56),1))*$D71*(1+Growth)^M$84/AnalysisTerm)*(1+Inflation)^L$84,"") -> 2590704.2 | N85: =IF(AnalysisTerm>$K$84,((Hardware_Refreshcylce+(1+Growth)^N$84-(1+Growth)^M$84)*$C85+MIN(SUM($E56:N56),1)*$D85*(1+Growth)^N$84/AnalysisTerm+(1-MIN(SUM($E56:N56),1))*$D71*(1+Growth)^N$84/AnalysisTerm)*(1+Inflation)^M$84,"") -> 2449878.8 | O85: =SUM(E85:N85) -> 27627724 | Q85: <-- growth applied in all years, inflation applied year 2+
B86: =B57 -> Storage | C86: =Storage!F34/(1+AnalysisTerm*Storage!F33)+Compute!F109 -> 1176000 | D86: =Storage!F34/(1+AnalysisTerm*Storage!F33)*AnalysisTerm*Storage!F33+Compute!F109*AnalysisTerm*Compute!F111 -> 1764000 | E86: =(Hardware_Refreshcylce+Growth)*$C86+MIN(SUM($E57:E57),1)*$D86*(1+Growth)/AnalysisTerm+(1-MIN(SUM($E57:E57),1))*$D72*(1+Growth)/AnalysisTerm -> 990896.96 | F86: =((Hardware_Refreshcylce+(1+Growth)^2-(1+Growth))*$C86+MIN(SUM($E57:F57),1)*$D86*(1+Growth)^2/AnalysisTerm+(1-MIN(SUM($E57:F57),1))*$D72*(1+Growth)^2/AnalysisTerm)*(1+Inflation)^1 -> 998055.75 | G86: =((Hardware_Refreshcylce+(1+Growth)^3-(1+Growth)^2)*$C86+MIN(SUM($E57:G57),1)*$D86*(1+Growth)^3/AnalysisTerm+(1-MIN(SUM($E57:G57),1))*$D72*(1+Growth)^3/AnalysisTerm)*(1+Inflation)^2 -> 1000423.4 | H86: =IF(AnalysisTerm>3,((Hardware_Refreshcylce+(1+Growth)^4-(1+Growth)^3)*$C86+MIN(SUM($E57:H57),1)*$D86*(1+Growth)^4/AnalysisTerm+(1-MIN(SUM($E57:H57),1))*$D72*(1+Growth)^4/AnalysisTerm)*(1+Inflation)^3,"") -> 997190.26 | I86: =IF(AnalysisTerm>3,((Hardware_Refreshcylce+(1+Growth)^5-(1+Growth)^4)*$C86+MIN(SUM($E57:I57),1)*$D86*(1+Growth)^5/AnalysisTerm+(1-MIN(SUM($E57:I57),1))*$D72*(1+Growth)^5/AnalysisTerm)*(1+Inflation)^4,"") -> 987446.8 | J86: =IF(AnalysisTerm>5,((Hardware_Refreshcylce+(1+Growth)^J$84-(1+Growth)^I$84)*$C86+MIN(SUM($E57:J57),1)*$D86*(1+Growth)^J$84/AnalysisTerm+(1-MIN(SUM($E57:J57),1))*$D72*(1+Growth)^J$84/AnalysisTerm)*(1+Inflation)^I$84,"") -> 970173.23 | K86: =IF(AnalysisTerm>5,((Hardware_Refreshcylce+(1+Growth)^K$84-(1+Growth)^J$84)*$C86+MIN(SUM($E57:K57),1)*$D86*(1+Growth)^K$84/AnalysisTerm+(1-MIN(SUM($E57:K57),1))*$D72*(1+Growth)^K$84/AnalysisTerm)*(1+Inflation)^J$84,"") -> 944227.29 | L86: =IF(AnalysisTerm>$K$84,((Hardware_Refreshcylce+(1+Growth)^L$84-(1+Growth)^K$84)*$C86+MIN(SUM($E57:L57),1)*$D86*(1+Growth)^L$84/AnalysisTerm+(1-MIN(SUM($E57:L57),1))*$D72*(1+Growth)^L$84/AnalysisTerm)*(1+Inflation)^K$84,"") -> 908331.21 | M86: =IF(AnalysisTerm>$K$84,((Hardware_Refreshcylce+(1+Growth)^M$84-(1+Growth)^L$84)*$C86+MIN(SUM($E57:M57),1)*$D86*(1+Growth)^M$84/AnalysisTerm+(1-MIN(SUM($E57:M57),1))*$D72*(1+Growth)^M$84/AnalysisTerm)*(1+Inflation)^L$84,"") -> 861057.12 | N86: =IF(AnalysisTerm>$K$84,((Hardware_Refreshcylce+(1+Growth)^N$84-(1+Growth)^M$84)*$C86+MIN(SUM($E57:N57),1)*$D86*(1+Growth)^N$84/AnalysisTerm+(1-MIN(SUM($E57:N57),1))*$D72*(1+Growth)^N$84/AnalysisTerm)*(1+Inflation)^M$84,"") -> 800811.21 | O86: =SUM(E86:N86) -> 9458613.3 | Q86: <-- growth applied in all years, inflation applied year 2+
B87: =B58 -> Network | C87: =Network!F19/(1+AnalysisTerm*Network!F18)+Network!F34/(1+AnalysisTerm*Network!F33)+Network!F56/(1+AnalysisTerm*Network!F55)+Compute!F110 -> 357500 | D87: =Network!F19/(1+AnalysisTerm*Network!F18)*AnalysisTerm*Network!F18+Network!F34/(1+AnalysisTerm*Network!F33)*AnalysisTerm*Network!F33+Network!F56/(1+AnalysisTerm*Network!F55)*AnalysisTerm*Network!F55+Compute!F110*AnalysisTerm*Compute!F111 -> 536250 | E87: =(Hardware_Refreshcylce+Growth)*$C87+MIN(SUM($E58:E58),1)*$D87*(1+Growth)/AnalysisTerm+(1-MIN(SUM($E58:E58),1))*$D73*(1+Growth)/AnalysisTerm -> 280077.45 | F87: =((Hardware_Refreshcylce+(1+Growth)^2-(1+Growth))*$C87+MIN(SUM($E58:F58),1)*$D87*(1+Growth)^2/AnalysisTerm+(1-MIN(SUM($E58:F58),1))*$D73*(1+Growth)^2/AnalysisTerm)*(1+Inflation)^1 -> 283071.57 | G87: =((Hardware_Refreshcylce+(1+Growth)^3-(1+Growth)^2)*$C87+MIN(SUM($E58:G58),1)*$D87*(1+Growth)^3/AnalysisTerm+(1-MIN(SUM($E58:G58),1))*$D73*(1+Growth)^3/AnalysisTerm)*(1+Inflation)^2 -> 284883.02 | H87: =IF(AnalysisTerm>3,((Hardware_Refreshcylce+(1+Growth)^4-(1+Growth)^3)*$C87+MIN(SUM($E58:H58),1)*$D87*(1+Growth)^4/AnalysisTerm+(1-MIN(SUM($E58:H58),1))*$D73*(1+Growth)^4/AnalysisTerm)*(1+Inflation)^3,"") -> 285304.83 | I87: =IF(AnalysisTerm>3,((Hardware_Refreshcylce+(1+Growth)^5-(1+Growth)^4)*$C87+MIN(SUM($E58:I58),1)*$D87*(1+Growth)^5/AnalysisTerm+(1-MIN(SUM($E58:I58),1))*$D73*(1+Growth)^5/AnalysisTerm)*(1+Inflation)^4,"") -> 284104.32 | J87: =IF(AnalysisTerm>5,((Hardware_Refreshcylce+(1+Growth)^J$84-(1+Growth)^I$84)*$C87+MIN(SUM($E58:J58),1)*$D87*(1+Growth)^J$84/AnalysisTerm+(1-MIN(SUM($E58:J58),1))*$D73*(1+Growth)^J$84/AnalysisTerm)*(1+Inflation)^I$84,"") -> 281020.27 | K87: =IF(AnalysisTerm>5,((Hardware_Refreshcylce+(1+Growth)^K$84-(1+Growth)^J$84)*$C87+MIN(SUM($E58:K58),1)*$D87*(1+Growth)^K$84/AnalysisTerm+(1-MIN(SUM($E58:K58),1))*$D73*(1+Growth)^K$84/AnalysisTerm)*(1+Inflation)^J$84,"") -> 275759.88 | L87: =IF(AnalysisTerm>$K$84,((Hardware_Refreshcylce+(1+Growth)^L$84-(1+Growth)^K$84)*$C87+MIN(SUM($E58:L58),1)*$D87*(1+Growth)^L$84/AnalysisTerm+(1-MIN(SUM($E58:L58),1))*$D73*(1+Growth)^L$84/AnalysisTerm)*(1+Inflation)^K$84,"") -> 267995.27 | M87: =IF(AnalysisTerm>$K$84,((Hardware_Refreshcylce+(1+Growth)^M$84-(1+Growth)^L$84)*$C87+MIN(SUM($E58:M58),1)*$D87*(1+Growth)^M$84/AnalysisTerm+(1-MIN(SUM($E58:M58),1))*$D73*(1+Growth)^M$84/AnalysisTerm)*(1+Inflation)^L$84,"") -> 257359.8 | N87: =IF(AnalysisTerm>$K$84,((Hardware_Refreshcylce+(1+Growth)^N$84-(1+Growth)^M$84)*$C87+MIN(SUM($E58:N58),1)*$D87*(1+Growth)^N$84/AnalysisTerm+(1-MIN(SUM($E58:N58),1))*$D73*(1+Growth)^N$84/AnalysisTerm)*(1+Inflation)^M$84,"") -> 243443.88 | O87: =SUM(E87:N87) -> 2743020.3 | Q87: <-- growth applied in all years, inflation applied year 2+
B88: =B59 -> Software | C88: n/a | D88: ='ROI Results'!O37+Software!F21+Software!F34+Software!F10 -> 8881408 | E88: ='ROI Results'!E37+(MIN(SUM($E59:E59),1)*(Software!$F$21+Software!$F$34)/AnalysisTerm+(1-MIN(SUM($E59:E59),1))*(Software!$F$18+Software!$F$30)/AnalysisTerm)*(1+Growth)+Software!$F$10/AnalysisTerm -> 1638140.8 | F88: ='ROI Results'!F37+(MIN(SUM($E59:F59),1)*(Software!$F$21+Software!$F$34)/AnalysisTerm+(1-MIN(SUM($E59:F59),1))*(Software!$F$18+Software!$F$30)/AnalysisTerm)*(1+Growth)^2*(1+Inflation)^1+Software!$F$10/AnalysisTerm -> 1638140.8 | G88: ='ROI Results'!G37+(MIN(SUM($E59:G59),1)*(Software!$F$21+Software!$F$34)/AnalysisTerm+(1-MIN(SUM($E59:G59),1))*(Software!$F$18+Software!$F$30)/AnalysisTerm)*(1+Growth)^3*(1+Inflation)^2+Software!$F$10/AnalysisTerm -> 1638140.8 | H88: =IF(AnalysisTerm>3,'ROI Results'!H37+(MIN(SUM($E59:H59),1)*(Software!$F$21+Software!$F$34)/AnalysisTerm+(1-MIN(SUM($E59:H59),1))*(Software!$F$18+Software!$F$30)/AnalysisTerm)*(1+Growth)^4*(1+Inflation)^3+Software!$F$10/AnalysisTerm,"") -> 1638140.8 | I88: =IF(AnalysisTerm>3,'ROI Results'!I37+(MIN(SUM($E59:I59),1)*(Software!$F$21+Software!$F$34)/AnalysisTerm+(1-MIN(SUM($E59:I59),1))*(Software!$F$18+Software!$F$30)/AnalysisTerm)*(1+Growth)^5*(1+Inflation)^4+Software!$F$10/AnalysisTerm,"") -> 1638140.8 | J88: =IF(AnalysisTerm>5,'ROI Results'!J37+(MIN(SUM($E59:J59),1)*(Software!$F$21+Software!$F$34)/AnalysisTerm+(1-MIN(SUM($E59:J59),1))*(Software!$F$18+Software!$F$30)/AnalysisTerm)*(1+Growth)^J$84*(1+Inflation)^I$84+Software!$F$10/AnalysisTerm,"") -> 138140.8 | K88: =IF(AnalysisTerm>5,'ROI Results'!K37+(MIN(SUM($E59:K59),1)*(Software!$F$21+Software!$F$34)/AnalysisTerm+(1-MIN(SUM($E59:K59),1))*(Software!$F$18+Software!$F$30)/AnalysisTerm)*(1+Growth)^K$84*(1+Inflation)^J$84+Software!$F$10/AnalysisTerm,"") -> 138140.8 | L88: =IF(AnalysisTerm>$K$84,'ROI Results'!L37+(MIN(SUM($E59:L59),1)*(Software!$F$21+Software!$F$34)/AnalysisTerm+(1-MIN(SUM($E59:L59),1))*(Software!$F$18+Software!$F$30)/AnalysisTerm)*(1+Growth)^L$84*(1+Inflation)^K$84+Software!$F$10/AnalysisTerm,"") -> 138140.8 | M88: =IF(AnalysisTerm>$K$84,'ROI Results'!M37+(MIN(SUM($E59:M59),1)*(Software!$F$21+Software!$F$34)/AnalysisTerm+(1-MIN(SUM($E59:M59),1))*(Software!$F$18+Software!$F$30)/AnalysisTerm)*(1+Growth)^M$84*(1+Inflation)^L$84+Software!$F$10/AnalysisTerm,"") -> 138140.8 | N88: =IF(AnalysisTerm>$K$84,'ROI Results'!N37+(MIN(SUM($E59:N59),1)*(Software!$F$21+Software!$F$34)/AnalysisTerm+(1-MIN(SUM($E59:N59),1))*(Software!$F$18+Software!$F$30)/AnalysisTerm)*(1+Growth)^N$84*(1+Inflation)^M$84+Software!$F$10/AnalysisTerm,"") -> 138140.8 | O88: =SUM(E88:N88) -> 8881408 | Q88: <-- growth and inflation not applied to VMware SW, otherwise growth applied in all years, inflation applied year 2+
B89: =B60 -> Facilities | C89: n/a | D89: =Facilities!F21 -> 7763470 | E89: =(MIN(SUM($E60:E60),1)*$D89/AnalysisTerm+(1-MIN(SUM($E60:E60),1))*$D75/AnalysisTerm)*(1+Growth/2) -> 2315956.2 | F89: =((MIN(SUM($E60:F60),1)*$D89/AnalysisTerm+(1-MIN(SUM($E60:F60),1))*$D75/AnalysisTerm)*(1+Growth/2)*(1+Growth))*(1+Inflation)^1 -> 2322029.2 | G89: =((MIN(SUM($E60:G60),1)*$D89/AnalysisTerm+(1-MIN(SUM($E60:G60),1))*$D75/AnalysisTerm)*(1+Growth/2)*(1+Growth)^2)*(1+Inflation)^2 -> 2313708.9 | H89: =IF(AnalysisTerm>3,((MIN(SUM($E60:H60),1)*$D89/AnalysisTerm+(1-MIN(SUM($E60:H60),1))*$D75/AnalysisTerm)*(1+Growth/2)*(1+Growth)^3)*(1+Inflation)^3,"") -> 2288608.9 | I89: =IF(AnalysisTerm>3,((MIN(SUM($E60:I60),1)*$D89/AnalysisTerm+(1-MIN(SUM($E60:I60),1))*$D75/AnalysisTerm)*(1+Growth/2)*(1+Growth)^4)*(1+Inflation)^4,"") -> 2244049.5 | J89: =IF(AnalysisTerm>$I$84,((MIN(SUM($E60:J60),1)*$D89/AnalysisTerm+(1-MIN(SUM($E60:J60),1))*$D75/AnalysisTerm)*(1+Growth/2)*(1+Growth)^J$84)*(1+Inflation)^I$84,"") -> 2285876.5 | K89: =IF(AnalysisTerm>$I$84,((MIN(SUM($E60:K60),1)*$D89/AnalysisTerm+(1-MIN(SUM($E60:K60),1))*$D75/AnalysisTerm)*(1+Growth/2)*(1+Growth)^K$84)*(1+Inflation)^J$84,"") -> 2188379.1 | L89: =IF(AnalysisTerm>$K$84,((MIN(SUM($E60:L60),1)*$D89/AnalysisTerm+(1-MIN(SUM($E60:L60),1))*$D75/AnalysisTerm)*(1+Growth/2)*(1+Growth)^L$84)*(1+Inflation)^K$84,"") -> 2059806.3 | M89: =IF(AnalysisTerm>$K$84,((MIN(SUM($E60:M60),1)*$D89/AnalysisTerm+(1-MIN(SUM($E60:M60),1))*$D75/AnalysisTerm)*(1+Growth/2)*(1+Growth)^M$84)*(1+Inflation)^L$84,"") -> 1895740.3 | N89: =IF(AnalysisTerm>$K$84,((MIN(SUM($E60:N60),1)*$D89/AnalysisTerm+(1-MIN(SUM($E60:N60),1))*$D75/AnalysisTerm)*(1+Growth/2)*(1+Growth)^N$84)*(1+Inflation)^M$84,"") -> 1691249.8 | O89: =SUM(E89:N89) -> 21605405 | Q89: <-- growth applied in all years, but only 50% of growth in year 1, inflation applied year 2+
B90: =B61 -> Labor | C90: n/a | D90: =Labor!F128 -> 23764409 | E90: =(MIN(SUM($E61:E61),1)*$D90/AnalysisTerm+(1-MIN(SUM($E61:E61),1))*$D76/AnalysisTerm)*(1+Growth/2) -> 4372744.5 | F90: =((MIN(SUM($E61:F61),1)*$D90/AnalysisTerm+(1-MIN(SUM($E61:F61),1))*$D76/AnalysisTerm)*(1+Growth/2)*(1+Growth))*(1+Inflation)^1 -> 4496373.3 | G90: =((MIN(SUM($E61:G61),1)*$D90/AnalysisTerm+(1-MIN(SUM($E61:G61),1))*$D76/AnalysisTerm)*(1+Growth/2)*(1+Growth)^2)*(1+Inflation)^2 -> 4611108.7 | H90: =IF(AnalysisTerm>3,((MIN(SUM($E61:H61),1)*$D90/AnalysisTerm+(1-MIN(SUM($E61:H61),1))*$D76/AnalysisTerm)*(1+Growth/2)*(1+Growth)^3)*(1+Inflation)^3,"") -> 4714679.9 | I90: =IF(AnalysisTerm>3,((MIN(SUM($E61:I61),1)*$D90/AnalysisTerm+(1-MIN(SUM($E61:I61),1))*$D76/AnalysisTerm)*(1+Growth/2)*(1+Growth)^4)*(1+Inflation)^4,"") -> 4804505.1 | J90: =IF(AnalysisTerm>$I$84,((MIN(SUM($E61:J61),1)*$D90/AnalysisTerm+(1-MIN(SUM($E61:J61),1))*$D76/AnalysisTerm)*(1+Growth/2)*(1+Growth)^J$84)*(1+Inflation)^I$84,"") -> 5121538.5 | K90: =IF(AnalysisTerm>$I$84,((MIN(SUM($E61:K61),1)*$D90/AnalysisTerm+(1-MIN(SUM($E61:K61),1))*$D76/AnalysisTerm)*(1+Growth/2)*(1+Growth)^K$84)*(1+Inflation)^J$84,"") -> 5177358 | L90: =IF(AnalysisTerm>$K$84,((MIN(SUM($E61:L61),1)*$D90/AnalysisTerm+(1-MIN(SUM($E61:L61),1))*$D76/AnalysisTerm)*(1+Growth/2)*(1+Growth)^L$84)*(1+Inflation)^K$84,"") -> 5208257.5 | M90: =IF(AnalysisTerm>$K$84,((MIN(SUM($E61:M61),1)*$D90/AnalysisTerm+(1-MIN(SUM($E61:M61),1))*$D76/AnalysisTerm)*(1+Growth/2)*(1+Growth)^M$84)*(1+Inflation)^L$84,"") -> 5209804.3 | N90: =IF(AnalysisTerm>$K$84,((MIN(SUM($E61:N61),1)*$D90/AnalysisTerm+(1-MIN(SUM($E61:N61),1))*$D76/AnalysisTerm)*(1+Growth/2)*(1+Growth)^N$84)*(1+Inflation)^M$84,"") -> 5177008.8 | O90: =SUM(E90:N90) -> 48893379 | Q90: <-- growth applied in all years, but only 50% of growth in year 1, inflation applied year 2+
B91: =B62 -> Support | C91: n/a | D91: ='ROI Results'!O40+Support!F10 -> 1375000 | E91: =MIN(SUM($E62:E62),1)*$D91/AnalysisTerm+(1-MIN(SUM($E62:E62),1))*$D77/AnalysisTerm -> 137500 | F91: =MIN(SUM($E62:F62),1)*$D91/AnalysisTerm+(1-MIN(SUM($E62:F62),1))*$D77/AnalysisTerm -> 137500 | G91: =MIN(SUM($E62:G62),1)*$D91/AnalysisTerm+(1-MIN(SUM($E62:G62),1))*$D77/AnalysisTerm -> 137500 | H91: =IF(AnalysisTerm>3,MIN(SUM($E62:H62),1)*$D91/AnalysisTerm+(1-MIN(SUM($E62:H62),1))*$D77/AnalysisTerm,"") -> 137500 | I91: =IF(AnalysisTerm>3,MIN(SUM($E62:I62),1)*$D91/AnalysisTerm+(1-MIN(SUM($E62:I62),1))*$D77/AnalysisTerm,"") -> 137500 | J91: =IF(AnalysisTerm>5,MIN(SUM($E62:J62),1)*$D91/AnalysisTerm+(1-MIN(SUM($E62:J62),1))*$D77/AnalysisTerm,"") -> 137500 | K91: =IF(AnalysisTerm>5,MIN(SUM($E62:K62),1)*$D91/AnalysisTerm+(1-MIN(SUM($E62:K62),1))*$D77/AnalysisTerm,"") -> 137500 | L91: =IF(AnalysisTerm>$K$84,MIN(SUM($E62:L62),1)*$D91/AnalysisTerm+(1-MIN(SUM($E62:L62),1))*$D77/AnalysisTerm,"") -> 137500 | M91: =IF(AnalysisTerm>$K$84,MIN(SUM($E62:M62),1)*$D91/AnalysisTerm+(1-MIN(SUM($E62:M62),1))*$D77/AnalysisTerm,"") -> 137500 | N91: =IF(AnalysisTerm>$K$84,MIN(SUM($E62:N62),1)*$D91/AnalysisTerm+(1-MIN(SUM($E62:N62),1))*$D77/AnalysisTerm,"") -> 137500 | O91: =SUM(E91:N91) -> 1375000 | Q91: <-- growth and inflation NOT applied to VMware Support
B92: =B63 -> Migration | C92: =MAX('Migration - Reskilling'!F14,O38) -> 1218750 | D92: n/a | E92: =IF('Migration - Reskilling'!$F$14>$O$38,E63*$C92*(1+Growth/2),E38) -> 124921.87 | F92: =IF('Migration - Reskilling'!$F$14>$O$38,F63*$C92*(1+Growth/2)*(1+Growth)*(1+Inflation)^1,F38) -> 135103.01 | G92: =IF('Migration - Reskilling'!$F$14>$O$38,G63*$C92*(1+Growth/2)*(1+Growth)^2*(1+Inflation)^2,G38) -> 146113.9 | H92: =IF(AnalysisTerm>3,IF('Migration - Reskilling'!$F$14>$O$38,H63*$C92*(1+Growth/2)*(1+Growth)^3*(1+Inflation)^3,H38),"") -> 158022.19 | I92: =IF(AnalysisTerm>3,IF('Migration - Reskilling'!$F$14>$O$38,I63*$C92*(1+Growth/2)*(1+Growth)^4*(1+Inflation)^4,I38),"") -> 170900.99 | J92: =IF(AnalysisTerm>5,IF('Migration - Reskilling'!$F$14>$O$38,J63*$C92*(1+Growth/2)*(1+Growth)^J$84*(1+Inflation)^I$84,J38),"") -> 194070.9 | K92: =IF(AnalysisTerm>5,IF('Migration - Reskilling'!$F$14>$O$38,K63*$C92*(1+Growth/2)*(1+Growth)^K$84*(1+Inflation)^J$84,K38),"") -> 209887.67 | L92: =IF(AnalysisTerm>7,IF('Migration - Reskilling'!$F$14>$O$38,L63*$C92*(1+Growth/2)*(1+Growth)^L$84*(1+Inflation)^K$84,L38),"") -> 226993.52 | M92: =IF(AnalysisTerm>7,IF('Migration - Reskilling'!$F$14>$O$38,M63*$C92*(1+Growth/2)*(1+Growth)^M$84*(1+Inflation)^L$84,M38),"") -> 245493.49 | N92: =IF(AnalysisTerm>7,IF('Migration - Reskilling'!$F$14>$O$38,N63*$C92*(1+Growth/2)*(1+Growth)^N$84*(1+Inflation)^M$84,N38),"") -> 265501.21 | O92: =SUM(E92:N92) -> 1877008.8 | Q92: <-- growth applied in all years, but only 50% of growth in year 1, inflation applied year 2+, and NEITHER applied to migration if PS > calculated migration
B93: =B64 -> One-time Reskilling | C93: n/a | D93: =MAX('Migration - Reskilling'!F29,O39) -> 156000 | E93: =IF('Migration - Reskilling'!$F$29>$O$39,$D$93*E64,E39) -> 156000 | F93: =IF('Migration - Reskilling'!$F$29>$O$39,$D$93*F64,F39) -> 0 | G93: =IF('Migration - Reskilling'!$F$29>$O$39,$D$93*G64,G39) -> 0 | H93: =IF(AnalysisTerm>3,IF('Migration - Reskilling'!$F$29>$O$39,$D$93*H64,H39),"") -> 0 | I93: =IF(AnalysisTerm>3,IF('Migration - Reskilling'!$F$29>$O$39,$D$93*I64,I39),"") -> 0 | J93: =IF(AnalysisTerm>5,IF('Migration - Reskilling'!$F$29>$O$39,$D$93*J64,J39),"") -> 0 | K93: =IF(AnalysisTerm>5,IF('Migration - Reskilling'!$F$29>$O$39,$D$93*K64,K39),"") -> 0 | L93: =IF(AnalysisTerm>$K$84,IF('Migration - Reskilling'!$F$29>$O$39,$D$93*L64,L39),"") -> 0 | M93: =IF(AnalysisTerm>$K$84,IF('Migration - Reskilling'!$F$29>$O$39,$D$93*M64,M39),"") -> 0 | N93: =IF(AnalysisTerm>$K$84,IF('Migration - Reskilling'!$F$29>$O$39,$D$93*N64,N39),"") -> 0 | O93: =SUM(E93:N93) -> 156000 | Q93: <-- growth and inflation NOT applied to reskilling
B94: =B65 -> Revenue Impact | C94: n/a | D94: ='Business impact'!F19+'Business impact'!F34 -> 0 | E94: =$D$94*E65 -> 0 | F94: =$D$94*F65 -> 0 | G94: =$D$94*G65 -> 0 | H94: =IF(AnalysisTerm>3,$D$94*H65,"") -> 0 | I94: =IF(AnalysisTerm>3,$D$94*I65,"") -> 0 | J94: =IF(AnalysisTerm>5,$D$94*J65,"") -> 0 | K94: =IF(AnalysisTerm>5,$D$94*K65,"") -> 0 | L94: =IF(AnalysisTerm>$K$84,$D$94*L65,"") -> 0 | M94: =IF(AnalysisTerm>$K$84,$D$94*M65,"") -> 0 | N94: =IF(AnalysisTerm>$K$84,$D$94*N65,"") -> 0 | O94: =SUM(E94:N94) -> 0
B95: =B66 -> Risk Reduction | C95: n/a | D95: ='Business impact'!F54+'Business impact'!F65+'Business impact'!F77 -> 0 | E95: =$D$95*E66 -> 0 | F95: =$D$95*F66 -> 0 | G95: =$D$95*G66 -> 0 | H95: =IF(AnalysisTerm>3,$D$95*H66,"") -> 0 | I95: =IF(AnalysisTerm>3,$D$95*I66,"") -> 0 | J95: =IF(AnalysisTerm>5,$D$95*J66,"") -> 0 | K95: =IF(AnalysisTerm>5,$D$95*K66,"") -> 0 | L95: =IF(AnalysisTerm>$K$84,$D$95*L66,"") -> 0 | M95: =IF(AnalysisTerm>$K$84,$D$95*M66,"") -> 0 | N95: =IF(AnalysisTerm>$K$84,$D$95*N66,"") -> 0 | O95: =SUM(E95:N95) -> 0
B98: Estimated VM / Host Count by Year
I99: =IF(AnalysisTerm<=3,"hide column","show column") -> show column | J99: =IF(AnalysisTerm<=4,"hide column","show column") -> show column | K99: =K$54 -> show column | L99: =L$54 -> show column | M99: =M$54 -> show column | N99: =N$54 -> show column
E100: Year 1 (start) | F100: Year 1 (end) | G100: Year 2 (end) | H100: Year 3 (end) | I100: =IF(AnalysisTerm>3,"Year 4 (end)","") -> Year 4 (end) | J100: =IF(AnalysisTerm>3,"Year 5 (end)","") -> Year 5 (end) | K100: =IF(AnalysisTerm>5,"Year 6 (end)","") -> Year 6 (end) | L100: =IF(AnalysisTerm>5,"Year 7 (end)","") -> Year 7 (end) | M100: =IF(AnalysisTerm>7,"Year 8 (end)","") -> Year 8 (end) | N100: =IF(AnalysisTerm>7,"Year 9 (end)","") -> Year 9 (end) | O100: =IF(AnalysisTerm>7,"Year 10 (end)","") -> Year 10 (end)
B101: ="Total VMs "&IF(Compute!D68="yes","(including P2V)","") -> Total VMs (including P2V) | E101: =VMs -> 5000 | F101: =VMs*(1-Compute!$F$14)*(1+Growth)^1+IF(Compute!$D$68="Yes",Compute!$F$73*(1+Growth)^1,0)*MIN(1,SUM($E$56:E56)) -> 4725 | G101: =VMs*(1-Compute!$F$14)*(1+Growth)^2+IF(Compute!$D$68="Yes",Compute!$F$73*(1+Growth)^2,0)*MIN(1,SUM($E$56:F56)) -> 4961.25 | H101: =VMs*(1-Compute!$F$14)*(1+Growth)^3+IF(Compute!$D$68="Yes",Compute!$F$73*(1+Growth)^3,0)*MIN(1,SUM($E$56:G56)) -> 5209.3125 | I101: =IF(AnalysisTerm>3,VMs*(1-Compute!$F$14)*(1+Growth)^4+IF(Compute!$D$68="Yes",Compute!$F$73*(1+Growth)^4,0)*MIN(1,SUM($E$56:H56)),"") -> 5469.7781 | J101: =IF(AnalysisTerm>3,VMs*(1-Compute!$F$14)*(1+Growth)^5+IF(Compute!$D$68="Yes",Compute!$F$73*(1+Growth)^5,0)*MIN(1,SUM($E$56:I56)),"") -> 5743.267 | K101: =IF(AnalysisTerm>5,VMs*(1-Compute!$F$14)*(1+Growth)^6+IF(Compute!$D$68="Yes",Compute!$F$73*(1+Growth)^6,0)*MIN(1,SUM($E$56:J56)),"") -> 6030.4304 | L101: =IF(AnalysisTerm>5,VMs*(1-Compute!$F$14)*(1+Growth)^7+IF(Compute!$D$68="Yes",Compute!$F$73*(1+Growth)^7,0)*MIN(1,SUM($E$56:K56)),"") -> 6331.9519 | M101: =IF(AnalysisTerm>7,VMs*(1-Compute!$F$14)*(1+Growth)^8+IF(Compute!$D$68="Yes",Compute!$F$73*(1+Growth)^8,0)*MIN(1,SUM($E$56:L56)),"") -> 6648.5495 | N101: =IF(AnalysisTerm>7,VMs*(1-Compute!$F$14)*(1+Growth)^9+IF(Compute!$D$68="Yes",Compute!$F$73*(1+Growth)^9,0)*MIN(1,SUM($E$56:M56)),"") -> 6980.977 | O101: =IF(AnalysisTerm>7,VMs*(1-Compute!$F$14)*(1+Growth)^10+IF(Compute!$D$68="Yes",Compute!$F$73*(1+Growth)^10,0)*MIN(1,SUM($E$56:N56)),"") -> 7330.0258
B102: ="VM Hosts - on prem "&IF(Compute!D68="yes","(including P2V hosts)","") -> VM Hosts - on prem (including P2V hosts) | E102: =Hosts -> 400 | F102: =VMs*(1+Growth)^1*(1-Compute!$F$14)/ROUND($E$103+(Misc!$C$130-$E$103)*MIN(1,SUM($E$56:E56)),1)+IF(Compute!$D$68="Yes",Misc!$C$131*MIN(1,SUM($E$56:E56))*(1+Growth)^1,0) -> 328.125 | G102: =VMs*(1+Growth)^2*(1-Compute!$F$14)/ROUND($E$103+(Misc!$C$130-$E$103)*MIN(1,SUM($E$56:F56)),1)+IF(Compute!$D$68="Yes",Misc!$C$131*MIN(1,SUM($E$56:F56))*(1+Growth)^2,0) -> 304.37117 | H102: =VMs*(1+Growth)^3*(1-Compute!$F$14)/ROUND($E$103+(Misc!$C$130-$E$103)*MIN(1,SUM($E$56:G56)),1)+IF(Compute!$D$68="Yes",Misc!$C$131*MIN(1,SUM($E$56:G56))*(1+Growth)^3,0) -> 286.22596 | I102: =IF(AnalysisTerm>3,VMs*(1+Growth)^4*(1-Compute!$F$14)/ROUND($E$103+(Misc!$C$130-$E$103)*MIN(1,SUM($E$56:H56)),1)+IF(Compute!$D$68="Yes",Misc!$C$131*MIN(1,SUM($E$56:H56))*(1+Growth)^4,0),"") -> 272.12826 | J102: =IF(AnalysisTerm>3,VMs*(1+Growth)^5*(1-Compute!$F$14)/ROUND($E$103+(Misc!$C$130-$E$103)*MIN(1,SUM($E$56:I56)),1)+IF(Compute!$D$68="Yes",Misc!$C$131*MIN(1,SUM($E$56:I56))*(1+Growth)^5,0),"") -> 261.05759 | K102: =IF(AnalysisTerm>5,VMs*(1+Growth)^6*(1-Compute!$F$14)/ROUND($E$103+(Misc!$C$130-$E$103)*MIN(1,SUM($E$56:J56)),1)+IF(Compute!$D$68="Yes",Misc!$C$131*MIN(1,SUM($E$56:J56))*(1+Growth)^6,0),"") -> 252.31926 | L102: =IF(AnalysisTerm>5,VMs*(1+Growth)^7*(1-Compute!$F$14)/ROUND($E$103+(Misc!$C$130-$E$103)*MIN(1,SUM($E$56:K56)),1)+IF(Compute!$D$68="Yes",Misc!$C$131*MIN(1,SUM($E$56:K56))*(1+Growth)^7,0),"") -> 245.42449 | M102: =IF(AnalysisTerm>7,VMs*(1+Growth)^8*(1-Compute!$F$14)/ROUND($E$103+(Misc!$C$130-$E$103)*MIN(1,SUM($E$56:L56)),1)+IF(Compute!$D$68="Yes",Misc!$C$131*MIN(1,SUM($E$56:L56))*(1+Growth)^8,0),"") -> 240.01984 | N102: =IF(AnalysisTerm>7,VMs*(1+Growth)^9*(1-Compute!$F$14)/ROUND($E$103+(Misc!$C$130-$E$103)*MIN(1,SUM($E$56:M56)),1)+IF(Compute!$D$68="Yes",Misc!$C$131*MIN(1,SUM($E$56:M56))*(1+Growth)^9,0),"") -> 235.84382 | O102: =IF(AnalysisTerm>7,VMs*(1+Growth)^10*(1-Compute!$F$14)/ROUND($E$103+(Misc!$C$130-$E$103)*MIN(1,SUM($E$56:N56)),1)+IF(Compute!$D$68="Yes",Misc!$C$131*MIN(1,SUM($E$56:N56))*(1+Growth)^10,0),"") -> 232.69923
B103: ="Consolidation Ratio - on prem "&IF(Compute!D68="yes","(weighted average with P2V)","") -> Consolidation Ratio - on prem (weighted average with P2V) | E103: =E101/E102 -> 12.5 | F103: =F101/F102 -> 14.4 | G103: =G101/G102 -> 16.3 | H103: =H101/H102 -> 18.2 | I103: =IF(AnalysisTerm>3,I101/I102,"") -> 20.1 | J103: =IF(AnalysisTerm>3,J101/J102,"") -> 22 | K103: =IF(AnalysisTerm>5,K101/K102,"") -> 23.9 | L103: =IF(AnalysisTerm>5,L101/L102,"") -> 25.8 | M103: =IF(AnalysisTerm>7,M101/M102,"") -> 27.7 | N103: =IF(AnalysisTerm>7,N101/N102,"") -> 29.6 | O103: =IF(AnalysisTerm>7,O101/O102,"") -> 31.5
B105: Payback Calculation | P105: This can be buried somewhere else
B107: Payback estimation calcs | E107: Year 1 | F107: Year 2 | G107: Year 3 | H107: Year 4 | I107: Year 5 | J107: =$J$13 -> 6 | K107: =K$13 -> 7 | L107: =L$13 -> 8 | M107: =M$13 -> 9 | N107: =N$13 -> 10
B108: cumulative net benefit | E108: =E16 -> 1395663 | F108: =F16+E108 -> 4881969 | G108: =G16+F108 -> 9362346 | H108: =H16+G108 -> 14971251 | I108: =I16+H108 -> 21858665 | J108: =J16+I108 -> 32002993 | K108: =K16+J108 -> 43822976 | L108: =L16+K108 -> 43822976 | M108: =M16+L108 -> 43822976 | N108: =N16+M108 -> 43822976
B109: is cumulative positive | E109: =IF(E108<0,0,1) -> 1 | F109: =IF(F108<0,0,1) -> 1 | G109: =IF(G108<0,0,1) -> 1 | H109: =IF(H108<0,0,1) -> 1 | I109: =IF(I108<0,0,1) -> 1 | J109: =IF(J108<0,0,1) -> 1 | K109: =IF(K108<0,0,1) -> 1 | L109: =IF(L108<0,0,1) -> 1 | ... N109: =IF(N108<0,0,1) -> 1
B110: in which year did cumulative become positive | E110: =IF(E109=1,1,0) -> 1 | F110: =IF(F109=1,1+E110,0) -> 2 | G110: =IF(G109=1,1+F110,0) -> 3 | H110: =IF(H109=1,1+G110,0) -> 4 | I110: =IF(I109=1,1+H110,0) -> 5 | J110: =IF(J109=1,1+I110,0) -> 6 | K110: =IF(K109=1,1+J110,0) -> 7 | L110: =IF(L109=1,1+K110,0) -> 8 | M110: =IF(M109=1,1+L110,0) -> 9 | N110: =IF(N109=1,1+M110,0) -> 10
B111: Amount cumulative benefit is greater than cumulative cost over in year benefit | E111: =(1-E108/E32) -> 0.66334384 | F111: =(1-F108/F32) -> 0.049517494 | G111: =(1-G108/G32) -> -0.52720559 | H111: =(1-H108/H32) -> -1.0624669 | I111: =(1-I108/I32) -> -1.5603379 | J111: =(1-J108/J32) -> -2.1547672 | K111: =(1-K108/K32) -> -2.7075329 | L111: =(1-L108/L32) -> -2.2290898 | ... N111: =(1-N108/N32) -> -1.4229838
B112: Initial months w/ zero value | E112: =(1-SUMPRODUCT('ROI Results'!E56:E66,'ROI Results'!E21:E31)/'ROI Results'!E32)*12 -> 10.779159
B113: (1-Amount cum benefit is greater than cum cost / in year benefit) * (months with value) | E113: =(1-E108/E32)*(12-E112)+E112 -> 11.588996 | F113: =(1-F108/F32)*(12-F112)+F112 -> 0.59420992 | G113: =(1-G108/G32)*(12-G112)+G112 -> -6.326467 | H113: =(1-H108/H32)*(12-H112)+H112 -> -12.749602 | I113: =(1-I108/I32)*(12-I112)+I112 -> -18.724055 | J113: =(1-J108/J32)*(12-J112)+J112 -> -25.857206 | K113: =(1-K108/K32)*(12-K112)+K112 -> -32.490395 | L113: =(1-L108/L32)*(12-L112)+L112 -> -26.749078 | ... N113: =(1-N108/N32)*(12-N112)+N112 -> -17.075805
...

Sheet Sustainability
B2: ="Projected Sustainability Benefit Over "&AnalysisTerm&" Years" -> Projected Sustainability Benefit Over 10 Years
B3: Reduced Power Consumption (in MWh) | C3: =C50 -> 17787.484
B4: CO2 emission avoided (Metric Tons) | C4: =ROUND(C3*C12,0) -> 9819
B5: Motor Vehicles off Road | C5: =ROUNDUP(C4/C18,0) -> 2116
B6: Urban Planted Trees (allowed to grow 10 years) | C6: =ROUNDUP(C4/C22,0) -> 163650
B8: Green House Gas Assumptions
B9: Carbon Emission from Datacenter Servers | N9: Sourcing and Comments
B10: Marginal Operating Emissions Rate (MOER in CO2 Pounds per MWh) | C10: =ROUND(1217.44,2) -> 1217.44 | N10: Represents the emissions rate of the electricity generator(s) which are responding to changes in load on the local grid at a certain time. Based on world average from : https://www.watttime.org/
B11: Metric tons per pound | C11: =ROUND(2204.6,2) -> 2204.6 | N11: Ratio of metric tons per pound
B12: CO2 MT per MWh | C12: =ROUND(C10/C11,3) -> 0.552 | N12: Calculation, https://www.epa.gov/energy/greenhouse-gases-equivalencies-calculator-calculations-and-references
B13: Carbon Emission from gasoline powered cars
B14: CO2 emissions ratio for passenger vehicles | C14: =ROUND(0.994,3) -> 0.994 | N14: CO2 emissions to total greenhouse gas emissions (including carbon dioxide, methane, and nitrous oxide, all expressed as carbon dioxide equivalents)
B15: Average motor vehicle miles traveled per year | C15: =ROUND(11520,0) -> 11520 | N15: Placeholder estimate from FHWA 2020
B16: Carbon dioxide emitted per gallon of motor gasoline (Metric Tons) | C16: =ROUND(0.00889,5) -> 0.00889 | N16: Placeholder estimate from FHWA 2020
B17: Number of Miles per Gallon for motor vehicles | C17: =ROUND(22.2,2) -> 22.2 | N17: Placeholder estimate from FHWA 2020
B18: Metric Ton CO2 Equivalent per Vehicle per year | C18: =ROUND(C16*C15/(C14*C17),3) -> 4.641 | N18: Calculation, https://www.epa.gov/energy/greenhouse-gases-equivalencies-calculator-calculations-and-references
B19: Carbon Sequestered by Urban Planted Trees allowed to grow 10 years
B20: Carbon Sequestered per tree (lbs C/tree) | C20: =ROUND(36.4,2) -> 36.4 | N20: https://www.epa.gov/energy/greenhouse-gases-equivalencies-calculator-calculations-and-references
B21: Carbon Dioxide (CO2) Sequestered per tree (MT per pound) | C21: =ROUND((44/12)*1/C11,5) -> 0.00166 | N21: Calculation, Ratio of the molecular weight of carbon dioxide to carbon = (44/12)
B22: Metric Ton CO2 per Urban Planted Tree | C22: =ROUND(C20*C21,3) -> 0.06 | N22: Calculation, https://www.epa.gov/energy/greenhouse-gases-equivalencies-calculator-calculations-and-references
B24: Power & Cooling Requirements
B25: Power Consumption by Hardware Component Type | C25: Annual | N25: Sourcing and Comments
B26: Physical Host (kWh) | C26: =Facilities!F32 -> 12584 | N26: From Facilites
B27: Physical legacy servers | C27: =Facilities!F33 -> 5808 | N27: From Facilites
B28: Load balancer (kWh) | C28: =Facilities!F35 -> 5808 | N28: From Facilites
B29: Firewall (kWh) | C29: =Facilities!F34 -> 5808 | N29: From Facilites
B31: Quantity of each Hardware Component | C31: Current State | D31: Future State | N31: Sourcing and Comments
B32: Number of VM Hosts (On-Prem) | C32: ='Excel Output'!D23 -> 400 | D32: =Facilities!F15 -> 143 | N32: From Compute
B33: Number of Physical legacy servers | C33: =Compute!F73 -> 0 | D33: 0 | N33: From Compute
B34: Number of Load balancers | C34: =Network!F26 -> 0 | D34: =Network!F32 -> 0 | N34: From Network
B35: Number of Firewalls | C35: =Network!F48 -> 0 | D35: =Network!F54 -> 0 | N35: From Network
B36: Total Annual Power & Cooling Requirement in Kwh | C36: =SUMPRODUCT(C32:C35,$C$26:$C$29) -> 5033600 | D36: =SUMPRODUCT(D32:D35,$C$26:$C$29) -> 1799512 | N36: Calculation
F37: =IF(AnalysisTerm=3,"Hide","Show") -> Show | G37: =IF(AnalysisTerm=3,"Hide","Show") -> Show | H37: =IF(AnalysisTerm<=5,"hide","show ") -> show | I37: =IF(AnalysisTerm<=5,"hide","show") -> show | J37: =IF(AnalysisTerm<=7,"hide","show") -> show | K37: =IF(AnalysisTerm<=7,"hide","show") -> show | L37: =IF(AnalysisTerm<=7,"hide","show") -> show
B38: Incremental Migration by year
C39: Year 1 | D39: Year 2 | E39: Year 3 | F39: =IF(AnalysisTerm>3,"Year 4","") -> Year 4 | G39: =IF(AnalysisTerm>3,"Year 5","") -> Year 5 | H39: =IF(AnalysisTerm>5,6,"") -> 6 | I39: =IF(AnalysisTerm>6,7,"") -> 7 | J39: =IF(AnalysisTerm>7,8,"") -> 8 | K39: =IF(AnalysisTerm>7,9,"") -> 9 | L39: =IF(AnalysisTerm>7,10,"") -> 10 | N39: Sourcing and Comments
B40: VM Host Server HW | C40: ='ROI Results'!E$56 -> 0.1 | D40: ='ROI Results'!F$56 -> 0.1 | E40: ='ROI Results'!G$56 -> 0.1 | F40: ='ROI Results'!H$56 -> 0.1 | G40: ='ROI Results'!I$56 -> 0.1 | H40: ='ROI Results'!J$56 -> 0.1 | I40: ='ROI Results'!K$56 -> 0.1 | J40: ='ROI Results'!L$56 -> 0.1 | ... L40: ='ROI Results'!N$56 -> 0.1 | N40: From ROI Results
B41: Physical Legacy Servers | C41: ='ROI Results'!E$56 -> 0.1 | D41: ='ROI Results'!F$56 -> 0.1 | E41: ='ROI Results'!G$56 -> 0.1 | F41: ='ROI Results'!H$56 -> 0.1 | G41: ='ROI Results'!I$56 -> 0.1 | H41: ='ROI Results'!J$56 -> 0.1 | I41: ='ROI Results'!K$56 -> 0.1 | J41: ='ROI Results'!L$56 -> 0.1 | ... L41: ='ROI Results'!N$56 -> 0.1 | N41: From ROI Results
B42: Load Balancer HW | C42: ='ROI Results'!E$58 -> 0.1 | D42: ='ROI Results'!F$58 -> 0.1 | E42: ='ROI Results'!G$58 -> 0.1 | F42: ='ROI Results'!H$58 -> 0.1 | G42: ='ROI Results'!I$58 -> 0.1 | H42: ='ROI Results'!J$58 -> 0.1 | I42: ='ROI Results'!K$58 -> 0.1 | J42: ='ROI Results'!L$58 -> 0.1 | ... L42: ='ROI Results'!N$58 -> 0.1 | N42: From ROI Results
B43: Firewall HW | C43: ='ROI Results'!E$58 -> 0.1 | D43: ='ROI Results'!F$58 -> 0.1 | E43: ='ROI Results'!G$58 -> 0.1 | F43: ='ROI Results'!H$58 -> 0.1 | G43: ='ROI Results'!I$58 -> 0.1 | H43: ='ROI Results'!J$58 -> 0.1 | I43: ='ROI Results'!K$58 -> 0.1 | J43: ='ROI Results'!L$58 -> 0.1 | ... L43: ='ROI Results'!N$58 -> 0.1 | N43: From ROI Results
B45: Total Power Consumption Savings by Hardware Component Type (in MWh)
B46: VM Host Server HW | C46: =(C32-D32)*C26*(IF(AnalysisTerm=3,SUMPRODUCT(C40:E40,{3,2,1}),IF(AnalysisTerm=5,SUMPRODUCT(C40:G40,{5,4,3,2,1}),IF(AnalysisTerm=7,SUMPRODUCT(C40:I40,{7,6,5,4,3,2,1}),SUMPRODUCT(C40:L40,{10,9,8,7,6,5,4,3,2,1}))))/1000) -> 17787.484
B47: Physical Legacy Servers | C47: =(C33-D33)*C27*(IF(AnalysisTerm=3,SUMPRODUCT(C41:E41,{3,2,1}),IF(AnalysisTerm=5,SUMPRODUCT(C41:G41,{5,4,3,2,1}),IF(AnalysisTerm=7,SUMPRODUCT(C41:I41,{7,6,5,4,3,2,1}),SUMPRODUCT(C41:L41,{10,9,8,7,6,5,4,3,2,1}))))/1000) -> 0
B48: Load Balancer HW | C48: =(C34-D34)*C28*(IF(AnalysisTerm=3,SUMPRODUCT(C42:E42,{3,2,1}),IF(AnalysisTerm=5,SUMPRODUCT(C42:G42,{5,4,3,2,1}),IF(AnalysisTerm=7,SUMPRODUCT(C42:I42,{7,6,5,4,3,2,1}),SUMPRODUCT(C42:L42,{10,9,8,7,6,5,4,3,2,1}))))/1000) -> 0
B49: Firewall HW | C49: =(C35-D35)*C29*(IF(AnalysisTerm=3,SUMPRODUCT(C43:E43,{3,2,1}),IF(AnalysisTerm=5,SUMPRODUCT(C43:G43,{5,4,3,2,1}),IF(AnalysisTerm=7,SUMPRODUCT(C43:I43,{7,6,5,4,3,2,1}),SUMPRODUCT(C43:L43,{10,9,8,7,6,5,4,3,2,1}))))/1000) -> 0
B50: Total | C50: =SUM(C46:C49) -> 17787.484

Sheet Transition
B2: Transition from Value Model to Competitive TCO Comparison
B3: When you choose to use both a value model and a competitive comparison, it's important to understand the transition between them. We utilize two distinct models for different purposes: the Value Model for calculating solution ROI, and the Competitive TCO Comparison Model for estimating end-state TCO against competitive solutions. This distinction is crucial to prevent confusion if the End-state TCO figures differ slightly from what you observed in the value model.
B4: You have to consider the results of the two models from different points of view.
B5: Value Model | D5: Competitive TCO Comparison
B6: ="The Value Model looks at actual costs and the value of "&'Initial Screens'!C13&" in the customers environment ramping over time taking into account adoption timeframes and investments." -> The Value Model looks at actual costs and the value of VCF 9 in the customers environment ramping over time taking into account adoption timeframes and investments. | D6: The Competitive TCO Comparison model compares an idealized end state TCO estimate (post adoption ramp) for the purposes of its comparison.
B7: The TCO shown on the next screen will be slightly different to account for the frame of reference shift of the competitive model. 1) When using the value model and comparison together your comparison model does not get to change configuration of server technology. 2) The software investment in the VCF Endstate will default to approximate list price for VCF and add-ons. Your approximate discount input in the prior screen will be used to estimate list. If you want to show discounts for Broadcom and the competition, please input those discounts in the Assumptions popup in the Competitive TCO Comparison module that follows. | E7: <-- If "VVF" or "VVF with vSAN", replace "VCF" as fit
B8: ='Initial Screens'!C13&" TCO Results Overview" -> VCF 9 TCO Results Overview
B10: Value Model | C10: Cost Categories | D10: Competitive TCO Comparison
B11: ='ROI Results'!O85 -> 27627724 | C11: Compute | D11: =Compute!F24+Compute!F86+Compute!F108*(1+AnalysisTerm*Compute!F111) -> 8937500
B12: ='ROI Results'!O86 -> 9458613.3 | C12: Storage | D12: =Storage!F34+Compute!F109*(1+AnalysisTerm*Compute!F111) -> 2940000
B13: ='ROI Results'!O87 -> 2743020.3 | C13: Network | D13: =Network!F19+Network!F34+Network!F56+Compute!F110*(1+AnalysisTerm*Compute!F111) -> 893750
B14: ='ROI Results'!O88 -> 8881408 | C14: Software | D14: =Software!F21+'ROI Results'!O37/(1-'ROI Results'!F34) -> 10000000
B15: ='ROI Results'!O89 -> 21605405 | C15: Facilities | D15: =Facilities!F21 -> 7763470
B16: ='ROI Results'!O90 -> 48893379 | C16: Labor | D16: =Labor!F128 -> 23764409
B17: ='ROI Results'!O40 -> 750000 | C17: Support | D17: ='ROI Results'!O40 -> 750000
B18: ='ROI Results'!O92 -> 1877008.8 | C18: Migration | D18: ='Migration - Reskilling'!F14 -> 1218750
B19: ='ROI Results'!O93 -> 156000 | C19: Reskilling | D19: ='Migration - Reskilling'!F29 -> 156000
